Workbook
Name _Toc135440555: 'Ante Proyecto Estructural'!#REF!
Name _Toc135440555: formulas!$AAB$4
Name type1: #REF!
Name type10: #REF!
Name type11: #REF!
Name type12: #REF!
Name type13: #REF!
Name type2: #REF!
Name type3: #REF!
Name type4: #REF!
Name type5: #REF!
Name type6: #REF!
Name type7: #REF!
Name type8: #REF!
Name type9: #REF!

Sheet Ante Proyecto Estructural
B4: Memoria Estructural | L4: Antecedentes Geológicos. | U4: Análisis Histórico | AD4: Analisis Por Viento: | BY4: VALOR DEL EXPONENTE X. | DD4: Opcion Seleccionada para Estructura | DM4: Analisis Dinamico de Estructura | EF4: claro maximo por momento | EN4: Bajando Cargas: | EW4: Análisis por elemento Finito | FF4: Análisis de Trabe Tipo como Continua Con Voladizo | GD4: Análisis de Trabe Tipo como Continua Arriostrada Parcialmente | GZ4: Analisis de Trabe Tipo como Continua Totalmente Arriostrada | IY4: Condiciones | KC4: Losas de Entrepiso Opción 1 Vigueta y Bovedilla
B5: Ampliacion de Recamara Principal de Villa en Palacio del mar | AD5: Debido a la incidencia de vientos de velocidad considerable asi como la pretendida utilización de materiales livianos debemos tener especial cuidado con el análisis de viento. | BY5: TOPOGRAFIA | CD5: VELOCIDAD DEL VIENTO MENOR DE 100 km/h | CH5: FL = N CL Vz^2 A | CP5: P rafa = | CQ5: =BZ29 -> 0.0048 | CR5: x | CS5: =CB29 -> 1 | CT5: x | CU5: =CD29 -> 127.29062 | CV5: ^2 = | CW5: =CQ5*CS5*(CU5^2) -> 77.773935 | DD5: Esquemático | EG5: Wb = 120 Fb KS / l1^2 | EN5: Área de Construccion | ES5: 36 | IJ5: 1 metro | IM5: Tension | IO5: Fy | IR5: Conecciones Concreto Acero | IY5: Analisis Eolico | KC5: =#REF! -> #REF!
B6: Dirección: | L6: Se verificaron datos geológicos de la zona. | U6: Se revisaron fotografías históricas para buscar indicios de movimientos o deslizamientos antiguos. Al menos en la historia fotográfica. | BY6: Terreno plano | CE6: 0.15 | CH6: FT = N CT Vz^2 A | CQ6: =CQ5 -> 0.0048 | CR6: =CR5 -> x | CS6: =CS5 -> 1 | CT6: =CT5 -> x | CU6: =CU5*0.8 -> 101.8325 | CV6: =CV5 -> ^2 = | CW6: =CQ6*CS6*(CU6^2) -> 49.775319 | DX6: Wux | EG6: Wb= Carga uniformemente repartida permisible | EN6: Capacidad de carca: | FF6: W= | FG6: =ES18+150 -> 585.4 | GD6: W= | GE6: =FG6 -> 585.4 | GZ6: W= | HA6: =GE6 -> 585.4 | IO6: 36000 | IP6: lbs-plg^2 | IY6: =CQ41 -> Se puede apreciar una convergencia de periodos de oscilacion en la direccion de viento en vortices de entre 3 a 4 segundos para velocidades que van de 5 a 132 km/hra. Esto equivale aproximadamente a elementos en voladizo (pendulos) de 2.2 a 4 metros por cuanto se debe tener cuidado de arriostrar los elementos adecuadamente a no mas de 1,5 metros entre arriostramiento. Los elementos que funcionen como verticales en la canceleria podrian ser una buena opcion para arriostrar los elementos en voladizo. En teoria se pudiera suponer que los canceles en si realizan estta funcion pero seria entonces vidrio quien resistiria la vibracion de la estructura lo cual no es recomendable.
B7: Km 50 Carretera Rosarito - Ensenada | BY7: Zonas accidentadas | CE7: 0.1 | CH7: A: Area Expuesta | CQ7: =CQ6 -> 0.0048 | CR7: =CR6 -> x | CS7: =CS6 -> 1 | CT7: =CT6 -> x | CU7: =CU5*0.6 -> 76.374375 | CV7: =CV6 -> ^2 = | CW7: =CQ7*CS7*(CU7^2) -> 27.998617 | DJ7: Trabes Principales | EG7: Fb = esfuerzo maximo permisible psi | EN7: Techumbre liviana | ES7: =DX15 -> 112 | ET7: =ES7 -> 112 | FF7: Ancho= | FG7: 3 | FJ7: momento puro en el claro | FL7: Atrib | FM7: 3 | FP7: momento puro en el claro | GD7: Ancho= | GE7: 3 | GH7: momento puro en el claro | GJ7: Atrib | GK7: 3 | GN7: momento puro en el claro | GZ7: =GD7 -> Ancho= | HA7: =GE7 -> 3 | HD7: momento puro en el claro | HF7: Atrib | HG7: 3 | HJ7: momento puro en el claro | HP7: momento puro en el claro | HV7: momento puro en el claro | IO7: =IO6/(2.2*2.54*2.54) -> 2536.3687 | IP7: kgs-cm^2 | IR7: Reaccion Maxima | IT7: F'c | IU7: Area Req | IV7: 20 x 20
AD8: Paralelamente se pretenden colocar amplios canceles por cuanto debemos conocer los esfuerzos a los que estos estaran sujetos a efecto de los vientos. | BY8: Centros de ciudades Zonas arboladas | CE8: 0.35 | CH8: VL y VT por tabla | CQ8: =CQ7 -> 0.0048 | CR8: =CR7 -> x | CS8: =CS7 -> 1 | CT8: =CT7 -> x | CU8: =CU5*0.4 -> 50.91625 | CV8: =CV7 -> ^2 = | CW8: =CQ8*CS8*(CU8^2) -> 12.44383 | EG8: KS = modulo de seccion en plg^3 | EN8: Techumbre | FF8: W16x40 | FG8: =40*3.28/2.2 -> 59.636364 | FK8: momentos generados en los nudos | FL8: A | FM8: B | FQ8: momentos generados en los nudos | FR8: A | FS8: B | GD8: W16x40 | GE8: =40*3.28/2.2 -> 59.636364 | GI8: momentos generados en los nudos | GJ8: A | GK8: B | GO8: momentos generados en los nudos | GP8: A | GQ8: B | GZ8: =GD8 -> W16x40 | HA8: =GE8 -> 59.636364 | HE8: momentos generados en los nudos | HF8: A | HG8: B | HK8: momentos generados en los nudos | HL8: A | HM8: B | HQ8: momentos generados en los nudos | HR8: A | HS8: B | HW8: momentos generados en los nudos | HX8: A | HY8: B | IR8: =FI28 -> 11367.361 | IT8: 200 | IU8: =IR8/IT8 -> 56.836807 | IV8: =20*20 -> 400 | IW8: pasa | KC8: =OV5 -> 0
CH9: Consideramos un Valor de 2 tanto para CL como para CT | CQ9: =CQ8 -> 0.0048 | CR9: =CR8 -> x | CS9: =CS8 -> 1 | CT9: =CT8 -> x | CU9: =CU5*0.2 -> 25.458125 | CV9: =CV8 -> ^2 = | CW9: =CQ9*CS9*(CU9^2) -> 3.1109574 | DJ9: Trabe Secundaria | EG9: l1 = claro entre apoyos | EN9: carga viva | ES9: 150 | ET9: kg | FF9: P.conc | FG9: =140+(31*3.28*3/2.2) -> 278.65455 | FJ9: Carga uniformemente Distribuida | FK9: =FG6*FG7 -> 1756.2 | FL9: =-1*(IF(FL24=0,0,IF(FK9=0,0,FK9*FL24*FL24/12))) -> -1317.15 | FM9: =FL9*-1 -> 1317.15 | FP9: Carga uniformemente Distribuida | FR9: =-1*(IF(FR24=0,0,IF(FQ9=0,0,FQ9*FR24*FR24/12))) -> 0 | FS9: =FR9*-1 -> 0 | GD9: =FF9 -> P.conc | GE9: =FG9 -> 278.65455 | GH9: Carga uniformemente Distribuida | GI9: =GE6*GE7 -> 1756.2 | GJ9: =-1*(IF(GJ24=0,0,IF(GI9=0,0,GI9*GJ24*GJ24/12))) -> -1317.15 | GK9: =GJ9*-1 -> 1317.15 | GN9: Carga uniformemente Distribuida | GO9: =GI9 -> 1756.2 | GP9: =-1*(IF(GP24=0,0,IF(GO9=0,0,GO9*GP24*GP24/12))) -> -1317.15 | GQ9: =GP9*-1 -> 1317.15 | GZ9: =GD9 -> P.conc | HA9: =GE9 -> 278.65455 | HD9: Carga uniformemente Distribuida | HE9: =HA6*HA7 -> 1756.2 | HF9: =-1*(IF(HF24=0,0,IF(HE9=0,0,HE9*HF24*HF24/12))) -> -146.35 | HG9: =HF9*-1 -> 146.35 | HJ9: Carga uniformemente Distribuida | HK9: =HE9 -> 1756.2 | HL9: =-1*(IF(HL24=0,0,IF(HK9=0,0,HK9*HL24*HL24/12))) -> -146.35 | HM9: =HL9*-1 -> 146.35 | HP9: Carga uniformemente Distribuida | HQ9: =HK9 -> 1756.2 | HR9: =-1*(IF(HR24=0,0,IF(HQ9=0,0,HQ9*HR24*HR24/12))) -> -146.35 | HS9: =HR9*-1 -> 146.35 | HV9: Carga uniformemente Distribuida | HW9: =HQ9 -> 1756.2 | HX9: =-1*(IF(HX24=0,0,IF(HW9=0,0,HW9*HX24*HX24/12))) -> -1317.15 | HY9: =HX9*-1 -> 1317.15
BY10: Vz = Vß X Z | CS10: presion | EG10: para triplay de 1" estructural | EN10: carga muerta | EP10: losa + acabados | ES10: =ET7+50 -> 162 | ET10: kg | FF10: Mmax= | FG10: =FH42 -> 8111.8909 | FJ10: Carga uniforme por peso prop | FK10: =FG8 -> 59.636364 | FL10: =-1*(IF(FL24=0,0,IF(FK10=0,0,FK10*FL24*FL24/12))) -> -44.727273 | FM10: =FL10*-1 -> 44.727273 | FP10: Carga uniforme por peso prop | FR10: =-1*(IF(FR24=0,0,IF(FQ10=0,0,FQ10*FR24*FR24/12))) -> 0 | FS10: =FR10*-1 -> 0 | GD10: Mmax= | GE10: =GF42 -> 1480.1955 | GH10: Carga uniforme por peso prop | GI10: =GE8 -> 59.636364 | GJ10: =-1*(IF(GJ24=0,0,IF(GI10=0,0,GI10*GJ24*GJ24/12))) -> -44.727273 | GK10: =GJ10*-1 -> 44.727273 | GN10: Carga uniforme por peso prop | GO10: =GI10 -> 59.636364 | GP10: =-1*(IF(GP24=0,0,IF(GO10=0,0,GO10*GP24*GP24/12))) -> -44.727273 | GQ10: =GP10*-1 -> 44.727273 | GZ10: Mmax= | HA10: =HB42 -> 1529.2334 | HD10: Carga uniforme por peso prop | HE10: =HA8 -> 59.636364 | HF10: =-1*(IF(HF24=0,0,IF(HE10=0,0,HE10*HF24*HF24/12))) -> -4.969697 | HG10: =HF10*-1 -> 4.969697 | HJ10: Carga uniforme por peso prop | HK10: =HE10 -> 59.636364 | HL10: =-1*(IF(HL24=0,0,IF(HK10=0,0,HK10*HL24*HL24/12))) -> -4.969697 | HM10: =HL10*-1 -> 4.969697 | HP10: Carga uniforme por peso prop | HQ10: =HK10 -> 59.636364 | HR10: =-1*(IF(HR24=0,0,IF(HQ10=0,0,HQ10*HR24*HR24/12))) -> -4.969697 | HS10: =HR10*-1 -> 4.969697 | HV10: Carga uniforme por peso prop | HW10: =HQ10 -> 59.636364 | HX10: =-1*(IF(HX24=0,0,IF(HW10=0,0,HW10*HX24*HX24/12))) -> -44.727273 | HY10: =HX10*-1 -> 44.727273 | IK10: Distancia | IR10: Debido a la configuracion de la estructura de soporte disenada como puente colgante se pretende que el unico esfuerzo que transmita a los apoyos sea cortante directo. Por lo tanto bastara con que se anclaran a columnas - castillo de 30 x 30 constuidas dentro del muro en los puntos de apoyo. Estos estaran armados con 4 varillas de 5/8" y varillas de 1/2" en los centros. estribos de 3/8" @ 15 cm. en anclaje se hara con las varillas sin doblar soldadas por lo menos en 4 ". El apoyo suplementario en la punta de viga palanca funcionara a tension, por cuanto se debera extremar cuidado en la coneccion. | KC10: Losas de Entrepiso Opción 2 Maciza
AD11: Análisis Estático | BY11: Vz = | BZ11: =BR42 -> 15.2352 | CA11: x | CB11: 2.5 | CC11: x | CD11: 0.35 | CE11: = | CF11: =BZ11*CB11*CD11 -> 13.3308 | CQ11: FL prom = | CR11: 0.0048 | CS11: 2 | CT11: =CU5 -> 127.29062 | CV11: =CF46 -> 6 | CW11: =CR11*CS11*(CT11^2)*CV11 -> 933.28723 | DJ11: Castillo Metálico | EG11: Fb = | EH11: 1110 | EI11: lbs/plg^3 | EN11: viento | ES11: =CF29 -> 77.773935 | ET11: kg | FF11: en kg/cm | FG11: =FG10*100 -> 811189.09 | FJ11: Distancia de nudo a carga puntual | FL11: =-1*(IF(FL24=0,0,IF(FK11=0,0,IF(FK12=0,0,IF(FK11=(FL24/2),FK12*FL24/8,FK12*FK11*((FL24-FK11)*(FL24-FK11))/(FL24*FL24)))))) -> 0 | FM11: =IF(FL24=0,0,IF(FK11=0,0,IF(FK12=0,0,IF(FK11=(FL24/2),FL11*-1,FK12*(FK11*FK11)*(FL24-FK11)/(FL24*FL24))))) -> 0 | FP11: Distancia de nudo a carga puntual | FR11: =-1*(IF(FR24=0,0,IF(FQ11=0,0,IF(FQ12=0,0,IF(FQ11=(FR24/2),FQ12*FR24/8,FQ12*FQ11*((FR24-FQ11)*(FR24-FQ11))/(FR24*FR24)))))) -> 0 | FS11: =IF(FR24=0,0,IF(FQ11=0,0,IF(FQ12=0,0,IF(FQ11=(FR24/2),FR11*-1,FQ12*(FQ11*FQ11)*(FR24-FQ11)/(FR24*FR24))))) -> 0 | GD11: en kg/cm | GE11: =GE10*100 -> 148019.55 | GH11: Distancia de nudo a carga puntual | GJ11: =-1*(IF(GJ24=0,0,IF(GI11=0,0,IF(GI12=0,0,IF(GI11=(GJ24/2),GI12*GJ24/8,GI12*GI11*((GJ24-GI11)*(GJ24-GI11))/(GJ24*GJ24)))))) -> 0 | GK11: =IF(GJ24=0,0,IF(GI11=0,0,IF(GI12=0,0,IF(GI11=(GJ24/2),GJ11*-1,GI12*(GI11*GI11)*(GJ24-GI11)/(GJ24*GJ24))))) -> 0 | GN11: Distancia de nudo a carga puntual | GP11: =-1*(IF(GP24=0,0,IF(GO11=0,0,IF(GO12=0,0,IF(GO11=(GP24/2),GO12*GP24/8,GO12*GO11*((GP24-GO11)*(GP24-GO11))/(GP24*GP24)))))) -> 0 | GQ11: =IF(GP24=0,0,IF(GO11=0,0,IF(GO12=0,0,IF(GO11=(GP24/2),GP11*-1,GO12*(GO11*GO11)*(GP24-GO11)/(GP24*GP24))))) -> 0 | GZ11: en kg/cm | HA11: =HA10*100 -> 152923.34 | HD11: Distancia de nudo a carga puntual | HE11: 0.1 | HF11: =-1*(IF(HF24=0,0,IF(HE11=0,0,IF(HE12=0,0,IF(HE11=(HF24/2),HE12*HF24/8,HE12*HE11*((HF24-HE11)*(HF24-HE11))/(HF24*HF24)))))) -> -22.571018 | HG11: =IF(HF24=0,0,IF(HE11=0,0,IF(HE12=0,0,IF(HE11=(HF24/2),HF11*-1,HE12*(HE11*HE11)*(HF24-HE11)/(HF24*HF24))))) -> 2.5078909 | HJ11: Distancia de nudo a carga puntual | HL11: =-1*(IF(HL24=0,0,IF(HK11=0,0,IF(HK12=0,0,IF(HK11=(HL24/2),HK12*HL24/8,HK12*HK11*((HL24-HK11)*(HL24-HK11))/(HL24*HL24)))))) -> 0 | HM11: =IF(HL24=0,0,IF(HK11=0,0,IF(HK12=0,0,IF(HK11=(HL24/2),HL11*-1,HK12*(HK11*HK11)*(HL24-HK11)/(HL24*HL24))))) -> 0 | HP11: Distancia de nudo a carga puntual | HQ11: =GB11 -> 0 | HR11: =-1*(IF(HR24=0,0,IF(HQ11=0,0,IF(HQ12=0,0,IF(HQ11=(HR24/2),HQ12*HR24/8,HQ12*HQ11*((HR24-HQ11)*(HR24-HQ11))/(HR24*HR24)))))) -> 0 | HS11: =IF(HR24=0,0,IF(HQ11=0,0,IF(HQ12=0,0,IF(HQ11=(HR24/2),HR11*-1,HQ12*(HQ11*HQ11)*(HR24-HQ11)/(HR24*HR24))))) -> 0 | HV11: Distancia de nudo a carga puntual | HX11: =-1*(IF(HX24=0,0,IF(HW11=0,0,IF(HW12=0,0,IF(HW11=(HX24/2),HW12*HX24/8,HW12*HW11*((HX24-HW11)*(HX24-HW11))/(HX24*HX24)))))) -> 0 | HY11: =IF(HX24=0,0,IF(HW11=0,0,IF(HW12=0,0,IF(HW11=(HX24/2),HX11*-1,HW12*(HW11*HW11)*(HX24-HW11)/(HX24*HX24))))) -> 0 | JH11: Muros Estructurales ME | KC11: =PQ31 -> 0
CR12: 0.0048 | CS12: 2 | CT12: =CU6 -> 101.8325 | CV12: 6 | CW12: =CR12*CS12*(CT12^2)*CV12 -> 597.30382 | DW12: Carga viva = | DX12: 150 | DY12: kg/m^2 | DZ12: =IF(DY12="kg/m^2",1,IF(DY12="lbs/pis^2",2,3)) -> 1 | EG12: KS = | EH12: 0.412 | EI12: plg^3 | EN12: lluvia | EP12: I cm | ES12: 2 | ET12: kg | FF12: Fy | FG12: 2500 | FJ12: Carga Puntual | FP12: Carga Puntual | GD12: Fy | GE12: 2500 | GH12: Carga Puntual | GN12: Carga Puntual | GZ12: Fy | HA12: 2500 | HD12: Carga Puntual | HE12: =HA9 -> 278.65455 | HJ12: Carga Puntual | HP12: Carga Puntual | HQ12: =GB12 -> 0 | HV12: Carga Puntual | IK12: Tensores | JH12: Armado con celdas coladas @3er celda Varilla vertical #4 , varilla longitudinal @ 2 hiladas amarrada a las varillas verticales. Block 1 Estos se colocaran en todos los laterales de la planta baja y alta a excepción de los muros en ángulo en cocina y recamara. Así como los muros indicados en las observaciones. | KC12: Losas de Cimentación
AD13: Primero se tiene que analizar la respuesta a Presiones Estaticas como con cualquier otra estructura, sin embargo, debido a los techos bolados deberemos poner especial atencion a los efectos de "Rafaga", de "Arrastre" y "Vortice". | BY13: Vz = | BZ13: =BR44 -> 145.475 | CA13: x | CB13: 2.5 | CC13: x | CD13: 0.35 | CE13: = | CF13: =BZ13*CB13*CD13 -> 127.29062 | CR13: 0.0048 | CS13: 2 | CT13: =CU7 -> 76.374375 | CV13: 6 | CW13: =CR13*CS13*(CT13^2)*CV13 -> 335.9834 | DJ13: Placa o Caja de Conección | DW13: Carga muerta = | DX13: 100 | DY13: kg/m^2 | DZ13: =IF(DY13="kg/m^2",1,IF(DY13="lbs/pis^2",2,3)) -> 1 | EG13: P.P. = | EH13: 2.2 | EI13: lbs/pie^2 | EN13: combinaciones de carga | FF13: Sreq | FG13: =FG11/FG12 -> 324.47564 | FJ13: Distancia de nudo a carga puntual | FL13: =-1*(IF(FL24=0,0,IF(FK13=0,0,IF(FK14=0,0,IF(FK13=(FL24/2),FK14*FL24/8,FK14*FK13*((FL24-FK13)*(FL24-FK13))/(FL24*FL24)))))) -> 0 | FM13: =IF(FL24=0,0,IF(FK13=0,0,IF(FK14=0,0,IF(FK13=(FL24/2),FL13*-1,FK14*(FK13*FK13)*(FL24-FK13)/(FL24*FL24))))) -> 0 | FP13: Distancia de nudo a carga puntual | FR13: =-1*(IF(FR24=0,0,IF(FQ13=0,0,IF(FQ14=0,0,IF(FQ13=(FR24/2),FQ14*FR24/8,FQ14*FQ13*((FR24-FQ13)*(FR24-FQ13))/(FR24*FR24)))))) -> 0 | FS13: =IF(FR24=0,0,IF(FQ13=0,0,IF(FQ14=0,0,IF(FQ13=(FR24/2),FR13*-1,FQ14*(FQ13*FQ13)*(FR24-FQ13)/(FR24*FR24))))) -> 0 | GD13: Sreq | GE13: =GE11/GE12 -> 59.207818 | GH13: Distancia de nudo a carga puntual | GJ13: =-1*(IF(GJ24=0,0,IF(GI13=0,0,IF(GI14=0,0,IF(GI13=(GJ24/2),GI14*GJ24/8,GI14*GI13*((GJ24-GI13)*(GJ24-GI13))/(GJ24*GJ24)))))) -> 0 | GK13: =IF(GJ24=0,0,IF(GI13=0,0,IF(GI14=0,0,IF(GI13=(GJ24/2),GJ13*-1,GI14*(GI13*GI13)*(GJ24-GI13)/(GJ24*GJ24))))) -> 0 | GN13: Distancia de nudo a carga puntual | GP13: =-1*(IF(GP24=0,0,IF(GO13=0,0,IF(GO14=0,0,IF(GO13=(GP24/2),GO14*GP24/8,GO14*GO13*((GP24-GO13)*(GP24-GO13))/(GP24*GP24)))))) -> 0 | GQ13: =IF(GP24=0,0,IF(GO13=0,0,IF(GO14=0,0,IF(GO13=(GP24/2),GP13*-1,GO14*(GO13*GO13)*(GP24-GO13)/(GP24*GP24))))) -> 0 | GZ13: Z req | HA13: =HA11/HA12 -> 61.169335 | HD13: Distancia de nudo a carga puntual | HF13: =-1*(IF(HF24=0,0,IF(HE13=0,0,IF(HE14=0,0,IF(HE13=(HF24/2),HE14*HF24/8,HE14*HE13*((HF24-HE13)*(HF24-HE13))/(HF24*HF24)))))) -> 0 | HG13: =IF(HF24=0,0,IF(HE13=0,0,IF(HE14=0,0,IF(HE13=(HF24/2),HF13*-1,HE14*(HE13*HE13)*(HF24-HE13)/(HF24*HF24))))) -> 0 | HJ13: Distancia de nudo a carga puntual | HL13: =-1*(IF(HL24=0,0,IF(HK13=0,0,IF(HK14=0,0,IF(HK13=(HL24/2),HK14*HL24/8,HK14*HK13*((HL24-HK13)*(HL24-HK13))/(HL24*HL24)))))) -> 0 | HM13: =IF(HL24=0,0,IF(HK13=0,0,IF(HK14=0,0,IF(HK13=(HL24/2),HL13*-1,HK14*(HK13*HK13)*(HL24-HK13)/(HL24*HL24))))) -> 0 | HP13: Distancia de nudo a carga puntual | HR13: =-1*(IF(HR24=0,0,IF(HQ13=0,0,IF(HQ14=0,0,IF(HQ13=(HR24/2),HQ14*HR24/8,HQ14*HQ13*((HR24-HQ13)*(HR24-HQ13))/(HR24*HR24)))))) -> 0 | HS13: =IF(HR24=0,0,IF(HQ13=0,0,IF(HQ14=0,0,IF(HQ13=(HR24/2),HR13*-1,HQ14*(HQ13*HQ13)*(HR24-HQ13)/(HR24*HR24))))) -> 0 | HV13: Distancia de nudo a carga puntual | HX13: =-1*(IF(HX24=0,0,IF(HW13=0,0,IF(HW14=0,0,IF(HW13=(HX24/2),HW14*HX24/8,HW14*HW13*((HX24-HW13)*(HX24-HW13))/(HX24*HX24)))))) -> 0 | HY13: =IF(HX24=0,0,IF(HW13=0,0,IF(HW14=0,0,IF(HW13=(HX24/2),HX13*-1,HW14*(HW13*HW13)*(HX24-HW13)/(HX24*HX24))))) -> 0 | IJ13: Reacciones | IK13: Distancia | IL13: Hipotenusa | IM13: Tension | IN13: Area Req | IO13: Tension H | KC13: Espesor 15 cm. Armado a base de varillas #4 @ 13 en ambas direcciones en el lecho superior, en los ejes de marco se aumentara el espesor a 20 cm armando un metro con varilla #4 @ 13 en el lecho inferior como zapata invertida. Finalmente se colocara una trabe de liga de 35 x 50 para absorber posibles asentamientos Armada comola Trabe T2.
CR14: 0.0048 | CS14: 2 | CT14: =CU8 -> 50.91625 | CV14: 6 | CW14: =CR14*CS14*(CT14^2)*CV14 -> 149.32596 | DW14: Peso Propio = | DX14: 12 | DY14: =DY13 -> kg/m^2 | EG14: Condicion | EH14: Wb >= Wu | EN14: 1 | EO14: 0.9 CM + 1.43 CT | ES14: =0.9*ES10 -> 145.8 | ET14: kg | FJ14: Carga Puntual | FP14: Carga Puntual | FX14: critico | GH14: Carga Puntual | GN14: Carga Puntual | GV14: critico | HD14: Carga Puntual | HJ14: Carga Puntual | HP14: Carga Puntual | HV14: Carga Puntual | IJ14: =HC28 -> 901.28948 | IK14: 6 | IL14: =((IK14^2)+1)^0.5 -> 6.0827625 | IM14: =IJ14*IL14/1 -> 5482.3299 | IN14: =IM14/2500 -> 2.192932 | IO14: =IM14*IK14/IL14 -> 5407.7369 | IY14: Muros Tapón MT
BQ15: Se puese considerar que la villa se encuentra cercana a promontorios. Así mismo las torres, Casa Club y demás villas actuan en los vientos ocasionando un efectos de encajonamiento. | BY15: estas velocidades se emplearan para determinar la carga viva constante (viento promedio) y la maxima (rafagas) | CR15: 0.0048 | CS15: 2 | CT15: =CU9 -> 25.458125 | CV15: 6 | CW15: =CR15*CS15*(CT15^2)*CV15 -> 37.331489 | DW15: Carga Muerta Total = | DX15: =DX14+DX13 -> 112 | EG15: l = (120 Fb KS / Wu )^0.5 = | EH15: =(120*EH11*EH12/DX19)^0.5 -> 26.00623 | EI15: pulgadas | EN15: 2 | EO15: 1.4 CM | ES15: =1.4*ES10 -> 226.8 | ET15: kg | FJ15: Distancia de nudo a carga puntual | FL15: =-1*(IF(FL24=0,0,IF(FK15=0,0,IF(FK16=0,0,IF(FK15=(FL24/2),FK16*FL24/8,FK16*FK15*((FL24-FK15)*(FL24-FK15))/(FL24*FL24)))))) -> 0 | FM15: =IF(FL24=0,0,IF(FK15=0,0,IF(FK16=0,0,IF(FK15=(FL24/2),FL15*-1,FK16*(FK15*FK15)*(FL24-FK15)/(FL24*FL24))))) -> 0 | FP15: Distancia de nudo a carga puntual | FR15: =-1*(IF(FR24=0,0,IF(FQ15=0,0,IF(FQ16=0,0,IF(FQ15=(FR24/2),FQ16*FR24/8,FQ16*FQ15*((FR24-FQ15)*(FR24-FQ15))/(FR24*FR24)))))) -> 0 | FS15: =IF(FR24=0,0,IF(FQ15=0,0,IF(FQ16=0,0,IF(FQ15=(FR24/2),FR15*-1,FQ16*(FQ15*FQ15)*(FR24-FQ15)/(FR24*FR24))))) -> 0 | GH15: Distancia de nudo a carga puntual | GJ15: =-1*(IF(GJ24=0,0,IF(GI15=0,0,IF(GI16=0,0,IF(GI15=(GJ24/2),GI16*GJ24/8,GI16*GI15*((GJ24-GI15)*(GJ24-GI15))/(GJ24*GJ24)))))) -> 0 | GK15: =IF(GJ24=0,0,IF(GI15=0,0,IF(GI16=0,0,IF(GI15=(GJ24/2),GJ15*-1,GI16*(GI15*GI15)*(GJ24-GI15)/(GJ24*GJ24))))) -> 0 | GN15: Distancia de nudo a carga puntual | GP15: =-1*(IF(GP24=0,0,IF(GO15=0,0,IF(GO16=0,0,IF(GO15=(GP24/2),GO16*GP24/8,GO16*GO15*((GP24-GO15)*(GP24-GO15))/(GP24*GP24)))))) -> 0 | GQ15: =IF(GP24=0,0,IF(GO15=0,0,IF(GO16=0,0,IF(GO15=(GP24/2),GP15*-1,GO16*(GO15*GO15)*(GP24-GO15)/(GP24*GP24))))) -> 0 | HD15: Distancia de nudo a carga puntual | HF15: =-1*(IF(HF24=0,0,IF(HE15=0,0,IF(HE16=0,0,IF(HE15=(HF24/2),HE16*HF24/8,HE16*HE15*((HF24-HE15)*(HF24-HE15))/(HF24*HF24)))))) -> 0 | HG15: =IF(HF24=0,0,IF(HE15=0,0,IF(HE16=0,0,IF(HE15=(HF24/2),HF15*-1,HE16*(HE15*HE15)*(HF24-HE15)/(HF24*HF24))))) -> 0 | HJ15: Distancia de nudo a carga puntual | HL15: =-1*(IF(HL24=0,0,IF(HK15=0,0,IF(HK16=0,0,IF(HK15=(HL24/2),HK16*HL24/8,HK16*HK15*((HL24-HK15)*(HL24-HK15))/(HL24*HL24)))))) -> 0 | HM15: =IF(HL24=0,0,IF(HK15=0,0,IF(HK16=0,0,IF(HK15=(HL24/2),HL15*-1,HK16*(HK15*HK15)*(HL24-HK15)/(HL24*HL24))))) -> 0 | HP15: Distancia de nudo a carga puntual | HR15: =-1*(IF(HR24=0,0,IF(HQ15=0,0,IF(HQ16=0,0,IF(HQ15=(HR24/2),HQ16*HR24/8,HQ16*HQ15*((HR24-HQ15)*(HR24-HQ15))/(HR24*HR24)))))) -> 0 | HS15: =IF(HR24=0,0,IF(HQ15=0,0,IF(HQ16=0,0,IF(HQ15=(HR24/2),HR15*-1,HQ16*(HQ15*HQ15)*(HR24-HQ15)/(HR24*HR24))))) -> 0 | HV15: Distancia de nudo a carga puntual | HX15: =-1*(IF(HX24=0,0,IF(HW15=0,0,IF(HW16=0,0,IF(HW15=(HX24/2),HW16*HX24/8,HW16*HW15*((HX24-HW15)*(HX24-HW15))/(HX24*HX24)))))) -> 0 | HY15: =IF(HX24=0,0,IF(HW15=0,0,IF(HW16=0,0,IF(HW15=(HX24/2),HX15*-1,HW16*(HW15*HW15)*(HX24-HW15)/(HX24*HX24))))) -> 0 | IJ15: =HI28 -> 2452.7036 | IK15: 4 | IL15: =((IK15^2)+1)^0.5 -> 4.1231056 | IM15: =IJ15*IL15/1 -> 10112.756 | IN15: =IM15/2500 -> 4.0451023 | IO15: =IM15*IK15/IL15 -> 9810.8143 | IP15: critico | IY15: =EN24 -> Toda vez que no se generar ningun cambio en el entrepiso, ninguna redistribucion de esfuerzos, ni colocacion alguna de cargas concentradas en la losa de entrepiso no se requiere reanalizarle. En realidad aun con los voladizos proyectados las cargas sobre los muros de carga donde estos voladizos cargaran se veran disminuidas al eliminarse la techumbre original de concreto.
DJ16: PTR | DW16: Carga viva factorizada = | DX16: =DX12*1.6 -> 240 | EG16: ponderado | EH16: 12 | EI16: pulgadas | EJ16: =EH16*2.54 -> 30.48 | EK16: cm | EN16: 3 | EO16: 1.2 CM + 1.6 CV viento | ES16: =(1.2*ES10)+(1.6*ES11) -> 318.8383 | ET16: kg | FJ16: Carga Puntual | FP16: Carga Puntual | GH16: Carga Puntual | GN16: Carga Puntual | HD16: Carga Puntual | HJ16: Carga Puntual | HP16: Carga Puntual | HV16: Carga Puntual | IJ16: =HO28 -> 342.92116 | IK16: 2 | IL16: =((IK16^2)+1)^0.5 -> 2.236068 | IM16: =IJ16*IL16/1 -> 766.79502 | IN16: =IM16/2500 -> 0.30671801 | IO16: =IM16*IK16/IL16 -> 685.84232
L17: El complejo se encuentra en una zona de conglomerado marino y roca intrusiva (graniticas). Superficialmente recubierto con arenas por deposito eolico. An norte se aprecia el aluvion formado por el arroyo de El Descanso. Al oeste se aprecia una falla sin actividad a menos de 2 km situacion que es el promedio en toda la zona costera de Baja California. Por tanto tomaremos las prevenciones sismicas basicas que nos exige la normatividad del estado. | CH17: FL prom = | CI17: 0.0048 | CJ17: 2 | CK17: =CF11 -> 13.3308 | CM17: =CF46 -> 6 | CN17: =CI17*CJ17*(CK17^2)*CM17 -> 10.236109 | DW17: Carga muerta factorizada = | DX17: =DX15*1.4 -> 156.8 | EN17: 4 | EO17: 1.2 CM + 1.6 CV + .5 lluvia | ES17: =(1.2*ES10)+(1.6*ES9)+(0.5*ES12) -> 435.4 | ET17: kg | FJ17: Distancia de nudo a carga puntual | FL17: =-1*(IF(FL24=0,0,IF(FK17=0,0,IF(FK18=0,0,IF(FK17=(FL24/2),FK18*FL24/8,FK18*FK17*((FL24-FK17)*(FL24-FK17))/(FL24*FL24)))))) -> 0 | FM17: =IF(FL24=0,0,IF(FK17=0,0,IF(FK18=0,0,IF(FK17=(FL24/2),FL17*-1,FK18*(FK17*FK17)*(FL24-FK17)/(FL24*FL24))))) -> 0 | FP17: Distancia de nudo a carga puntual | FR17: =-1*(IF(FR24=0,0,IF(FQ17=0,0,IF(FQ18=0,0,IF(FQ17=(FR24/2),FQ18*FR24/8,FQ18*FQ17*((FR24-FQ17)*(FR24-FQ17))/(FR24*FR24)))))) -> 0 | FS17: =IF(FR24=0,0,IF(FQ17=0,0,IF(FQ18=0,0,IF(FQ17=(FR24/2),FR17*-1,FQ18*(FQ17*FQ17)*(FR24-FQ17)/(FR24*FR24))))) -> 0 | GH17: Distancia de nudo a carga puntual | GJ17: =-1*(IF(GJ24=0,0,IF(GI17=0,0,IF(GI18=0,0,IF(GI17=(GJ24/2),GI18*GJ24/8,GI18*GI17*((GJ24-GI17)*(GJ24-GI17))/(GJ24*GJ24)))))) -> 0 | GK17: =IF(GJ24=0,0,IF(GI17=0,0,IF(GI18=0,0,IF(GI17=(GJ24/2),GJ17*-1,GI18*(GI17*GI17)*(GJ24-GI17)/(GJ24*GJ24))))) -> 0 | GN17: Distancia de nudo a carga puntual | GP17: =-1*(IF(GP24=0,0,IF(GO17=0,0,IF(GO18=0,0,IF(GO17=(GP24/2),GO18*GP24/8,GO18*GO17*((GP24-GO17)*(GP24-GO17))/(GP24*GP24)))))) -> 0 | GQ17: =IF(GP24=0,0,IF(GO17=0,0,IF(GO18=0,0,IF(GO17=(GP24/2),GP17*-1,GO18*(GO17*GO17)*(GP24-GO17)/(GP24*GP24))))) -> 0 | HD17: Distancia de nudo a carga puntual | HF17: =-1*(IF(HF24=0,0,IF(HE17=0,0,IF(HE18=0,0,IF(HE17=(HF24/2),HE18*HF24/8,HE18*HE17*((HF24-HE17)*(HF24-HE17))/(HF24*HF24)))))) -> 0 | HG17: =IF(HF24=0,0,IF(HE17=0,0,IF(HE18=0,0,IF(HE17=(HF24/2),HF17*-1,HE18*(HE17*HE17)*(HF24-HE17)/(HF24*HF24))))) -> 0 | HJ17: Distancia de nudo a carga puntual | HL17: =-1*(IF(HL24=0,0,IF(HK17=0,0,IF(HK18=0,0,IF(HK17=(HL24/2),HK18*HL24/8,HK18*HK17*((HL24-HK17)*(HL24-HK17))/(HL24*HL24)))))) -> 0 | HM17: =IF(HL24=0,0,IF(HK17=0,0,IF(HK18=0,0,IF(HK17=(HL24/2),HL17*-1,HK18*(HK17*HK17)*(HL24-HK17)/(HL24*HL24))))) -> 0 | HP17: Distancia de nudo a carga puntual | HR17: =-1*(IF(HR24=0,0,IF(HQ17=0,0,IF(HQ18=0,0,IF(HQ17=(HR24/2),HQ18*HR24/8,HQ18*HQ17*((HR24-HQ17)*(HR24-HQ17))/(HR24*HR24)))))) -> 0 | HS17: =IF(HR24=0,0,IF(HQ17=0,0,IF(HQ18=0,0,IF(HQ17=(HR24/2),HR17*-1,HQ18*(HQ17*HQ17)*(HR24-HQ17)/(HR24*HR24))))) -> 0 | HV17: Distancia de nudo a carga puntual | HX17: =-1*(IF(HX24=0,0,IF(HW17=0,0,IF(HW18=0,0,IF(HW17=(HX24/2),HW18*HX24/8,HW18*HW17*((HX24-HW17)*(HX24-HW17))/(HX24*HX24)))))) -> 0 | HY17: =IF(HX24=0,0,IF(HW17=0,0,IF(HW18=0,0,IF(HW17=(HX24/2),HX17*-1,HW18*(HW17*HW17)*(HX24-HW17)/(HX24*HX24))))) -> 0 | IJ17: =HU28 -> 4585.6479 | IK17: 0 | IL17: =((IK17^2)+1)^0.5 -> 1 | IM17: =IJ17*IL17/1 -> 4585.6479 | IN17: =IM17/2500 -> 1.8342591 | IO17: =IM17*IK17/IL17 -> 0
AD18: Velocidad de Diseño. | BY18: Empuje Estatico por viento: | CH18: FL raf = | CI18: 0.0048 | CJ18: 2 | CK18: =CF13 -> 127.29062 | CM18: =CM17 -> 6 | CN18: =CI18*CJ18*(CK18^2)*CM18 -> 933.28723 | DJ18: Tensores | DW18: Carga Total = | DX18: =DX17+DX16 -> 396.8 | EF18: claro maximo por cortante | EN18: la formula 4 rige | ES18: =MAX(ES14:ES17) -> 435.4 | ET18: kg | FJ18: Carga Puntual | FP18: Carga Puntual | GH18: Carga Puntual | GN18: Carga Puntual | HD18: Carga Puntual | HJ18: Carga Puntual | HP18: Carga Puntual | HV18: Carga Puntual | KC18: Del Procedimiento de Construcción
U19: 2010 | AD19: Vß = K1 K2 Vo | BQ19: Claramente podemos apreciar que los vientos predominantes en la zona son de este a oeste y viceversa teniendo: | BY19: P = N C Vz² donde: P = presión o succión en kg/m² C = coeficiente de empuje 8 + a N = coeficiente de densidad del aire, igual a 0.0048 Vz = velocidad de diseño en km/h a = altura sobre el nivel del mar en km. | CH19: FL = FT | CP19: t= | CQ19: 0-->4 | CR19: To= | CS19: 1 | CU19: d= | CV19: 0.5 | DA19: elemento | DW19: Carga en lbs/pie2 = | DX19: =DX18*2.2/(3.28^2) -> 81.142177 | EG19: Ws = 20 Fs (lb/Q)/l2 | EN19: carga total techumbre: | ES19: =ES18 -> 435.4 | FJ19: Distancia de nudo a carga puntual | FL19: =-1*(IF(FL24=0,0,IF(FK19=0,0,IF(FK20=0,0,IF(FK19=(FL24/2),FK20*FL24/8,FK20*FK19*((FL24-FK19)*(FL24-FK19))/(FL24*FL24)))))) -> 0 | FM19: =IF(FL24=0,0,IF(FK19=0,0,IF(FK20=0,0,IF(FK19=(FL24/2),FL19*-1,FK20*(FK19*FK19)*(FL24-FK19)/(FL24*FL24))))) -> 0 | FP19: Distancia de nudo a carga puntual | FR19: =-1*(IF(FR24=0,0,IF(FQ19=0,0,IF(FQ20=0,0,IF(FQ19=(FR24/2),FQ20*FR24/8,FQ20*FQ19*((FR24-FQ19)*(FR24-FQ19))/(FR24*FR24)))))) -> 0 | FS19: =IF(FR24=0,0,IF(FQ19=0,0,IF(FQ20=0,0,IF(FQ19=(FR24/2),FR19*-1,FQ20*(FQ19*FQ19)*(FR24-FQ19)/(FR24*FR24))))) -> 0 | GH19: Distancia de nudo a carga puntual | GJ19: =-1*(IF(GJ24=0,0,IF(GI19=0,0,IF(GI20=0,0,IF(GI19=(GJ24/2),GI20*GJ24/8,GI20*GI19*((GJ24-GI19)*(GJ24-GI19))/(GJ24*GJ24)))))) -> 0 | GK19: =IF(GJ24=0,0,IF(GI19=0,0,IF(GI20=0,0,IF(GI19=(GJ24/2),GJ19*-1,GI20*(GI19*GI19)*(GJ24-GI19)/(GJ24*GJ24))))) -> 0 | GN19: Distancia de nudo a carga puntual | GP19: =-1*(IF(GP24=0,0,IF(GO19=0,0,IF(GO20=0,0,IF(GO19=(GP24/2),GO20*GP24/8,GO20*GO19*((GP24-GO19)*(GP24-GO19))/(GP24*GP24)))))) -> 0 | GQ19: =IF(GP24=0,0,IF(GO19=0,0,IF(GO20=0,0,IF(GO19=(GP24/2),GP19*-1,GO20*(GO19*GO19)*(GP24-GO19)/(GP24*GP24))))) -> 0 | HD19: Distancia de nudo a carga puntual | HF19: =-1*(IF(HF24=0,0,IF(HE19=0,0,IF(HE20=0,0,IF(HE19=(HF24/2),HE20*HF24/8,HE20*HE19*((HF24-HE19)*(HF24-HE19))/(HF24*HF24)))))) -> 0 | HG19: =IF(HF24=0,0,IF(HE19=0,0,IF(HE20=0,0,IF(HE19=(HF24/2),HF19*-1,HE20*(HE19*HE19)*(HF24-HE19)/(HF24*HF24))))) -> 0 | HJ19: Distancia de nudo a carga puntual | HL19: =-1*(IF(HL24=0,0,IF(HK19=0,0,IF(HK20=0,0,IF(HK19=(HL24/2),HK20*HL24/8,HK20*HK19*((HL24-HK19)*(HL24-HK19))/(HL24*HL24)))))) -> 0 | HM19: =IF(HL24=0,0,IF(HK19=0,0,IF(HK20=0,0,IF(HK19=(HL24/2),HL19*-1,HK20*(HK19*HK19)*(HL24-HK19)/(HL24*HL24))))) -> 0 | HP19: Distancia de nudo a carga puntual | HR19: =-1*(IF(HR24=0,0,IF(HQ19=0,0,IF(HQ20=0,0,IF(HQ19=(HR24/2),HQ20*HR24/8,HQ20*HQ19*((HR24-HQ19)*(HR24-HQ19))/(HR24*HR24)))))) -> 0 | HS19: =IF(HR24=0,0,IF(HQ19=0,0,IF(HQ20=0,0,IF(HQ19=(HR24/2),HR19*-1,HQ20*(HQ19*HQ19)*(HR24-HQ19)/(HR24*HR24))))) -> 0 | HV19: Distancia de nudo a carga puntual | HX19: =-1*(IF(HX24=0,0,IF(HW19=0,0,IF(HW20=0,0,IF(HW19=(HX24/2),HW20*HX24/8,HW20*HW19*((HX24-HW19)*(HX24-HW19))/(HX24*HX24)))))) -> 0 | HY19: =IF(HX24=0,0,IF(HW19=0,0,IF(HW20=0,0,IF(HW19=(HX24/2),HX19*-1,HW20*(HW19*HW19)*(HX24-HW19)/(HX24*HX24))))) -> 0 | IK19: Angulo | IL19: 2 x 1/4 | IY19: Trabes T1 | KC19: Se procurara colar Monolíticamente Trabes Losas y Columnas en cada nivel. Particularmente en el nivel sótano para evitar juntas frías que conduzcan a filtraciones. Se empleara Block dala para colocar la varilla horizontal . Para ganchos y traslapes referirse a manual ACI.
AD20: 1.15 | AE20: K1= | AF20: factor de topografia se tomara 1 para terreno plano y 1.15 en promontonrios, centros industriales y residenciales | CP20: p \/ | CQ20: v \/ t= | CR20: 0 | CS20: 1 | CT20: 2 | CU20: 3 | CV20: 4 | CW20: Ck= | CX20: C= | CY20: T= | CZ20: d= | DA20: l= | DB20: Periodo | DD20: Condicion: | DW20: peso tablaroca = | DX20: 6.75 | DY20: m^2 | EG20: Ws = maxima carga uniforme por cortante | EN20: carga total techumbre en ton: | ES20: =ES19/1000 -> 0.4354 | FJ20: Carga Puntual | FP20: Carga Puntual | GH20: Carga Puntual | GN20: Carga Puntual | HD20: Carga Puntual | HJ20: Carga Puntual | HP20: Carga Puntual | HV20: Carga Puntual | IK20: Canal | IL20: 3 x 4.1 | IY20: Trabe de 60 x 35 cm armada con 3 Varillas #5 en cada lecho, dos varillas # 4 al centro, Estribos #3 @ 20 al centro y @ 15 a 1/4 de L en cada extremo así como como a 70 cm de cada nodo interno (donde reciba otra trabe)
CP21: =CW11 -> 933.28723 | CQ21: =CW5 -> 77.773935 | CR21: =CP21*(CW21/CX21)*CZ21*(SIN(2*PI()*CR20/CY21)) -> 0 | CS21: =CP21*(CW21/CX21)*CZ21*(SIN(2*PI()*CS20/CY21)) -> -213.1952 | CT21: =CP21*(CW21/CX21)*CZ21*(SIN(2*PI()*CT20/CY21)) -> 268.58238 | CU21: =CP21*(CW21/CX21)*CZ21*(SIN(2*PI()*CU20/CY21)) -> -125.1637 | CV21: =CP21*(CW21/CX21)*CZ21*(SIN(2*PI()*CV20/CY21)) -> -110.9017 | CW21: 1 | CX21: 1.7 | CY21: =18*(CZ21/CQ21) -> 0.11572 | CZ21: =CV19 -> 0.5 | DA21: 4.1 | DB21: =2*PI()*((DA21/9.81)^0.5) -> 4.0619754 | DD21: Se desea ampliar la recámara principal de una de la villas. Paralelamente el dueño desea cambiar el diseño a fin de obtener un cancel similar al de los condominios (1,4) sin obstrucción alguna a la vista. Esto significa que la techumbre de la recámara estará sobre algún tipo de estructura en voladizo con un largo máximo de poco menos de 6 metros. | DW21: cargas entrepiso= | DX21: =DX18 -> 396.8 | EG21: Fs = esfuerzo cortante maximo permisible | FJ21: Distancia de nudo a carga puntual | FL21: =-1*(IF(FL24=0,0,IF(FK21=0,0,IF(FK22=0,0,IF(FK21=(FL24/2),FK22*FL24/8,FK22*FK21*((FL24-FK21)*(FL24-FK21))/(FL24*FL24)))))) -> 0 | FM21: =IF(FL24=0,0,IF(FK21=0,0,IF(FK22=0,0,IF(FK21=(FL24/2),FL21*-1,FK22*(FK21*FK21)*(FL24-FK21)/(FL24*FL24))))) -> 0 | FP21: Distancia de nudo a carga puntual | FR21: =-1*(IF(FR24=0,0,IF(FQ21=0,0,IF(FQ22=0,0,IF(FQ21=(FR24/2),FQ22*FR24/8,FQ22*FQ21*((FR24-FQ21)*(FR24-FQ21))/(FR24*FR24)))))) -> 0 | FS21: =IF(FR24=0,0,IF(FQ21=0,0,IF(FQ22=0,0,IF(FQ21=(FR24/2),FR21*-1,FQ22*(FQ21*FQ21)*(FR24-FQ21)/(FR24*FR24))))) -> 0 | GH21: Distancia de nudo a carga puntual | GJ21: =-1*(IF(GJ24=0,0,IF(GI21=0,0,IF(GI22=0,0,IF(GI21=(GJ24/2),GI22*GJ24/8,GI22*GI21*((GJ24-GI21)*(GJ24-GI21))/(GJ24*GJ24)))))) -> 0 | GK21: =IF(GJ24=0,0,IF(GI21=0,0,IF(GI22=0,0,IF(GI21=(GJ24/2),GJ21*-1,GI22*(GI21*GI21)*(GJ24-GI21)/(GJ24*GJ24))))) -> 0 | GN21: Distancia de nudo a carga puntual | GP21: =-1*(IF(GP24=0,0,IF(GO21=0,0,IF(GO22=0,0,IF(GO21=(GP24/2),GO22*GP24/8,GO22*GO21*((GP24-GO21)*(GP24-GO21))/(GP24*GP24)))))) -> 0 | GQ21: =IF(GP24=0,0,IF(GO21=0,0,IF(GO22=0,0,IF(GO21=(GP24/2),GP21*-1,GO22*(GO21*GO21)*(GP24-GO21)/(GP24*GP24))))) -> 0 | HD21: Distancia de nudo a carga puntual | HF21: =-1*(IF(HF24=0,0,IF(HE21=0,0,IF(HE22=0,0,IF(HE21=(HF24/2),HE22*HF24/8,HE22*HE21*((HF24-HE21)*(HF24-HE21))/(HF24*HF24)))))) -> 0 | HG21: =IF(HF24=0,0,IF(HE21=0,0,IF(HE22=0,0,IF(HE21=(HF24/2),HF21*-1,HE22*(HE21*HE21)*(HF24-HE21)/(HF24*HF24))))) -> 0 | HJ21: Distancia de nudo a carga puntual | HL21: =-1*(IF(HL24=0,0,IF(HK21=0,0,IF(HK22=0,0,IF(HK21=(HL24/2),HK22*HL24/8,HK22*HK21*((HL24-HK21)*(HL24-HK21))/(HL24*HL24)))))) -> 0 | HM21: =IF(HL24=0,0,IF(HK21=0,0,IF(HK22=0,0,IF(HK21=(HL24/2),HL21*-1,HK22*(HK21*HK21)*(HL24-HK21)/(HL24*HL24))))) -> 0 | HP21: Distancia de nudo a carga puntual | HR21: =-1*(IF(HR24=0,0,IF(HQ21=0,0,IF(HQ22=0,0,IF(HQ21=(HR24/2),HQ22*HR24/8,HQ22*HQ21*((HR24-HQ21)*(HR24-HQ21))/(HR24*HR24)))))) -> 0 | HS21: =IF(HR24=0,0,IF(HQ21=0,0,IF(HQ22=0,0,IF(HQ21=(HR24/2),HR21*-1,HQ22*(HQ21*HQ21)*(HR24-HQ21)/(HR24*HR24))))) -> 0 | HV21: Distancia de nudo a carga puntual | HX21: =-1*(IF(HX24=0,0,IF(HW21=0,0,IF(HW22=0,0,IF(HW21=(HX24/2),HW22*HX24/8,HW22*HW21*((HX24-HW21)*(HX24-HW21))/(HX24*HX24)))))) -> 0 | HY21: =IF(HX24=0,0,IF(HW21=0,0,IF(HW22=0,0,IF(HW21=(HX24/2),HX21*-1,HW22*(HW21*HW21)*(HX24-HW21)/(HX24*HX24))))) -> 0
BU22: Promedio NASA | CP22: =CW12 -> 597.30382 | CQ22: =CW6 -> 49.775319 | CR22: =CP22*(CW22/CX22)*CZ22*(SIN(2*PI()*CR21/CY22)) -> 0 | CS22: =CP22*(CW22/CX22)*CZ22*(SIN(2*PI()*CS21/CY22)) -> -150.28675 | CT22: =CP22*(CW22/CX22)*CZ22*(SIN(2*PI()*CT21/CY22)) -> -35.515322 | CU22: =CP22*(CW22/CX22)*CZ22*(SIN(2*PI()*CU21/CY22)) -> 110.40683 | CV22: =CP22*(CW22/CX22)*CZ22*(SIN(2*PI()*CV21/CY22)) -> -133.66207 | CW22: =CW21 -> 1 | CX22: =CX21 -> 1.7 | CY22: =CY21 -> 0.11572 | CZ22: =CZ21 -> 0.5 | DA22: 4 | DB22: =2*PI()*((DA22/9.81)^0.5) -> 4.0121334 | DW22: reacciones= | DX22: =DX21*DW42/3.28 -> 362.92683 | EG22: Ib/Q = constante para cortante por seccion | EN22: Entrepiso | FF22: long | FG22: 3 | FJ22: Carga Puntual | FP22: Carga Puntual | FW22: long. | GD22: long | GE22: 1 | GH22: Carga Puntual | GN22: Carga Puntual | GU22: long. | GZ22: long | HD22: Carga Puntual | HJ22: Carga Puntual | HP22: Carga Puntual | HV22: Carga Puntual | IC22: long. | IK22: Perfil Principal
AD23: 1.15 | AE23: K2= | AF23: factor de recurrencia se tomara 1 para estructuras tipo B y 1.15 para estructuras tipo A | BU23: De | CP23: =CW13 -> 335.9834 | CQ23: =CW7 -> 27.998617 | CR23: =CP23*(CW23/CX23)*CZ23*(SIN(2*PI()*CR22/CY23)) -> 0 | CS23: =CP23*(CW23/CX23)*CZ23*(SIN(2*PI()*CS22/CY23)) -> 95.751755 | CT23: =CP23*(CW23/CX23)*CZ23*(SIN(2*PI()*CT22/CY23)) -> 54.319918 | CU23: =CP23*(CW23/CX23)*CZ23*(SIN(2*PI()*CU22/CY23)) -> 50.7947 | CV23: =CP23*(CW23/CX23)*CZ23*(SIN(2*PI()*CV22/CY23)) -> -28.892776 | CW23: =CW22 -> 1 | CX23: =CX22 -> 1.7 | CY23: =CY22 -> 0.11572 | CZ23: =CZ22 -> 0.5 | DA23: 3.8 | DB23: =2*PI()*((DA23/9.81)^0.5) -> 3.9105439 | DW23: area req | DX23: =DX22/EA32 -> 0.17038818 | DY23: cm2 | EG23: l = claro entre soportes | FF23: w | FG23: =FG6*FG7 -> 1756.2 | FK23: Momento total en Nudos = suma. | FL23: =SUM(FL9:FL22) -> -1361.8773 | FM23: =SUM(FM9:FM22) -> 1361.8773 | FQ23: Momento total en Nudos = suma. | FR23: =SUM(FR9:FR22) -> 0 | FS23: =SUM(FS9:FS22) -> 0 | FW23: w | GD23: w | GE23: =GE6*GE7 -> 1756.2 | GI23: Momento total en Nudos = suma. | GJ23: =SUM(GJ9:GJ22) -> -1361.8773 | GK23: =SUM(GK9:GK22) -> 1361.8773 | GO23: Momento total en Nudos = suma. | GP23: =SUM(GP9:GP22) -> -1361.8773 | GQ23: =SUM(GQ9:GQ22) -> 1361.8773 | GU23: w | GZ23: w | HE23: Momento total en Nudos = suma. | HF23: =SUM(HF9:HF22) -> -173.89072 | HG23: =SUM(HG9:HG22) -> 153.82759 | HK23: Momento total en Nudos = suma. | HL23: =SUM(HL9:HL22) -> -151.3197 | HM23: =SUM(HM9:HM22) -> 151.3197 | HQ23: Momento total en Nudos = suma. | HR23: =SUM(HR9:HR22) -> -151.3197 | HS23: =SUM(HS9:HS22) -> 151.3197 | HW23: Momento total en Nudos = suma. | HX23: =SUM(HX9:HX22) -> -1361.8773 | HY23: =SUM(HY9:HY22) -> 1361.8773 | IC23: w | IK23: Momento | IL23: Mom kg-cm | IM23: Cortante | IN23: Z req | IO23: Area Req Vy | IY23: Trabe T2 | KC23: Materiales de Construcción
L24: Mecanica de Suelos Estimada | BU24: 3.2 | BV24: m/s | CP24: =CW14 -> 149.32596 | CQ24: =CW8 -> 12.44383 | CR24: =CP24*(CW24/CX24)*CZ24*(SIN(2*PI()*CR23/CY24)) -> 0 | CS24: =CP24*(CW24/CX24)*CZ24*(SIN(2*PI()*CS23/CY24)) -> 15.286476 | CT24: =CP24*(CW24/CX24)*CZ24*(SIN(2*PI()*CT23/CY24)) -> 23.951787 | CU24: =CP24*(CW24/CX24)*CZ24*(SIN(2*PI()*CU23/CY24)) -> -14.913237 | CV24: =CP24*(CW24/CX24)*CZ24*(SIN(2*PI()*CV23/CY24)) -> 39.539617 | CW24: =CW23 -> 1 | CX24: =CX23 -> 1.7 | CY24: =CY23 -> 0.11572 | CZ24: =CZ23 -> 0.5 | DA24: 2.2 | DB24: =2*PI()*((DA24/9.81)^0.5) -> 2.9754777 | DU24: Wux | EG24: =EG10 -> para triplay de 1" estructural | EN24: Toda vez que no se generar ningun cambio en el entrepiso, ninguna redistribucion de esfuerzos, ni colocacion alguna de cargas concentradas en la losa de entrepiso no se requiere reanalizarle. En realidad aun con los voladizos proyectados las cargas sobre los muros de carga donde estos voladizos cargaran se veran disminuidas al eliminarse la techumbre original de concreto. | FJ24: =FI24+FH25+FI26+FJ25 -> -0.5 | FK24: 1 | FL24: 3 | FP24: =FO24+FN25+FO26+FP25 -> 0 | FQ24: 3 | FV24: =FU24+FT25+FU26+FV25 -> 0 | FX24: =FX23*FX22 -> 0 | GH24: =GG24+GF25+GG26+GH25 -> -0.5 | GJ24: 3 | GN24: =GM24+GL25+GM26+GN25 -> -0.5 | GO24: 1 | GP24: 3 | GT24: =GS24+GR25+GS26+GT25 -> 0 | GV24: =GV23*GV22 -> 0 | HD24: =HC24+HB25+HC26+HD25 -> -0.5 | HF24: 1 | HG24: 0 | HJ24: =HI24+HH25+HI26+HJ25 -> -0.5 | HL24: 1 | HP24: =HO24+HN25+HO26+HP25 -> -0.5 | HR24: 1 | HS24: 0 | HV24: =HU24+HT25+HU26+HV25 -> -0.5 | HW24: 1 | HX24: 3 | HY24: 0 | IB24: =IA24+HZ25+IA26+IB25 -> 0 | ID24: =ID23*ID22 -> 0 | IJ24: voladizo | IK24: =FH42 -> 8111.8909 | IL24: =IK24*100 -> 811189.09 | IM24: =FH47 -> 2961.8227 | IN24: =IL24/2500 -> 324.47564 | IO24: =IM24/2500 -> 1.1847291 | IP24: critico | IY24: =#REF! -> #REF! | KC24: Block
L25: No contamos con un estudio de mecanica de suelos sin embargo sabemos que en el lugar se encontraron arenas por tanto se tomaran estos datos para la evaluacion sismica. | AE25: Vo= | AF25: velocidad de viento regional | BU25: =BU24*3600/1000 -> 11.52 | BV25: km/hra | CP25: =CW15 -> 37.331489 | CQ25: =CW9 -> 3.1109574 | CR25: =CP25*(CW25/CX25)*CZ25*(SIN(2*PI()*CR24/CY25)) -> 0 | CS25: =CP25*(CW25/CX25)*CZ25*(SIN(2*PI()*CS24/CY25)) -> 6.3877911 | CT25: =CP25*(CW25/CX25)*CZ25*(SIN(2*PI()*CT24/CY25)) -> -1.3399552 | CU25: =CP25*(CW25/CX25)*CZ25*(SIN(2*PI()*CU24/CY25)) -> 7.8385378 | CV25: =CP25*(CW25/CX25)*CZ25*(SIN(2*PI()*CV24/CY25)) -> -10.035749 | CW25: =CW24 -> 1 | CX25: =CX24 -> 1.7 | CY25: =CY24 -> 0.11572 | CZ25: =CZ24 -> 0.5 | DA25: 2 | DB25: =2*PI()*((DA25/9.81)^0.5) -> 2.8370067 | EG25: Fs = | EH25: 48 | EI25: lbs/plg^2 | FF25: momento | FG25: =(FG23*FG22*FG22/2)+(FG9*FG22/4) -> 8111.8909 | FI25: =FG25+FK25 -> 6750.0136 | FJ25: =IF(FL26=0,0,IF(FK24=3,0,IF(FM24=3,0,IF(FM24=2,-0.5,IF(FM24=1,0,-0.5))))) -> -0.5 | FK25: =FL23 -> -1361.8773 | FL25: 1 | FM25: =FM23 -> 1361.8773 | FN25: =IF(FL26=0,0,IF(FM24=3,0,IF(FK24=3,0,IF(FK24=2,-0.5,IF(FK24=1,0,(FL26/(FL26+FR26))*(-0.5)))))) -> 0 | FO25: =IF(FL24=0,FM26+FQ25,IF(FR24=0,FQ26+FM25,FM25+FQ25)) -> 1361.8773 | FP25: =IF(FR26=0,0,IF(FQ24=3,0,IF(FS24=3,0,IF(FS24=2,-0.5,IF(FS24=1,0,(FR26/(FR26+FL26))*(-0.5)))))) -> 0 | FQ25: =FR23 -> 0 | FR25: =FL25 -> 1 | FS25: =FS23 -> 0 | FT25: =IF(FR26=0,0,IF(FS24=3,0,IF(FQ24=3,0,IF(FQ24=2,-0.5,IF(FQ24=1,0,-0.5))))) -> 0 | FU25: =FS25+FW25 -> 0 | FW25: 0 | GD25: momento | GE25: =(GE23*GE22*GE22/2)+(GE9*GE22/4) -> 947.76364 | GG25: =GE25+GI25 -> -414.11364 | GH25: =IF(GJ26=0,0,IF(GI24=3,0,IF(GK24=3,0,IF(GK24=2,-0.5,IF(GK24=1,0,-0.5))))) -> -0.5 | GI25: =GJ23 -> -1361.8773 | GJ25: 1 | GK25: =GK23 -> 1361.8773 | GL25: =IF(GJ26=0,0,IF(GK24=3,0,IF(GI24=3,0,IF(GI24=2,-0.5,IF(GI24=1,0,(GJ26/(GJ26+GP26))*(-0.5)))))) -> -0.25 | GM25: =IF(GJ24=0,GK26+GO25,IF(GP24=0,GO26+GK25,GK25+GO25)) -> 0 | GN25: =IF(GP26=0,0,IF(GO24=3,0,IF(GQ24=3,0,IF(GQ24=2,-0.5,IF(GQ24=1,0,(GP26/(GP26+GJ26))*(-0.5)))))) -> -0.25 | GO25: =GP23 -> -1361.8773 | GP25: =GJ25 -> 1 | GQ25: =GQ23 -> 1361.8773 | GR25: =IF(GP26=0,0,IF(GQ24=3,0,IF(GO24=3,0,IF(GO24=2,-0.5,IF(GO24=1,0,-0.5))))) -> 0 | GS25: =GQ25+GU25 -> 1361.8773 | GU25: 0 | GZ25: momento | HC25: =HA25+HE25 -> -173.89072 | HD25: =IF(HF26=0,0,IF(HE24=3,0,IF(HG24=3,0,IF(HG24=2,-0.5,IF(HG24=1,0,-0.5))))) -> -0.5 | HE25: =HF23 -> -173.89072 | HF25: 1 | HG25: =HG23 -> 153.82759 | HH25: =IF(HF26=0,0,IF(HG24=3,0,IF(HE24=3,0,IF(HE24=2,-0.5,IF(HE24=1,0,(HF26/(HF26+HL26))*(-0.5)))))) -> -0.25 | HI25: =IF(HF24=0,HG26+HK25,IF(HL24=0,HK26+HG25,HG25+HK25)) -> 2.5078909 | HJ25: =IF(HL26=0,0,IF(HK24=3,0,IF(HM24=3,0,IF(HM24=2,-0.5,IF(HM24=1,0,(HL26/(HL26+HF26))*(-0.5)))))) -> -0.25 | HK25: =HL23 -> -151.3197 | HL25: 1 | HM25: =HM23 -> 151.3197 | HN25: =IF(HL26=0,0,IF(HM24=3,0,IF(HK24=3,0,IF(HK24=2,-0.5,IF(HK24=1,0,(HL26/(HL26+HR26))*(-0.5)))))) -> -0.25 | HO25: =IF(HL24=0,HM26+HQ25,IF(HR24=0,HQ26+HM25,HM25+HQ25)) -> 0 | HP25: =IF(HR26=0,0,IF(HQ24=3,0,IF(HS24=3,0,IF(HS24=2,-0.5,IF(HS24=1,0,(HR26/(HR26+HL26))*(-0.5)))))) -> -0.25 | HQ25: =HR23 -> -151.3197 | HR25: 1 | HS25: =HS23 -> 151.3197 | HT25: =IF(HR26=0,0,IF(HS24=3,0,IF(HQ24=3,0,IF(HQ24=2,-0.5,IF(HQ24=1,0,(HR26/(HR26+HX26))*(-0.5)))))) -> -0.375 | HU25: =IF(HR24=0,HS26+HW25,IF(HX24=0,HW26+HS25,HS25+HW25)) -> -1210.5576 | HV25: =IF(HX26=0,0,IF(HW24=3,0,IF(HY24=3,0,IF(HY24=2,-0.5,IF(HY24=1,0,(HX26/(HX26+HR26))*(-0.5)))))) -> -0.125 | HW25: =HX23 -> -1361.8773 | HX25: =HR25 -> 1 | HY25: =HY23 -> 1361.8773 | HZ25: =IF(HX26=0,0,IF(HY24=3,0,IF(HW24=3,0,IF(HW24=2,-0.5,IF(HW24=1,0,-0.5))))) -> 0 | IA25: =HY25+IC25 -> 1361.8773 | IC25: 0 | IJ25: semiarriostrado | IK25: =GF42 -> 1480.1955 | IL25: =IK25*100 -> 148019.55 | IM25: =GF47 -> 2961.8227 | IN25: =IL25/2500 -> 59.207818 | IO25: =IM25/2500 -> 1.1847291 | KC25: Block 1= Block Estructural 20x40, en todo caso en que se deban construir muros confinados se empleara este block. Para muros de relleno o muros pantalla se puede emplear block o tabique a elección del contratista. En ningún momento se ataran los muro pantalla a la estructura debiendo dejar una junta constructiva de mínimo 1/2" sellada con sicaflex o algún producto similar. En caso de desear modificar algún muro pantalla para integrarlo a la estructura favor de consultar primero para verificar los efectos sobre los marcos.
AD26: encontramos la siguiente roseta de los vientos para esta zona . | BU26: Promedio SAHOPE | BY26: Para paredes aisladas y anuncios C= | CC26: 1 | DX26: Wuy =Wux*.25 | EG26: Ib/Q = | EH26: 6.762 | EI26: plg^2/pie | FL26: =IF(FL24=0,0,FL25/FL24) -> 0.33333333 | FR26: =IF(FR24=0,0,FR25/FR24) -> 0 | GJ26: =IF(GJ24=0,0,GJ25/GJ24) -> 0.33333333 | GP26: =IF(GP24=0,0,GP25/GP24) -> 0.33333333 | HF26: =IF(HF24=0,0,HF25/HF24) -> 1 | HL26: =IF(HL24=0,0,HL25/HL24) -> 1 | HR26: =IF(HR24=0,0,HR25/HR24) -> 1 | HX26: =IF(HX24=0,0,HX25/HX24) -> 0.33333333 | IJ26: arriostrado | IK26: =HB42 -> 1529.2334 | IL26: =IK26*100 -> 152923.34 | IM26: =HB47 -> 2735.3075 | IN26: =IL26/2500 -> 61.169335 | IO26: =IM26/2500 -> 1.094123
BU27: De | BY27: P prom = | BZ27: =0.0048 -> 0.0048 | CA27: x | CB27: =CC26 -> 1 | CC27: x | CD27: =CF11 -> 13.3308 | CE27: ^2 = | CF27: =BZ27*CB27*(CD27^2) -> 0.8530091 | DD27: Solución | EG27: Condicion | EI27: Ws > = Wu | FF27: voladizo | FG27: =FG22*FG23 -> 5268.6 | FI27: =FG27 -> 5268.6 | FJ27: =(FI25+FN27)*FJ25 -> -3375.0068 | FL27: momento puro: | FM27: =FK7 -> 0 | FN27: =(FO25)*FN25 -> 0 | FO27: reacción | FP27: =(FO25)*FP25 -> 0 | FR27: momento puro: | FS27: =FQ7 -> 0 | FT27: =(FU25+FP27)*FT25 -> 0 | FU27: =FX24 -> 0 | GD27: voladizo | GE27: =GE22*GE23 -> 1756.2 | GG27: =GE27 -> 1756.2 | GH27: =(GG25+GL27)*GH25 -> 207.05682 | GJ27: momento puro: | GK27: =GI7 -> 0 | GL27: =(GM25)*GL25 -> 0 | GM27: reacción | GN27: =(GM25)*GN25 -> 0 | GP27: momento puro: | GQ27: =GO7 -> 0 | GR27: =(GS25+GN27)*GR25 -> 0 | GS27: =GV24 -> 0 | GZ27: voladizo | HA27: =HA22*HA23 -> 0 | HC27: =HA27 -> 0 | HD27: =(HC25+HH27)*HD25 -> 73.072622 | HF27: momento puro: | HG27: =HE7 -> 0 | HH27: =(HI25+HN27)*HH25 -> 27.74547 | HI27: reacción | HJ27: =(HI25+HN27)*HJ25 -> 27.74547 | HL27: momento puro: | HM27: =HK7 -> 0 | HN27: =(HO25+HT27)*HN25 -> -113.48977 | HO27: reacción | HP27: =(HO25+HT27)*HP25 -> -113.48977 | HR27: momento puro: | HS27: =HQ7 -> 0 | HT27: =(HU25)*HT25 -> 453.95909 | HU27: reacción | HV27: =(HU25)*HV25 -> 151.3197 | HX27: momento puro: | HY27: =HW7 -> 0 | HZ27: =(IA25+HV27)*HZ25 -> 0 | IA27: =ID24 -> 0
L28: Suelo Arenoso | AH28: Los Valores aqui mostrados nos dan una idea de los vientos tipicos. 8.8 m/s = 31.68 km/hra, sin embargo, tanto por observaciones propias como por los minimos que nos pide Reglamento de la Ley de Edificaciones del Estado de Baja California sabemos que podemos tener rafagas mucho muy superiores. Tenemos registradas por medicion directa velocidades de rafaga de hasta 110 km/hra. La CFE nos propone 125 km/hra. Por lo tanto emplearemos esta roseta para proponer una carga viva adicional, constante y emplearemos el valor de rafaga para el analisis por viento. | BU28: 1.7 | BV28: m/s | CH28: F= Fuerza | CJ28: CK= coheficiente por VzD | CM28: t= tiempo | DD28: En primero término se le recomendó al cliente demoler la techumbre original toda vez que esta es de losa inclincada de concreto de 10 cm y teja. Esto debido a que en primer lugar, realizar cortes y ampliaciones en concreto generaria juntas frias, en segundo lugar no podriamos preservar el mismo concepto arquitectonico si tuvieremos un pedazo de techo al que se le agrego otro; y finalmente, estariamos cargando con un peso muerto innecesario y esto sobre una estructura en voladizo. Aun cuando es realativamente sencillo diseñar una trabe lo suficientemente aperaltada para resistir un peso dado (por elevado que sea ) dejar cargas elevadas, asimetricas, en estructuras en voladizo es sumamente peligros ante efectos sismicos. | EC28: Mu=WxL^2 / 32 | EG28: =DW19 -> Carga en lbs/pie2 = | EH28: =DX19 -> 81.142177 | FH28: reacciones en el nudo | FI28: =FK38+FG27 -> 11367.361 | FJ28: =(FI25+FN28)*FJ25 -> -3375.0068 | FK28: =IF(FL24=0,0,IF(FM27=0,0,-1*(FM27/FL24))) -> 0 | FL28: reacciones | FM28: =IF(FL24=0,0,IF(FM27=0,0,FM27/FL24)) -> 0 | FN28: =(FO25+FJ27+FT27)*FN25 -> 0 | FO28: =IF(FL24=0,FQ38+FM39,IF(FR24=0,FQ39+FM38,FM38+FQ38)) -> -651.25227 | FP28: =(FO25+FJ27+FT27)*FP25 -> 0 | FQ28: =IF(FR24=0,0,IF(FS27=0,0,-1*(FS27/FR24))) -> 0 | FR28: reacciones | FS28: =IF(FR24=0,0,IF(FS27=0,0,FS27/FR24)) -> 0 | FT28: =(FU25+FP28)*FT25 -> 0 | FU28: =FS38+FU27 -> 0 | FV28: Cortante en el nudo | GF28: reacciones en el nudo | GG28: =GI38+GE27 -> 4302.4773 | GH28: =(GG25+GL28)*GH25 -> 232.93892 | GI28: =IF(GJ24=0,0,IF(GK27=0,0,-1*(GK27/GJ24))) -> 0 | GJ28: reacciones | GK28: =IF(GJ24=0,0,IF(GK27=0,0,GK27/GJ24)) -> 0 | GL28: =(GM25+GH27+GR27)*GL25 -> -51.764205 | GM28: =IF(GJ24=0,GO38+GK39,IF(GP24=0,GO39+GK38,GK38+GO38)) -> 5684.1455 | GN28: =(GM25+GH27+GR27)*GN25 -> -51.764205 | GO28: =IF(GP24=0,0,IF(GQ27=0,0,-1*(GQ27/GP24))) -> 0 | GP28: reacciones | GQ28: =IF(GP24=0,0,IF(GQ27=0,0,GQ27/GP24)) -> 0 | GR28: =(GS25+GN28)*GR25 -> 0 | GS28: =GQ38+GS27 -> 2664.5955 | GT28: Cortante en el nudo | HB28: reacciones en el nudo | HC28: =HE38+HA27 -> 901.28948 | HD28: =(HC25+HH28)*HD25 -> 80.009696 | HE28: =IF(HF24=0,0,IF(HG27=0,0,-1*(HG27/HF24))) -> 0 | HF28: reacciones | HG28: =IF(HF24=0,0,IF(HG27=0,0,HG27/HF24)) -> 0 | HH28: =(HI25+HD27+HN28)*HH25 -> 13.871323 | HI28: =IF(HF24=0,HK38+HG39,IF(HL24=0,HK39+HG38,HG38+HK38)) -> 2452.7036 | HJ28: =(HI25+HD27+HN28)*HJ25 -> 13.871323 | HK28: =IF(HL24=0,0,IF(HM27=0,0,-1*(HM27/HL24))) -> 0 | HL28: reacciones | HM28: =IF(HL24=0,0,IF(HM27=0,0,HM27/HL24)) -> 0 | HN28: =(HO25+HJ27+HT28)*HN25 -> -131.06581 | HO28: =IF(HL24=0,HQ38+HM39,IF(HR24=0,HQ39+HM38,HM38+HQ38)) -> 342.92116 | HP28: =(HO25+HJ27+HT28)*HP25 -> -131.06581 | HQ28: =IF(HR24=0,0,IF(HS27=0,0,-1*(HS27/HR24))) -> 0 | HR28: reacciones | HS28: =IF(HR24=0,0,IF(HS27=0,0,HS27/HR24)) -> 0 | HT28: =(HU25+HP27+HZ27)*HT25 -> 496.51776 | HU28: =IF(HR24=0,HW38+HS39,IF(HX24=0,HW39+HS38,HS38+HW38)) -> 4585.6479 | HV28: =(HU25+HP27+HZ27)*HV25 -> 165.50592 | HW28: =IF(HX24=0,0,IF(HY27=0,0,-1*(HY27/HX24))) -> 0 | HX28: reacciones | HY28: =IF(HX24=0,0,IF(HY27=0,0,HY27/HX24)) -> 0 | HZ28: =(IA25+HV28)*HZ25 -> 0 | IA28: =HY38+IA27 -> 2891.1106 | IB28: Cortante en el nudo | IK28: Efecto Rafaga = Impacto | IM28: Z req | IN28: =IN24 -> 324.47564 | IO28: x 3 = | IP28: =IN28*3 -> 973.42691
B29: Ingeniero Calculista | L29: Caracteristicas Promedio | BU29: =BU28*3600/1000 -> 6.12 | BV29: km/hra | BY29: P rafa = | BZ29: =BZ27 -> 0.0048 | CA29: x | CB29: =CB27 -> 1 | CC29: x | CD29: =CF13 -> 127.29062 | CE29: ^2 = | CF29: =BZ29*CB29*(CD29^2) -> 77.773935 | CH29: p= presion de diseno | CJ29: C: Coheficiente empuje | CM29: T= periodo alternante ( 18 d/v) | EH29: l = 20 Fs (Ib/Q) / Wu = | EI29: =(20*EH25*EH26/EH28) -> 80.001797 | EJ29: pulgadas | FJ29: =(FI25+FN29)*FJ25 -> -3375.0068 | FL29: Reacciones por cargas | FN29: =(FO25+FJ28+FT28)*FN25 -> 0 | FP29: =(FO25+FJ28+FT28)*FP25 -> 0 | FR29: Reacciones por cargas | FT29: =(FU25+FP29)*FT25 -> 0 | GH29: =(GG25+GL29)*GH25 -> 236.17418 | GJ29: Reacciones por cargas | GL29: =(GM25+GH28+GR28)*GL25 -> -58.23473 | GN29: =(GM25+GH28+GR28)*GN25 -> -58.23473 | GP29: Reacciones por cargas | GR29: =(GS25+GN29)*GR25 -> 0 | HD29: =(HC25+HH29)*HD25 -> 81.104428 | HF29: Reacciones por cargas | HH29: =(HI25+HD28+HN29)*HH25 -> 11.681859 | HJ29: =(HI25+HD28+HN29)*HJ25 -> 11.681859 | HL29: Reacciones por cargas | HN29: =(HO25+HJ28+HT29)*HN25 -> -129.24502 | HP29: =(HO25+HJ28+HT29)*HP25 -> -129.24502 | HR29: Reacciones por cargas | HT29: =(HU25+HP28+HZ28)*HT25 -> 503.10877 | HV29: =(HU25+HP28+HZ28)*HV25 -> 167.70292 | HX29: Reacciones por cargas | HZ29: =(IA25+HV29)*HZ25 -> 0 | IK29: vigaW | IL29: W 16x40 | IM29: 1195
B30: Ing. Arnoldo Coronado | M30: Densidad | P30: Angulo de Friccion | BU30: A | CH30: d= diametro | CJ30: To = periodo de la estructura | CM30: v = velocidad | EN30: Corniza | FJ30: =(FI25+FN30)*FJ25 -> -3375.0068 | FK30: =IF(FL24=0,0,IF(FK11=0,0,IF(FK12=0,0,FK12*(FL24-FK11)/FL24))) -> 0 | FL30: puntual 1 | FM30: =IF(FL24=0,0,IF(FK11=0,0,IF(FK12=0,0,FK12*FK11/FL24))) -> 0 | FN30: =(FO25+FJ29+FT29)*FN25 -> 0 | FP30: =(FO25+FJ29+FT29)*FP25 -> 0 | FQ30: =IF(FR24=0,0,IF(FQ11=0,0,IF(FQ12=0,0,FQ12*(FR24-FQ11)/FR24))) -> 0 | FR30: puntual 1 | FS30: =IF(FR24=0,0,IF(FQ11=0,0,IF(FQ12=0,0,FQ12*FQ11/FR24))) -> 0 | FT30: =(FU25+FP30)*FT25 -> 0 | GH30: =(GG25+GL30)*GH25 -> 236.57859 | GI30: =IF(GJ24=0,0,IF(GI11=0,0,IF(GI12=0,0,GI12*(GJ24-GI11)/GJ24))) -> 0 | GJ30: puntual 1 | GK30: =IF(GJ24=0,0,IF(GI11=0,0,IF(GI12=0,0,GI12*GI11/GJ24))) -> 0 | GL30: =(GM25+GH29+GR29)*GL25 -> -59.043546 | GN30: =(GM25+GH29+GR29)*GN25 -> -59.043546 | GO30: =IF(GP24=0,0,IF(GO11=0,0,IF(GO12=0,0,GO12*(GP24-GO11)/GP24))) -> 0 | GP30: puntual 1 | GQ30: =IF(GP24=0,0,IF(GO11=0,0,IF(GO12=0,0,GO12*GO11/GP24))) -> 0 | GR30: =(GS25+GN30)*GR25 -> 0 | HD30: =(HC25+HH30)*HD25 -> 81.331028 | HE30: =IF(HF24=0,0,IF(HE11=0,0,IF(HE12=0,0,HE12*(HF24-HE11)/HF24))) -> 250.78909 | HF30: puntual 1 | HG30: =IF(HF24=0,0,IF(HE11=0,0,IF(HE12=0,0,HE12*HE11/HF24))) -> 27.865455 | HH30: =(HI25+HD29+HN30)*HH25 -> 11.22866 | HJ30: =(HI25+HD29+HN30)*HJ25 -> 11.22866 | HK30: =IF(HL24=0,0,IF(HK11=0,0,IF(HK12=0,0,HK12*(HL24-HK11)/HL24))) -> 0 | HL30: puntual 1 | HM30: =IF(HL24=0,0,IF(HK11=0,0,IF(HK12=0,0,HK12*HK11/HL24))) -> 0 | HN30: =(HO25+HJ29+HT30)*HN25 -> -128.52696 | HP30: =(HO25+HJ29+HT30)*HP25 -> -128.52696 | HQ30: =IF(HR24=0,0,IF(HQ11=0,0,IF(HQ12=0,0,HQ12*(HR24-HQ11)/HR24))) -> 0 | HR30: puntual 1 | HS30: =IF(HR24=0,0,IF(HQ11=0,0,IF(HQ12=0,0,HQ12*HQ11/HR24))) -> 0 | HT30: =(HU25+HP29+HZ29)*HT25 -> 502.42597 | HV30: =(HU25+HP29+HZ29)*HV25 -> 167.47532 | HW30: =IF(HX24=0,0,IF(HW11=0,0,IF(HW12=0,0,HW12*(HX24-HW11)/HX24))) -> 0 | HX30: puntual 1 | HY30: =IF(HX24=0,0,IF(HW11=0,0,IF(HW12=0,0,HW12*HW11/HX24))) -> 0 | HZ30: =(IA25+HV30)*HZ25 -> 0 | IY30: Trabes T3
B31: Cedula: | L31: Peso 3: | M31: 2060 | N31: kg/m4 | O31: Ang 3 | P31: 30 | Q31: no cohesivo | BU31: 8.8 | BV31: m/s | BY31: La presion estatica se considerara como carga viva constante para las techumbres y canceleria | EF31: carga uniforme | FJ31: =(FI25+FN31)*FJ25 -> -3375.0068 | FK31: =IF(FL24=0,0,IF(FK13=0,0,IF(FK14=0,0,FK14*(FL24-FK13)/FL24))) -> 0 | FL31: puntual 2 | FM31: =IF(FL24=0,0,IF(FK13=0,0,IF(FK14=0,0,FK14*FK13/FL24))) -> 0 | FN31: =(FO25+FJ30+FT30)*FN25 -> 0 | FP31: =(FO25+FJ30+FT30)*FP25 -> 0 | FQ31: =IF(FR24=0,0,IF(FQ13=0,0,IF(FQ14=0,0,FQ14*(FR24-FQ13)/FR24))) -> 0 | FR31: puntual 2 | FS31: =IF(FR24=0,0,IF(FQ13=0,0,IF(FQ14=0,0,FQ14*FQ13/FR24))) -> 0 | FT31: =(FU25+FP31)*FT25 -> 0 | GH31: =(GG25+GL31)*GH25 -> 236.62914 | GI31: =IF(GJ24=0,0,IF(GI13=0,0,IF(GI14=0,0,GI14*(GJ24-GI13)/GJ24))) -> 0 | GJ31: puntual 2 | GK31: =IF(GJ24=0,0,IF(GI13=0,0,IF(GI14=0,0,GI14*GI13/GJ24))) -> 0 | GL31: =(GM25+GH30+GR30)*GL25 -> -59.144648 | GN31: =(GM25+GH30+GR30)*GN25 -> -59.144648 | GO31: =IF(GP24=0,0,IF(GO13=0,0,IF(GO14=0,0,GO14*(GP24-GO13)/GP24))) -> 0 | GP31: puntual 2 | GQ31: =IF(GP24=0,0,IF(GO13=0,0,IF(GO14=0,0,GO14*GO13/GP24))) -> 0 | GR31: =(GS25+GN31)*GR25 -> 0 | HD31: =(HC25+HH31)*HD25 -> 81.38193 | HE31: =IF(HF24=0,0,IF(HE13=0,0,IF(HE14=0,0,HE14*(HF24-HE13)/HF24))) -> 0 | HF31: puntual 2 | HG31: =IF(HF24=0,0,IF(HE13=0,0,IF(HE14=0,0,HE14*HE13/HF24))) -> 0 | HH31: =(HI25+HD30+HN31)*HH25 -> 11.126855 | HJ31: =(HI25+HD30+HN31)*HJ25 -> 11.126855 | HK31: =IF(HL24=0,0,IF(HK13=0,0,IF(HK14=0,0,HK14*(HL24-HK13)/HL24))) -> 0 | HL31: puntual 2 | HM31: =IF(HL24=0,0,IF(HK13=0,0,IF(HK14=0,0,HK14*HK13/HL24))) -> 0 | HN31: =(HO25+HJ30+HT31)*HN25 -> -128.34634 | HP31: =(HO25+HJ30+HT31)*HP25 -> -128.34634 | HQ31: =IF(HR24=0,0,IF(HQ13=0,0,IF(HQ14=0,0,HQ14*(HR24-HQ13)/HR24))) -> 0 | HR31: puntual 2 | HS31: =IF(HR24=0,0,IF(HQ13=0,0,IF(HQ14=0,0,HQ14*HQ13/HR24))) -> 0 | HT31: =(HU25+HP30+HZ30)*HT25 -> 502.1567 | HV31: =(HU25+HP30+HZ30)*HV25 -> 167.38557 | HW31: =IF(HX24=0,0,IF(HW13=0,0,IF(HW14=0,0,HW14*(HX24-HW13)/HX24))) -> 0 | HX31: puntual 2 | HY31: =IF(HX24=0,0,IF(HW13=0,0,IF(HW14=0,0,HW14*HW13/HX24))) -> 0 | HZ31: =(IA25+HV31)*HZ25 -> 0 | IK31: Conectores | IY31: =RM31 -> 0
B32: INGENIERO CIVIL.: 5533080 | L32: Cap Carga | M32: 11 | N32: ton/m2 | O32: con factores de seg | U32: 2007 | BU32: =BU31*3600/1000 -> 31.68 | BV32: km/hra | CH32: p= | CI32: =CN18 -> 933.28723 | CJ32: C= | CK32: 1.7 | CL32: d= | CM32: 0.5 | DV32: Fb= | DW32: 2310 | DX32: kg/cm^2 | DZ32: Fy = | EA32: 2130 | EB32: kg/cm^2 | EG32: claro en pulgadas | EH32: =EH16 -> 12 | EN32: Corniza de Cantera aproximadamente 0.06 m^2 osea 0.06 m^3 x cada metro lineal. Lo que equivale a unos 150 kg-metro lineal | FJ32: =(FI25+FN32)*FJ25 -> -3375.0068 | FK32: =IF(FL24=0,0,IF(FK15=0,0,IF(FK16=0,0,FK16*(FL24-FK15)/FL24))) -> 0 | FL32: puntual 3 | FM32: =IF(FL24=0,0,IF(FK15=0,0,IF(FK16=0,0,FK16*FK15/FL24))) -> 0 | FN32: =(FO25+FJ31+FT31)*FN25 -> 0 | FP32: =(FO25+FJ31+FT31)*FP25 -> 0 | FQ32: =IF(FR24=0,0,IF(FQ15=0,0,IF(FQ16=0,0,FQ16*(FR24-FQ15)/FR24))) -> 0 | FR32: puntual 3 | FS32: =IF(FR24=0,0,IF(FQ15=0,0,IF(FQ16=0,0,FQ16*FQ15/FR24))) -> 0 | FT32: =(FU25+FP32)*FT25 -> 0 | GH32: =(GG25+GL32)*GH25 -> 236.63546 | GI32: =IF(GJ24=0,0,IF(GI15=0,0,IF(GI16=0,0,GI16*(GJ24-GI15)/GJ24))) -> 0 | GJ32: puntual 3 | GK32: =IF(GJ24=0,0,IF(GI15=0,0,IF(GI16=0,0,GI16*GI15/GJ24))) -> 0 | GL32: =(GM25+GH31+GR31)*GL25 -> -59.157286 | GN32: =(GM25+GH31+GR31)*GN25 -> -59.157286 | GO32: =IF(GP24=0,0,IF(GO15=0,0,IF(GO16=0,0,GO16*(GP24-GO15)/GP24))) -> 0 | GP32: puntual 3 | GQ32: =IF(GP24=0,0,IF(GO15=0,0,IF(GO16=0,0,GO16*GO15/GP24))) -> 0 | GR32: =(GS25+GN32)*GR25 -> 0 | HD32: =(HC25+HH32)*HD25 -> 81.393591 | HE32: =IF(HF24=0,0,IF(HE15=0,0,IF(HE16=0,0,HE16*(HF24-HE15)/HF24))) -> 0 | HF32: puntual 3 | HG32: =IF(HF24=0,0,IF(HE15=0,0,IF(HE16=0,0,HE16*HE15/HF24))) -> 0 | HH32: =(HI25+HD31+HN32)*HH25 -> 11.103534 | HJ32: =(HI25+HD31+HN32)*HJ25 -> 11.103534 | HK32: =IF(HL24=0,0,IF(HK15=0,0,IF(HK16=0,0,HK16*(HL24-HK15)/HL24))) -> 0 | HL32: puntual 3 | HM32: =IF(HL24=0,0,IF(HK15=0,0,IF(HK16=0,0,HK16*HK15/HL24))) -> 0 | HN32: =(HO25+HJ31+HT32)*HN25 -> -128.30396 | HP32: =(HO25+HJ31+HT32)*HP25 -> -128.30396 | HQ32: =IF(HR24=0,0,IF(HQ15=0,0,IF(HQ16=0,0,HQ16*(HR24-HQ15)/HR24))) -> 0 | HR32: puntual 3 | HS32: =IF(HR24=0,0,IF(HQ15=0,0,IF(HQ16=0,0,HQ16*HQ15/HR24))) -> 0 | HT32: =(HU25+HP31+HZ31)*HT25 -> 502.08897 | HV32: =(HU25+HP31+HZ31)*HV25 -> 167.36299 | HW32: =IF(HX24=0,0,IF(HW15=0,0,IF(HW16=0,0,HW16*(HX24-HW15)/HX24))) -> 0 | HX32: puntual 3 | HY32: =IF(HX24=0,0,IF(HW15=0,0,IF(HW16=0,0,HW16*HW15/HX24))) -> 0 | HZ32: =(IA25+HV32)*HZ25 -> 0 | IK32: Reaccion M | IO32: Area Req | KC32: Block 2= Block liviano para divisiones. Este es de 10 cm de ancho y se empleara en el muro de la recamara que se encuentra sobre el voladizo así como en el muro en el eje h sobre trabe. Ambos en el Segundo nivel.
BU33: durante la epoca de vientos de santa ana tenemos rafagas en la region de hasta: | CH33: Ck= | CI33: 1 | CJ33: T= | CK33: =18*(CM32/CM33) -> 0.11572 | CL33: v= | CM33: =CF29 -> 77.773935 | DV33: Wu y = | DW33: =EH36 -> 120.97561 | DZ33: Wu x = | EA33: =DW33*0.25 -> 30.243902 | EG33: claro en pies= | EH33: =EH32/12 -> 1 | FJ33: =(FI25+FN33)*FJ25 -> -3375.0068 | FK33: =IF(FL24=0,0,IF(FK17=0,0,IF(FK18=0,0,FK18*(FL24-FK17)/FL24))) -> 0 | FL33: puntual 4 | FM33: =IF(FL24=0,0,IF(FK17=0,0,IF(FK18=0,0,FK18*FK17/FL24))) -> 0 | FN33: =(FO25+FJ32+FT32)*FN25 -> 0 | FP33: =(FO25+FJ32+FT32)*FP25 -> 0 | FQ33: =IF(FR24=0,0,IF(FQ17=0,0,IF(FQ18=0,0,FQ18*(FR24-FQ17)/FR24))) -> 0 | FR33: puntual 4 | FS33: =IF(FR24=0,0,IF(FQ17=0,0,IF(FQ18=0,0,FQ18*FQ17/FR24))) -> 0 | FT33: =(FU25+FP33)*FT25 -> 0 | GH33: =(GG25+GL33)*GH25 -> 236.63625 | GI33: =IF(GJ24=0,0,IF(GI17=0,0,IF(GI18=0,0,GI18*(GJ24-GI17)/GJ24))) -> 0 | GJ33: puntual 4 | GK33: =IF(GJ24=0,0,IF(GI17=0,0,IF(GI18=0,0,GI18*GI17/GJ24))) -> 0 | GL33: =(GM25+GH32+GR32)*GL25 -> -59.158865 | GN33: =(GM25+GH32+GR32)*GN25 -> -59.158865 | GO33: =IF(GP24=0,0,IF(GO17=0,0,IF(GO18=0,0,GO18*(GP24-GO17)/GP24))) -> 0 | GP33: puntual 4 | GQ33: =IF(GP24=0,0,IF(GO17=0,0,IF(GO18=0,0,GO18*GO17/GP24))) -> 0 | GR33: =(GS25+GN33)*GR25 -> 0 | HD33: =(HC25+HH33)*HD25 -> 81.396274 | HE33: =IF(HF24=0,0,IF(HE17=0,0,IF(HE18=0,0,HE18*(HF24-HE17)/HF24))) -> 0 | HF33: puntual 4 | HG33: =IF(HF24=0,0,IF(HE17=0,0,IF(HE18=0,0,HE18*HE17/HF24))) -> 0 | HH33: =(HI25+HD32+HN33)*HH25 -> 11.098168 | HJ33: =(HI25+HD32+HN33)*HJ25 -> 11.098168 | HK33: =IF(HL24=0,0,IF(HK17=0,0,IF(HK18=0,0,HK18*(HL24-HK17)/HL24))) -> 0 | HL33: puntual 4 | HM33: =IF(HL24=0,0,IF(HK17=0,0,IF(HK18=0,0,HK18*HK17/HL24))) -> 0 | HN33: =(HO25+HJ32+HT33)*HN25 -> -128.29415 | HP33: =(HO25+HJ32+HT33)*HP25 -> -128.29415 | HQ33: =IF(HR24=0,0,IF(HQ17=0,0,IF(HQ18=0,0,HQ18*(HR24-HQ17)/HR24))) -> 0 | HR33: puntual 4 | HS33: =IF(HR24=0,0,IF(HQ17=0,0,IF(HQ18=0,0,HQ18*HQ17/HR24))) -> 0 | HT33: =(HU25+HP32+HZ32)*HT25 -> 502.07307 | HV33: =(HU25+HP32+HZ32)*HV25 -> 167.35769 | HW33: =IF(HX24=0,0,IF(HW17=0,0,IF(HW18=0,0,HW18*(HX24-HW17)/HX24))) -> 0 | HX33: puntual 4 | HY33: =IF(HX24=0,0,IF(HW17=0,0,IF(HW18=0,0,HW18*HW17/HX24))) -> 0 | HZ33: =(IA25+HV33)*HZ25 -> 0 | IK33: =MAX(IM14:IM17) -> 10112.756 | IO33: =IK33/2500 -> 4.0451023
B34: Ingeniero Responsble | L34: Antecedentes Eólicos | CH34: t= | CI34: 0-->1 | CJ34: To= | CK34: 1 | DV34: L= | DW34: 3 | DX34: mts | EG34: carga= | EH34: =EH28 -> 81.142177 | EI34: lbs/pie^2 | FJ34: =(FI25+FN34)*FJ25 -> -3375.0068 | FK34: =IF(FL24=0,0,IF(FK19=0,0,IF(FK20=0,0,FK20*(FL24-FK19)/FL24))) -> 0 | FL34: puntual 5 | FM34: =IF(FL24=0,0,IF(FK19=0,0,IF(FK20=0,0,FK20*FK19/FL24))) -> 0 | FN34: =(FO25+FJ33+FT33)*FN25 -> 0 | FP34: =(FO25+FJ33+FT33)*FP25 -> 0 | FQ34: =IF(FR24=0,0,IF(FQ19=0,0,IF(FQ20=0,0,FQ20*(FR24-FQ19)/FR24))) -> 0 | FR34: puntual 5 | FS34: =IF(FR24=0,0,IF(FQ19=0,0,IF(FQ20=0,0,FQ20*FQ19/FR24))) -> 0 | FT34: =(FU25+FP34)*FT25 -> 0 | GH34: =(GG25+GL34)*GH25 -> 236.63635 | GI34: =IF(GJ24=0,0,IF(GI19=0,0,IF(GI20=0,0,GI20*(GJ24-GI19)/GJ24))) -> 0 | GJ34: puntual 5 | GK34: =IF(GJ24=0,0,IF(GI19=0,0,IF(GI20=0,0,GI20*GI19/GJ24))) -> 0 | GL34: =(GM25+GH33+GR33)*GL25 -> -59.159063 | GN34: =(GM25+GH33+GR33)*GN25 -> -59.159063 | GO34: =IF(GP24=0,0,IF(GO19=0,0,IF(GO20=0,0,GO20*(GP24-GO19)/GP24))) -> 0 | GP34: puntual 5 | GQ34: =IF(GP24=0,0,IF(GO19=0,0,IF(GO20=0,0,GO20*GO19/GP24))) -> 0 | GR34: =(GS25+GN34)*GR25 -> 0 | HD34: =(HC25+HH34)*HD25 -> 81.396892 | HE34: =IF(HF24=0,0,IF(HE19=0,0,IF(HE20=0,0,HE20*(HF24-HE19)/HF24))) -> 0 | HF34: puntual 5 | HG34: =IF(HF24=0,0,IF(HE19=0,0,IF(HE20=0,0,HE20*HE19/HF24))) -> 0 | HH34: =(HI25+HD33+HN34)*HH25 -> 11.096932 | HJ34: =(HI25+HD33+HN34)*HJ25 -> 11.096932 | HK34: =IF(HL24=0,0,IF(HK19=0,0,IF(HK20=0,0,HK20*(HL24-HK19)/HL24))) -> 0 | HL34: puntual 5 | HM34: =IF(HL24=0,0,IF(HK19=0,0,IF(HK20=0,0,HK20*HK19/HL24))) -> 0 | HN34: =(HO25+HJ33+HT34)*HN25 -> -128.29189 | HP34: =(HO25+HJ33+HT34)*HP25 -> -128.29189 | HQ34: =IF(HR24=0,0,IF(HQ19=0,0,IF(HQ20=0,0,HQ20*(HR24-HQ19)/HR24))) -> 0 | HR34: puntual 5 | HS34: =IF(HR24=0,0,IF(HQ19=0,0,IF(HQ20=0,0,HQ20*HQ19/HR24))) -> 0 | HT34: =(HU25+HP33+HZ33)*HT25 -> 502.0694 | HV34: =(HU25+HP33+HZ33)*HV25 -> 167.35647 | HW34: =IF(HX24=0,0,IF(HW19=0,0,IF(HW20=0,0,HW20*(HX24-HW19)/HX24))) -> 0 | HX34: puntual 5 | HY34: =IF(HX24=0,0,IF(HW19=0,0,IF(HW20=0,0,HW20*HW19/HX24))) -> 0 | HZ34: =(IA25+HV34)*HZ25 -> 0 | IK34: Ing | IL34: cm | IM34: A req | IN34: Long cms | IO34: Long Ing
B35: Ing. Edgar López Martínez | L35: La zona recibe vientos fuertes durante epocas de Santa Ana y Tormentas | CH35: t= | CI35: 0 | CJ35: 0.25 | CK35: 0.5 | CL35: 0.75 | CM35: 1 | CN35: max abs | DW35: Mu y = Wu x L^2 / 8 | DX35: =EH38 -> 136.09756 | DY35: kg - m | EA35: =DX35*100 -> 13609.756 | EB35: kg - cm | EG35: W = | EH35: =EH34*EH33 -> 81.142177 | FJ35: =(FI25+FN35)*FJ25 -> -3375.0068 | FK35: =IF(FL24=0,0,IF(FK9=0,0,FK9*FL24/2)) -> 2634.3 | FL35: uniforme | FM35: =FK35 -> 2634.3 | FN35: =(FO25+FJ34+FT34)*FN25 -> 0 | FP35: =(FO25+FJ34+FT34)*FP25 -> 0 | FQ35: =IF(FR24=0,0,IF(FQ9=0,0,FQ9*FR24/2)) -> 0 | FR35: uniforme | FS35: =FQ35 -> 0 | FT35: =(FU25+FP35)*FT25 -> 0 | GH35: =(GG25+GL35)*GH25 -> 236.63636 | GI35: =IF(GJ24=0,0,IF(GI9=0,0,GI9*GJ24/2)) -> 2634.3 | GJ35: uniforme | GK35: =GI35 -> 2634.3 | GL35: =(GM25+GH34+GR34)*GL25 -> -59.159087 | GN35: =(GM25+GH34+GR34)*GN25 -> -59.159087 | GO35: =IF(GP24=0,0,IF(GO9=0,0,GO9*GP24/2)) -> 2634.3 | GP35: uniforme | GQ35: =GO35 -> 2634.3 | GR35: =(GS25+GN35)*GR25 -> 0 | HD35: =(HC25+HH35)*HD25 -> 81.397034 | HE35: =IF(HF24=0,0,IF(HE9=0,0,HE9*HF24/2)) -> 878.1 | HF35: uniforme | HG35: =HE35 -> 878.1 | HH35: =(HI25+HD34+HN35)*HH25 -> 11.096647 | HJ35: =(HI25+HD34+HN35)*HJ25 -> 11.096647 | HK35: =IF(HL24=0,0,IF(HK9=0,0,HK9*HL24/2)) -> 878.1 | HL35: uniforme | HM35: =HK35 -> 878.1 | HN35: =(HO25+HJ34+HT35)*HN25 -> -128.29137 | HP35: =(HO25+HJ34+HT35)*HP25 -> -128.29137 | HQ35: =IF(HR24=0,0,IF(HQ9=0,0,HQ9*HR24/2)) -> 878.1 | HR35: uniforme | HS35: =HQ35 -> 878.1 | HT35: =(HU25+HP34+HZ34)*HT25 -> 502.06855 | HV35: =(HU25+HP34+HZ34)*HV25 -> 167.35618 | HW35: =IF(HX24=0,0,IF(HW9=0,0,HW9*HX24/2)) -> 2634.3 | HX35: uniforme | HY35: =HW35 -> 2634.3 | HZ35: =(IA25+HV35)*HZ25 -> 0 | IJ35: Placa de 1/2 | IK35: 0.5 | IL35: =IK35*2.54 -> 1.27 | IM35: =IO33 -> 4.0451023 | IN35: =IM35/IL35 -> 3.18512 | IO35: =IN35/2.54 -> 1.2539842 | IY35: Trabes T4 | KC35: Concreto
BU36: =BU37*1000/3600 -> 30.555556 | BV36: =BV31 -> m/s | CF36: 6 | CH36: F1 = | CI36: =CI32*(CI33/CK32)*CM32*(SIN(2*PI()*CI35/CK33)) -> 0 | CJ36: =CI32*(CI33/CK32)*CM32*(SIN(2*PI()*CJ35/CK33)) -> 232.12189 | CK36: =CI32*(CI33/CK32)*CM32*(SIN(2*PI()*CK35/CK33)) -> 247.80017 | CL36: =CI32*(CI33/CK32)*CM32*(SIN(2*PI()*CL35/CK33)) -> 32.415516 | CM36: =CI32*(CI33/CK32)*CM32*(SIN(2*PI()*CM35/CK33)) -> -213.1952 | CN36: =MAX((CJ36:CM36),ABS(MIN(CJ36:CM36))) -> 247.80017 | DW36: Mu=Wu y L^2 / 32 = | DX36: =EA33*(DW34^2)/32 -> 8.5060976 | DY36: =DY35 -> kg - m | DZ36: =DX36*100 -> 850.60976 | EA36: =EB35 -> kg - cm | EG36: W siu = | EH36: =EH35*3.28/2.2 -> 120.97561 | FJ36: =(FI25+FN36)*FJ25 -> -3375.0068 | FK36: =IF(FL24=0,0,IF(FK10=0,0,FK10*FL24/2)) -> 89.454545 | FL36: p.p | FM36: =FK36 -> 89.454545 | FN36: =(FO25+FJ35+FT35)*FN25 -> 0 | FP36: =(FO25+FJ35+FT35)*FP25 -> 0 | FQ36: =IF(FR24=0,0,IF(FQ10=0,0,FQ10*FR24/2)) -> 0 | FR36: p.p | FS36: =FQ36 -> 0 | FT36: =(FU25+FP36)*FT25 -> 0 | GH36: =(GG25+GL36)*GH25 -> 236.63636 | GI36: =IF(GJ24=0,0,IF(GI10=0,0,GI10*GJ24/2)) -> 89.454545 | GJ36: p.p | GK36: =GI36 -> 89.454545 | GL36: =(GM25+GH35+GR35)*GL25 -> -59.15909 | GN36: =(GM25+GH35+GR35)*GN25 -> -59.15909 | GO36: =IF(GP24=0,0,IF(GO10=0,0,GO10*GP24/2)) -> 89.454545 | GP36: p.p | GQ36: =GO36 -> 89.454545 | GR36: =(GS25+GN36)*GR25 -> 0 | HD36: =(HC25+HH36)*HD25 -> 81.397067 | HE36: =IF(HF24=0,0,IF(HE10=0,0,HE10*HF24/2)) -> 29.818182 | HF36: p.p | HG36: =HE36 -> 29.818182 | HH36: =(HI25+HD35+HN36)*HH25 -> 11.096581 | HI36: =2.44*36/12 -> 7.32 | HJ36: =(HI25+HD35+HN36)*HJ25 -> 11.096581 | HK36: =IF(HL24=0,0,IF(HK10=0,0,HK10*HL24/2)) -> 29.818182 | HL36: p.p | HM36: =HK36 -> 29.818182 | HN36: =(HO25+HJ35+HT36)*HN25 -> -128.29125 | HP36: =(HO25+HJ35+HT36)*HP25 -> -128.29125 | HQ36: =IF(HR24=0,0,IF(HQ10=0,0,HQ10*HR24/2)) -> 29.818182 | HR36: p.p | HS36: =HQ36 -> 29.818182 | HT36: =(HU25+HP35+HZ35)*HT25 -> 502.06835 | HV36: =(HU25+HP35+HZ35)*HV25 -> 167.35612 | HW36: =IF(HX24=0,0,IF(HW10=0,0,HW10*HX24/2)) -> 89.454545 | HX36: p.p | HY36: =HW36 -> 89.454545 | HZ36: =(IA25+HV36)*HZ25 -> 0 | IJ36: Placa de 5/8 | IK36: =5/8 -> 0.625 | IL36: =IK36*2.54 -> 1.5875 | IM36: =IM35 -> 4.0451023 | IN36: =IM36/IL36 -> 2.548096 | IO36: =IN36/2.54 -> 1.0031874 | IY36: =#REF! -> #REF! | KC36: El calculo se llevo a cabo suponiendo concreto f'c 200, de no ser mezclado en obra deberá contratarse resistente a la acción de sulfatos y condiciones de medio ambiente adversas, teniendo cuidado de verificar revenimiento y tomar muestras (cilindros) del concreto suministrado.
BU37: 110 | BV37: km/hra | CH37: F2 = | CI37: =CI32*(CI33/CK32)*CM32*(SIN(2*PI()*CI36/CK33)) -> 0 | CJ37: =CI32*(CI33/CK32)*CM32*(SIN(2*PI()*CJ36/CK33)) -> -171.57294 | CK37: =CI32*(CI33/CK32)*CM32*(SIN(2*PI()*CK36/CK33)) -> 191.48743 | CL37: =CI32*(CI33/CK32)*CM32*(SIN(2*PI()*CL36/CK33)) -> 188.21749 | CM37: =CI32*(CI33/CK32)*CM32*(SIN(2*PI()*CM36/CK33)) -> -234.82305 | CN37: =MAX((CJ37:CM37),ABS(MIN(CJ37:CM37))) -> 234.82305 | DV37: Sx= | DW37: =EA35/(DW32*0.9) -> 6.5462992 | EG37: Claro largueros = | EH37: 3 | FJ37: =(FI25+FN37)*FJ25 -> -3375.0068 | FK37: =IF(FL24=0,0,-1*(FJ42+FN42)/FL24) -> 3375.0068 | FL37: dif. Mom. | FM37: =IF(FL24=0,0,(FJ42+FN42)/FL24) -> -3375.0068 | FN37: =(FO25+FJ36+FT36)*FN25 -> 0 | FP37: =(FO25+FJ36+FT36)*FP25 -> 0 | FQ37: =IF(FR24=0,0,-1*(FP42+FT42)/FR24) -> 0 | FR37: reacciones | FS37: =IF(FR24=0,0,(FP42+FT42)/FR24) -> 0 | FT37: =(FU25+FP37)*FT25 -> 0 | GH37: =(GG25+GL37)*GH25 -> 236.63636 | GI37: =IF(GJ24=0,0,-1*(GH42+GL42)/GJ24) -> -177.47727 | GJ37: dif. Mom. | GK37: =IF(GJ24=0,0,(GH42+GL42)/GJ24) -> 177.47727 | GL37: =(GM25+GH36+GR36)*GL25 -> -59.159091 | GN37: =(GM25+GH36+GR36)*GN25 -> -59.159091 | GO37: =IF(GP24=0,0,-1*(GN42+GR42)/GP24) -> 59.159091 | GP37: reacciones | GQ37: =IF(GP24=0,0,(GN42+GR42)/GP24) -> -59.159091 | GR37: =(GS25+GN37)*GR25 -> 0 | HD37: =(HC25+HH37)*HD25 -> 81.397074 | HE37: =IF(HF24=0,0,-1*(HD42+HH42)/HF24) -> -257.41779 | HF37: dif. Mom. | HG37: =IF(HF24=0,0,(HD42+HH42)/HF24) -> 257.41779 | HH37: =(HI25+HD36+HN37)*HH25 -> 11.096566 | HI37: =2.44*6/2 -> 7.32 | HJ37: =(HI25+HD36+HN37)*HJ25 -> 11.096566 | HK37: =IF(HL24=0,0,-1*(HJ42+HN42)/HL24) -> 351.58396 | HL37: reacciones | HM37: =IF(HL24=0,0,(HJ42+HN42)/HL24) -> -351.58396 | HN37: =(HO25+HJ36+HT37)*HN25 -> -128.29122 | HP37: =(HO25+HJ36+HT37)*HP25 -> -128.29122 | HQ37: =IF(HR24=0,0,-1*(HP42+HT42)/HR24) -> -1121.3312 | HR37: reacciones | HS37: =IF(HR24=0,0,(HP42+HT42)/HR24) -> 1121.3312 | HT37: =(HU25+HP36+HZ36)*HT25 -> 502.06831 | HV37: =(HU25+HP36+HZ36)*HV25 -> 167.3561 | HW37: =IF(HX24=0,0,-1*(HV42+HZ42)/HX24) -> -167.3561 | HX37: reacciones | HY37: =IF(HX24=0,0,(HV42+HZ42)/HX24) -> 167.3561 | HZ37: =(IA25+HV37)*HZ25 -> 0
CE38: 1 | CF38: maximo | DD38: En segundo termino se diseñó una estructura a base de trabes de acero colganteadas al para resolver el problema del voladizo. Sobre esta se depositara el peso de una techumbre realizada com material liviano: perfiles de acero rolados en frio, denzglas en el exterior, 100% aislada, y terminada al interior con tablaroca; quedando un techo de catedral esensialmente igual al que se demolió. | DV38: Sy= | DW38: =DZ36/(0.9*DW32) -> 0.4091437 | DY38: CF 4 cal 14 Sx efectivo = 13.6 y Sy = 4.36 | EG38: M = W L^2 / 8 = | EH38: =EH37*EH37*EH36/8 -> 136.09756 | FJ38: =(FI25+FN38)*FJ25 -> -3375.0068 | FK38: =SUM(FK28:FK37) -> 6098.7614 | FL38: suma | FM38: =SUM(FM28:FM37) -> -651.25227 | FN38: =(FO25+FJ37+FT37)*FN25 -> 0 | FP38: =(FO25+FJ37+FT37)*FP25 -> 0 | FQ38: =SUM(FQ28:FQ37) -> 0 | FR38: suma | FS38: =SUM(FS28:FS37) -> 0 | FT38: =(FU25+FP38)*FT25 -> 0 | GH38: =(GG25+GL38)*GH25 -> 236.63636 | GI38: =SUM(GI28:GI37) -> 2546.2773 | GJ38: suma | GK38: =SUM(GK28:GK37) -> 2901.2318 | GL38: =(GM25+GH37+GR37)*GL25 -> -59.159091 | GN38: =(GM25+GH37+GR37)*GN25 -> -59.159091 | GO38: =SUM(GO28:GO37) -> 2782.9136 | GP38: suma | GQ38: =SUM(GQ28:GQ37) -> 2664.5955 | GR38: =(GS25+GN38)*GR25 -> 0 | HD38: =(HC25+HH38)*HD25 -> 81.397076 | HE38: =SUM(HE28:HE37) -> 901.28948 | HF38: suma | HG38: =SUM(HG28:HG37) -> 1193.2014 | HH38: =(HI25+HD37+HN38)*HH25 -> 11.096563 | HJ38: =(HI25+HD37+HN38)*HJ25 -> 11.096563 | HK38: =SUM(HK28:HK37) -> 1259.5021 | HL38: suma | HM38: =SUM(HM28:HM37) -> 556.33422 | HN38: =(HO25+HJ37+HT38)*HN25 -> -128.29122 | HP38: =(HO25+HJ37+HT38)*HP25 -> -128.29122 | HQ38: =SUM(HQ28:HQ37) -> -213.41306 | HR38: suma | HS38: =SUM(HS28:HS37) -> 2029.2494 | HT38: =(HU25+HP37+HZ37)*HT25 -> 502.0683 | HV38: =(HU25+HP37+HZ37)*HV25 -> 167.3561 | HW38: =SUM(HW28:HW37) -> 2556.3984 | HX38: suma | HY38: =SUM(HY28:HY37) -> 2891.1106 | HZ38: =(IA25+HV38)*HZ25 -> 0
BU39: Vß = K1 K2 Vo | CN39: oscilaciones | EG39: E = | EH39: 29500000 | FJ39: =(FI25+FN39)*FJ25 -> -3375.0068 | FL39: cantiléver w | FN39: =(FO25+FJ38+FT38)*FN25 -> 0 | FP39: =(FO25+FJ38+FT38)*FP25 -> 0 | FQ39: =1.5*(FQ9+FQ10) -> 0 | FR39: cantiléver w | FT39: =(FU25+FP39)*FT25 -> 0 | GH39: =(GG25+GL39)*GH25 -> 236.63636 | GJ39: cantiléver w | GL39: =(GM25+GH38+GR38)*GL25 -> -59.159091 | GN39: =(GM25+GH38+GR38)*GN25 -> -59.159091 | GO39: =1.5*(GO9+GO10) -> 2723.7545 | GP39: cantiléver w | GR39: =(GS25+GN39)*GR25 -> 0 | HD39: =(HC25+HH39)*HD25 -> 81.397077 | HF39: cantiliver w | HH39: =(HI25+HD38+HN39)*HH25 -> 11.096562 | HJ39: =(HI25+HD38+HN39)*HJ25 -> 11.096562 | HL39: cantiliver w | HN39: =(HO25+HJ38+HT39)*HN25 -> -128.29121 | HP39: =(HO25+HJ38+HT39)*HP25 -> -128.29121 | HR39: cantiliver w | HT39: =(HU25+HP38+HZ38)*HT25 -> 502.0683 | HV39: =(HU25+HP38+HZ38)*HV25 -> 167.3561 | HW39: =1.5*(HW9+HW10) -> 2723.7545 | HX39: cantiliver w | HZ39: =(IA25+HV39)*HZ25 -> 0
B40: Antecedentes: | DV40: p.p = | DW40: 3.31 | DY40: cargas de= | DZ40: =DW43*DW42 -> 372.85683 | EG40: E siu = | EH40: =EH39*2.54*2.54/2.2 -> 86510091 | EN40: Observaciones | FJ40: =(FI25+FN40)*FJ25 -> -3375.0068 | FN40: =(FO25+FJ39+FT39)*FN25 -> 0 | FP40: =(FO25+FJ39+FT39)*FP25 -> 0 | FT40: =(FU25+FP40)*FT25 -> 0 | GH40: =(GG25+GL40)*GH25 -> 236.63636 | GL40: =(GM25+GH39+GR39)*GL25 -> -59.159091 | GN40: =(GM25+GH39+GR39)*GN25 -> -59.159091 | GR40: =(GS25+GN40)*GR25 -> 0 | HD40: =(HC25+HH40)*HD25 -> 81.397077 | HH40: =(HI25+HD39+HN40)*HH25 -> 11.096562 | HJ40: =(HI25+HD39+HN40)*HJ25 -> 11.096562 | HN40: =(HO25+HJ39+HT40)*HN25 -> -128.29121 | HP40: =(HO25+HJ39+HT40)*HP25 -> -128.29121 | HT40: =(HU25+HP39+HZ39)*HT25 -> 502.0683 | HV40: =(HU25+HP39+HZ39)*HV25 -> 167.3561 | HZ40: =(IA25+HV40)*HZ25 -> 0 | KC40: Acero
BQ41: Vß = | BR41: =AD20 -> 1.15 | BS41: x | BT41: =AD23 -> 1.15 | BU41: x | BV41: =BU25 -> 11.52 | CQ41: Se puede apreciar una convergencia de periodos de oscilacion en la direccion de viento en vortices de entre 3 a 4 segundos para velocidades que van de 5 a 132 km/hra. Esto equivale aproximadamente a elementos en voladizo (pendulos) de 2.2 a 4 metros por cuanto se debe tener cuidado de arriostrar los elementos adecuadamente a no mas de 1,5 metros entre arriostramiento. Los elementos que funcionen como verticales en la canceleria podrian ser una buena opcion para arriostrar los elementos en voladizo. En teoria se pudiera suponer que los canceles en si realizan estta funcion pero seria entonces vidrio quien resistiria la vibracion de la estructura lo cual no es recomendable. | DV41: p.tot = | DW41: =DW33+DW40 -> 124.28561 | DY41: =DZ40 -> 372.85683 | DZ41: @ | EA41: =EH32 -> 12 | EB41: plg | EC41: =EA41*2.54 -> 30.48 | ED41: cm | EN41: Se puede claramente apreciar que los esfuerzos | FF41: M neg max | FG41: M pos max | FH41: M max | FJ41: =(FI25+FN41)*FJ25 -> -3375.0068 | FN41: =(FO25+FJ40+FT40)*FN25 -> 0 | FP41: =(FO25+FJ40+FT40)*FP25 -> 0 | FT41: =(FU25+FP41)*FT25 -> 0 | GD41: M neg max | GE41: M pos max | GF41: M max | GH41: =(GG25+GL41)*GH25 -> 236.63636 | GL41: =(GM25+GH40+GR40)*GL25 -> -59.159091 | GN41: =(GM25+GH40+GR40)*GN25 -> -59.159091 | GR41: =(GS25+GN41)*GR25 -> 0 | GZ41: M neg max | HA41: M pos max | HB41: M max | HD41: =(HC25+HH41)*HD25 -> 81.397077 | HH41: =(HI25+HD40+HN41)*HH25 -> 11.096562 | HJ41: =(HI25+HD40+HN41)*HJ25 -> 11.096562 | HN41: =(HO25+HJ40+HT41)*HN25 -> -128.29121 | HP41: =(HO25+HJ40+HT41)*HP25 -> -128.29121 | HT41: =(HU25+HP40+HZ40)*HT25 -> 502.0683 | HV41: =(HU25+HP40+HZ40)*HV25 -> 167.3561 | HZ41: =(IA25+HV41)*HZ25 -> 0 | IY41: Columnas C1 40 x 40 | KC41: Se supone para los elementos estructurales (columnas y trabes) acero de refuerzo fy: 4200 Si el contratista puede conseguir acero de mejores características favor de consultar para hacer las adecuaciones correspondientes. Tanto los sistemas de vigueta y bovedilla como los armex para castillo emplean acero fy 6000.
B42: El Ing. Edgar López me solicito realizara el Análisis de Factibilidad y Diseno Estructural para la Ampliacion de la recamara principal de la Villa #3 en Palacio del Mar. | BQ42: Vß = | BR42: =BR41*BT41*BV41 -> 15.2352 | BS42: promedio | DV42: Claro = | DW42: 3 | EW42: El analisis preliminar por elemento finito no revela ningun sobre esfuerzo ocasionado por la modidificacion-ampliacion. | FF42: =MIN(FJ42:FP42) -> -8111.8909 | FG42: =MAX(FL42) -> 2477.7031 | FH42: =MAX(FG42:FG43) -> 8111.8909 | FJ42: =FK25+(2*FJ41)+FN41 -> -8111.8909 | FL42: =FL54 -> 2477.7031 | FN42: =FM25+(2*FN41)+FJ41 -> -2013.1295 | FP42: =FQ25+(2*FP41)+FT41 -> 0 | FR42: =FR54 -> 0 | FT42: =FS25+(2*FT41)+FP41 -> 0 | GD42: =MIN(GH42:GR42) -> -1480.1955 | GE42: =MAX(GJ42,GP42) -> 1017.3543 | GF42: =MAX(GE42:GE43) -> 1480.1955 | GH42: =GI25+(2*GH41)+GL41 -> -947.76364 | GJ42: =GJ54 -> 898.13317 | GL42: =GK25+(2*GL41)+GH41 -> 1480.1955 | GN42: =GO25+(2*GN41)+GR41 -> -1480.1955 | GP42: =GP54 -> 1017.3543 | GR42: =GQ25+(2*GR41)+GN41 -> 1302.7182 | GZ42: =MIN(HD42:HZ42) -> -1027.1651 | HA42: =HZ42 -> 1529.2334 | HB42: =MAX(HA42:HA43) -> 1529.2334 | HD42: =HE25+(2*HD41)+HH41 -> 0 | HF42: =HF54 -> 46.223948 | HH42: =HG25+(2*HH41)+HD41 -> 257.41779 | HJ42: =HK25+(2*HJ41)+HN41 -> -257.41779 | HL42: =HL54 -> 238.00597 | HN42: =HM25+(2*HN41)+HJ41 -> -94.16617 | HP42: =HQ25+(2*HP41)+HT41 -> 94.16617 | HR42: =HR54 -> 96.689346 | HT42: =HS25+(2*HT41)+HP41 -> 1027.1651 | HV42: =HW25+(2*HV41)+HZ41 -> -1027.1651 | HX42: =HX54 -> 1102.9759 | HZ42: =HY25+(2*HZ41)+HV41 -> 1529.2334 | IY42: Columnas de 40 x 40 armadas con 12 varillas de 3/4 en cuadro. Estribos #3 @ 15 cm en los tercios extremos y @ 30 cm en el centro.
BQ43: Vß = | BR43: =BR41 -> 1.15 | BS43: x | BT43: =BT41 -> 1.15 | BU43: x | BV43: =BU37 -> 110 | CN43: T= | CO43: 3 | DV43: Wut = | DW43: =DW41 -> 124.28561 | DY43: area = | DZ43: =DZ40/(EA32*0.9) -> 0.19450017 | EB43: CF 4 cal 14 | FG43: =FF42*-1 -> 8111.8909 | FP43: =FN42+FP42 -> -2013.1295 | GE43: =GD42*-1 -> 1480.1955 | GN43: =GL42+GN42 -> 4.7066351e-11 | HA43: =GZ42*-1 -> 1027.1651 | HJ43: =HH42+HJ42 -> 2.1286041e-08 | HP43: =HN42+HP42 -> -4.2572111e-08 | HV43: =HT42+HV42 -> 7.7894811e-08 | IJ43: Colocar Conectores que ofrezcan una base igual a la cara ante diagonal, Los tensores se deberan soldar a todo lo largo en las tres caras con soldadura de filete. Adicionalmente se perforara un agujero de 1 1/8" en el centro del tensor y rellenar de soldadura. Placa de 1/2" es suficiente pero puede sustituirse por placa de 5/8". Tanto la Base del conector (a viga) como la cara a diagonal (recibe tensor) mediran el doble del peralte nominal del tensor pero no menos de 4". El traslape del Tensor sera de por lo menos su peralte nominal pero no menor a 3". La altura se determinara por trabajabilidad pero no sera mayor a la base de la placa de coneccion.
L44: Los primeros azotan de Este a Oeste mientras que la mayoria de las tormentas traen vientos en sentido inverso. Tenemos los vientos tazados en hasta 111 km/hra por cuanto usaremos el estandar de la CFE vientos de hasta 120 km/hra para verificar nuestro diseno | BQ44: Vß = | BR44: =BR43*BT43*BV43 -> 145.475 | BS44: maximo | CN44: L= | CO44: =9.81*((CO43/(2*PI()))^2) -> 2.2364118 | DD44: Esta estructura de acero se lligará a la estructura existente en los muros de carga. Dado que se retirara la losa hoy eistente y se remplazara por techumbre liviana estos estaran sobrados. | DM44: 1246.1 | DN44: kg
U45: 2005 | BQ45: Definimos la Estructura como Tipo 2 | DM45: 1218.9 | DN45: kg | DQ45: ahorro | FI45: cortante alto | FU45: =IF(FU46<0.01,IF(FU46>-0.01,"Cierra de diagrama","No Cierra"),"No Cierra") -> No Cierra | GG45: cortante alto | GS45: =IF(GS46<0.01,IF(GS46>-0.01,"Cierra de diagrama","No Cierra"),"No Cierra") -> No Cierra | HC45: cortante alto | IA45: =IF(IA46<0.01,IF(IA46>-0.01,"Cierra de diagrama","No Cierra"),"No Cierra") -> No Cierra
BQ46: Toda Vez que por el bajo peso de sis elementos se encuentra sensible a rafagas. | CC46: Area= | CD46: 1 x 6 '= | CF46: =CF36*CE38 -> 6 | CH46: Corto periodo de Vortice | DM46: =DM44-DM45 -> 27.2 | DN46: diferencia | DQ46: =DM46/DM44 -> 0.021828104 | FF46: V pos max | FG46: V neg max | FH46: V max | FI46: =FI50+FI47 -> 6098.7614 | FL46: =IF(FL49=0,0,FI46-FJ48) -> 0 | FO46: =FO50+FO47 -> 178.90909 | FR46: =IF(FR49=0,0,FO46-FP48) -> 0 | FU46: =FU50+FU47 -> 178.90909 | GD46: V pos max | GE46: V neg max | GF46: V max | GG46: =GG50+GG47 -> 2546.2773 | GJ46: =IF(GJ49=0,0,GG46-GH48) -> 0 | GM46: =GM50+GM47 -> 2961.8227 | GP46: =IF(GP49=0,0,GM46-GN48) -> 0 | GS46: =GS50+GS47 -> 357.81818 | GZ46: V pos max | HA46: V neg max | HB46: V max | HC46: =HC50+HC47 -> 901.28948 | HF46: =IF(HF49=0,0,HC46-HD48) -> 23.189485 | HI46: =HI50+HI47 -> 1319.1385 | HL46: =IF(HL49=0,0,HI46-HJ48) -> 0 | HO46: =HO50+HO47 -> -94.140336 | HR46: =IF(HR49=0,0,HO46-HP48) -> 0 | HU46: =HU50+HU47 -> 2735.3075 | HX46: =IF(HX49=0,0,HU46-HV48) -> 0 | IA46: =IA50+IA47 -> 357.81818
CC47: Fp=PxA = | CD47: =CF27 -> 0.8530091 | CE47: =CF46 -> 6 | CF47: =CE47*CD47 -> 5.1180546 | CH47: Como podemos apreciar tenemos un periodo corto para los vortices de 3.5 segundos. Puede generar vibraciones en elementos de 2 metros | FF47: =MAX(FJ46:IW46) -> 2961.8227 | FG47: =MIN(FJ50:IW50) -> -2722.3227 | FH47: =MAX(FF47:FF48) -> 2961.8227 | FI47: =FI28 -> 11367.361 | FO47: =FO28 -> -651.25227 | FU47: =FU28 -> 0 | GD47: =MAX(GH46:IW46) -> 2961.8227 | GE47: =MIN(GH50:IW50) -> -2722.3227 | GF47: =MAX(GD47:GD48) -> 2961.8227 | GG47: =GG28 -> 4302.4773 | GM47: =GM28 -> 5684.1455 | GS47: =GS28 -> 2664.5955 | GZ47: =MAX(HD46:IG46) -> 2735.3075 | HA47: =MIN(HD50:IN50) -> -2533.2925 | HB47: =MAX(GZ47:GZ48) -> 2735.3075 | HC47: =HC28 -> 901.28948 | HI47: =HI28 -> 2452.7036 | HO47: =HO28 -> 342.92116 | HU47: =HU28 -> 4585.6479 | IA47: =IA28 -> 2891.1106
CC48: Fr=PxA = | CD48: =CF29 -> 77.773935 | CE48: =CE47 -> 6 | CF48: =CE48*CD48 -> 466.64361 | FF48: =FG47*-1 -> 2722.3227 | FJ48: =FL48*FL24/2 -> 2634.3 | FK48: w | FL48: =FK9 -> 1756.2 | FN48: =FJ48 -> 2634.3 | FP48: =FR48*FR24/2 -> 0 | FQ48: w | FR48: =FQ9 -> 0 | FT48: =FP48 -> 0 | GD48: =GE47*-1 -> 2722.3227 | GH48: =GJ48*GJ24/2 -> 2634.3 | GI48: w | GJ48: =GI9 -> 1756.2 | GL48: =GH48 -> 2634.3 | GN48: =GP48*GP24/2 -> 2634.3 | GO48: w | GP48: =GO9 -> 1756.2 | GR48: =GN48 -> 2634.3 | GZ48: =HA47*-1 -> 2533.2925 | HD48: =HF48*HF24/2 -> 878.1 | HE48: w | HF48: =HE9 -> 1756.2 | HH48: =HD48 -> 878.1 | HJ48: =HL48*HL24/2 -> 878.1 | HK48: w | HL48: =HK9 -> 1756.2 | HN48: =HJ48 -> 878.1 | HP48: =HR48*HR24/2 -> 878.1 | HQ48: w | HR48: =HQ9 -> 1756.2 | HT48: =HP48 -> 878.1 | HV48: =HX48*HX24/2 -> 2634.3 | HW48: w | HX48: =HW9 -> 1756.2 | HZ48: =HV48 -> 2634.3
DU49: Trabe | DV49: b | DW49: d | DX49: i | FK49: p | FL49: =FK12 -> 0 | FN49: =FL48*FL24 -> 5268.6 | FQ49: p | FR49: =FQ12 -> 0 | FT49: =FR48*FR24 -> 0 | GI49: p | GJ49: =GI12 -> 0 | GL49: =GJ48*GJ24 -> 5268.6 | GO49: p | GP49: =GO12 -> 0 | GR49: =GP48*GP24 -> 5268.6 | HE49: p | HF49: =HE12 -> 278.65455 | HH49: =HF48*HF24 -> 1756.2 | HK49: p | HL49: =HK12 -> 0 | HN49: =HL48*HL24 -> 1756.2 | HQ49: p | HR49: =HQ12 -> 0 | HT49: =HR48*HR24 -> 1756.2 | HW49: p | HX49: =HW12 -> 0 | HZ49: =HX48*HX24 -> 5268.6
DV50: 30 | DW50: 40 | DX50: =DV50*(DW50^3) -> 1920000 | FI50: =FG27*(-1) -> -5268.6 | FL50: =IF(FL49=0,0,FL46-FL49) -> 0 | FO50: =IF(FL24=0,-1*FM39,IF(FL49=0,FI46-FN49,FL50-FN48)) -> 830.16136 | FR50: =IF(FR49=0,0,FR46-FR49) -> 0 | FU50: =IF(FR49=0,FO46-FT49,FR50-FT48) -> 178.90909 | GG50: =GE27*(-1) -> -1756.2 | GJ50: =IF(GJ49=0,0,GJ46-GJ49) -> 0 | GM50: =IF(GJ24=0,-1*GK39,IF(GJ49=0,GG46-GL49,GJ50-GL48)) -> -2722.3227 | GP50: =IF(GP49=0,0,GP46-GP49) -> 0 | GS50: =IF(GP49=0,GM46-GR49,GP50-GR48) -> -2306.7773 | HC50: =HA27*(-1) -> 0 | HF50: =IF(HF49=0,0,HF46-HF49) -> -255.46506 | HI50: =IF(HF24=0,-1*HG39,IF(HF49=0,HC46-HH49,HF50-HH48)) -> -1133.5651 | HL50: =IF(HL49=0,0,HL46-HL49) -> 0 | HO50: =IF(HL24=0,-1*HM39,IF(HL49=0,HI46-HN49,HL50-HN48)) -> -437.0615 | HR50: =IF(HR49=0,0,HR46-HR49) -> 0 | HU50: =IF(HR24=0,-1*HS39,IF(HR49=0,HO46-HT49,HR50-HT48)) -> -1850.3403 | HX50: =IF(HX49=0,0,HX46-HX49) -> 0 | IA50: =IF(HX49=0,HU46-HZ49,HX50-HZ48) -> -2533.2925
FK51: Distancia del nudo anterior al punto de inversión o cortante cero | GI51: Distancia del nudo anterior al punto de inversión o cortante cero | HE51: Distancia del nudo anterior al punto de inverción o cortante cero
FL52: Momento Máximo al centro del claro | GJ52: Momento Máximo al centro del claro | HF52: Momento Máximo al centro del claro
DU53: W en trab | DV53: =#REF!/(2000*EC41/100) -> #REF! | DX53: =DX57+DX60+DX63+DX66 -> #REF! | DY53: =DX53*2 -> #REF! | FM53: distancia del punto de inversión o cortante cero al nudo siguiente | GK53: distancia del punto de inversión o cortante cero al nudo siguiente | HG53: distancia del punto de inverción o cortante cero al nudo siguiente
DX54: A | DZ54: B | FH54: =FG25 -> 8111.8909 | FI54: =FI46 -> 6098.7614 | FJ54: =FJ42 -> -8111.8909 | FK54: =IF(FI54=0,0,IF(FL48=0,0,IF(FL49=0,FI54/FL48,FK11))) -> 3.4727032 | FL54: =FJ54+IF(FL49=0,FI54*FK54/2,(FI46+FL46)*FK54/2) -> 2477.7031 | FM54: =IF(FL24=0,0,FL24-FK54) -> -0.4727032 | FN54: =FN42 -> -2013.1295 | FO54: =FO46 -> 178.90909 | FP54: =FP42 -> 0 | FQ54: =IF(FO54=0,0,IF(FR48=0,0,IF(FR49=0,FO54/FR48,FQ11))) -> 0 | FR54: =FP54+IF(FR49=0,FO54*FQ54/2,(FO46+FR46)*FQ54/2) -> 0 | FS54: =IF(FR24=0,0,FR24-FQ54) -> 0 | FT54: =FT42 -> 0 | FU54: =FU46 -> 178.90909 | FV54: =FW25 -> 0 | GF54: =GE25 -> 947.76364 | GG54: =GG46 -> 2546.2773 | GH54: =GH42 -> -947.76364 | GI54: =IF(GG54=0,0,IF(GJ48=0,0,IF(GJ49=0,GG54/GJ48,GI11))) -> 1.4498789 | GJ54: =GH54+IF(GJ49=0,GG54*GI54/2,(GG46+GJ46)*GI54/2) -> 898.13317 | GK54: =IF(GJ24=0,0,GJ24-GI54) -> 1.5501211 | GL54: =GL42 -> 1480.1955 | GM54: =GM46 -> 2961.8227 | GN54: =GN42 -> -1480.1955 | GO54: =IF(GM54=0,0,IF(GP48=0,0,IF(GP49=0,GM54/GP48,GO11))) -> 1.6864951 | GP54: =GN54+IF(GP49=0,GM54*GO54/2,(GM46+GP46)*GO54/2) -> 1017.3543 | GQ54: =IF(GP24=0,0,GP24-GO54) -> 1.3135049 | GR54: =GR42 -> 1302.7182 | GS54: =GS46 -> 357.81818 | GT54: =GU25 -> 0 | HB54: =HA25 -> 0 | HC54: =HC46 -> 901.28948 | HD54: =HD42 -> 0 | HE54: =IF(HC54=0,0,IF(HF48=0,0,IF(HF49=0,HC54/HF48,HE11))) -> 0.1 | HF54: =HD54+IF(HF49=0,HC54*HE54/2,(HC46+HF46)*HE54/2) -> 46.223948 | HG54: =IF(HF24=0,0,HF24-HE54) -> 0.9 | HH54: =HH42 -> 257.41779 | HI54: =HI46 -> 1319.1385 | HJ54: =HJ42 -> -257.41779 | HK54: =IF(HI54=0,0,IF(HL48=0,0,IF(HL49=0,HI54/HL48,HK11))) -> 0.75113228 | HL54: =HJ54+IF(HL49=0,HI54*HK54/2,(HI46+HL46)*HK54/2) -> 238.00597 | HM54: =IF(HL24=0,0,HL24-HK54) -> 0.24886772 | HN54: =HN42 -> -94.16617 | HO54: =HO46 -> -94.140336 | HP54: =HP42 -> 94.16617 | HQ54: =IF(HO54=0,0,IF(HR48=0,0,IF(HR49=0,HO54/HR48,HQ11))) -> -0.053604565 | HR54: =HP54+IF(HR49=0,HO54*HQ54/2,(HO46+HR46)*HQ54/2) -> 96.689346 | HS54: =IF(HR24=0,0,HR24-HQ54) -> 1.0536046 | HT54: =HT42 -> 1027.1651 | HU54: =HU46 -> 2735.3075 | HV54: =HV42 -> -1027.1651 | HW54: =IF(HU54=0,0,IF(HX48=0,0,IF(HX49=0,HU54/HX48,HW11))) -> 1.5575148 | HX54: =HV54+IF(HX49=0,HU54*HW54/2,(HU46+HX46)*HW54/2) -> 1102.9759 | HY54: =IF(HX24=0,0,HX24-HW54) -> 1.4424852 | HZ54: =HZ42 -> 1529.2334 | IA54: =IA46 -> 357.81818 | IB54: =IC25 -> 0
DW55: 1 | DX55: =DX50 -> 1920000 | DY55: #REF! | DZ55: =DX55 -> 1920000 | EA55: #REF! | FI55: Nudo | FL55: Barra | FM55: =((FI46+FO50)/2)*FL45 -> 0 | GG55: Nudo | GJ55: Barra | GK55: =((GG46+GM50)/2)*GJ45 -> 0 | HC55: Nudo | HF55: Barra | HG55: =((HC46+HI50)/2)*HF45 -> 0 | HJ55: Momento en este extremo de la barra
DW56: =DY56+EA56+EF72+EH72+EJ72+EL72+#REF! -> #REF! | DX56: #REF! | DY56: =DX55/(DY55*100) -> #REF! | DZ56: #REF! | EA56: =DZ55/(EA55*100) -> #REF! | HI56: Cortante alto en este extremo de la barra
DX57: =DX55/(DX56*100) -> #REF! | DZ57: =DZ55/(DZ56*100) -> #REF! | HH57: momento | HI57: en este extremo
DW58: 2 | DX58: =DX55 -> 1920000 | DY58: #REF! | DZ58: =DX58 -> 1920000 | EA58: #REF!
DX59: #REF! | DY59: =DX58/(DY58*100) -> #REF! | DZ59: #REF! | EA59: =DZ58/(EA58*100) -> #REF!
DX60: =DX58/(DX59*100) -> #REF! | DZ60: =DZ58/(DZ59*100) -> #REF!
DW61: 3 | DX61: =DX58 -> 1920000 | DY61: #REF! | DZ61: =DX61 -> 1920000 | EA61: #REF!
DX62: #REF! | DY62: =DX61/(DY61*100) -> #REF! | DZ62: #REF! | EA62: =DZ61/(EA61*100) -> #REF!
DX63: =DX61/(DX62*100) -> #REF! | DZ63: =DZ61/(DZ62*100) -> #REF!
DW64: 4 | DX64: =DX61 -> 1920000 | DY64: #REF! | DZ64: =DX64 -> 1920000 | EA64: #REF!
DX65: #REF! | DY65: =DX64/(DY64*100) -> #REF! | DZ65: #REF! | EA65: =DZ64/(EA64*100) -> #REF!
DX66: =DX64/(DX65*100) -> #REF! | DZ66: =DZ64/(DZ65*100) -> #REF!
DW67: 5
DX69: A | DZ69: B | EH69: peso total = | EI69: =DW40*3 -> 9.93 | EJ69: + | EK69: =+DZ40 -> 372.85683 | EL69: =
DW70: 1 | DY70: =DY55 -> #REF! | EA70: =EA55 -> #REF! | EE70: C | EG70: D | EI70: E | EK70: F
DX71: =DX56 -> #REF! | DY71: =DX55*DY56/DY55 -> #REF! | DZ71: =DZ56 -> #REF! | EA71: =DZ55*EA56/EA55 -> #REF! | EE71: =DZ55 -> 1920000 | EF71: #REF! | EG71: =EE71 -> 1920000 | EH71: #REF! | EI71: =EG71 -> 1920000 | EJ71: #REF! | EK71: =EI71 -> 1920000 | EL71: #REF!
DX72: =DX57*DX55/DX56 -> #REF! | DZ72: =DZ57*DZ55/DZ56 -> #REF! | EE72: #REF! | EF72: =EE71/(EF71*100) -> #REF! | EG72: #REF! | EH72: =EG71/(EH71*100) -> #REF! | EI72: #REF! | EJ72: =EI71/(EJ71*100) -> #REF! | EK72: #REF! | EL72: =EK71/(EL71*100) -> #REF!
DW73: 2 | DY73: =DY58 -> #REF! | EA73: =EA58 -> #REF! | EE73: =EE71/(EE72*100) -> #REF! | EG73: =EG71/(EG72*100) -> #REF! | EI73: =EI71/(EI72*100) -> #REF! | EK73: =EK71/(EK72*100) -> #REF!
DX74: =DX59 -> #REF! | DY74: =DX58*DY59/DY58 -> #REF! | DZ74: =DZ59 -> #REF! | EA74: =DZ58*EA59/EA58 -> #REF! | EE74: =DZ58 -> 1920000 | EF74: #REF! | EG74: =EE74 -> 1920000 | EH74: #REF! | EI74: =EG74 -> 1920000 | EJ74: #REF! | EK74: =EI74 -> 1920000 | EL74: #REF!
DX75: =DX60*DX58/DX59 -> #REF! | DZ75: =DZ60*DZ58/DZ59 -> #REF! | EE75: #REF! | EF75: =EE74/(EF74*100) -> #REF! | EG75: #REF! | EH75: =EG74/(EH74*100) -> #REF! | EI75: #REF! | EJ75: =EI74/(EJ74*100) -> #REF! | EK75: #REF! | EL75: =EK74/(EL74*100) -> #REF!
DW76: 3 | DY76: =DY61 -> #REF! | EA76: =EA61 -> #REF! | EE76: =EE74/(EE75*100) -> #REF! | EG76: =EG74/(EG75*100) -> #REF! | EI76: =EI74/(EI75*100) -> #REF! | EK76: =EK74/(EK75*100) -> #REF!
DX77: =DX62 -> #REF! | DY77: =DX61*DY62/DY61 -> #REF! | DZ77: =DZ62 -> #REF! | EA77: =DZ61*EA62/EA61 -> #REF! | EE77: =DZ61 -> 1920000 | EF77: #REF! | EG77: =EE77 -> 1920000 | EH77: #REF! | EI77: =EG77 -> 1920000 | EJ77: #REF! | EK77: =EI77 -> 1920000 | EL77: #REF!
DX78: =DX63*DX61/DX62 -> #REF! | DZ78: =DZ63*DZ61/DZ62 -> #REF! | EE78: #REF! | EF78: =EE77/(EF77*100) -> #REF! | EG78: #REF! | EH78: =EG77/(EH77*100) -> #REF! | EI78: #REF! | EJ78: =EI77/(EJ77*100) -> #REF! | EK78: #REF! | EL78: =EK77/(EL77*100) -> #REF!
DW79: 4 | DY79: =DY64 -> #REF! | EA79: =EA64 -> #REF! | EE79: =EE77/(EE78*100) -> #REF! | EG79: =EG77/(EG78*100) -> #REF! | EI79: =EI77/(EI78*100) -> #REF! | EK79: =EK77/(EK78*100) -> #REF!
DX80: =DX65 -> #REF! | DY80: =DX64*DY65/DY64 -> #REF! | DZ80: =DZ65 -> #REF! | EA80: =DZ64*EA65/EA64 -> #REF! | EE80: =DZ64 -> 1920000 | EF80: #REF! | EG80: =EE80 -> 1920000 | EH80: #REF! | EI80: =EG80 -> 1920000 | EJ80: #REF! | EK80: =EI80 -> 1920000 | EL80: #REF!
DX81: =DX66*DX64/DX65 -> #REF! | DZ81: =DZ66*DZ64/DZ65 -> #REF! | EE81: #REF! | EF81: =EE80/(EF80*100) -> #REF! | EG81: #REF! | EH81: =EG80/(EH80*100) -> #REF! | EI81: #REF! | EJ81: =EI80/(EJ80*100) -> #REF! | EK81: #REF! | EL81: =EK80/(EL80*100) -> #REF!
DW82: 5 | EE82: =EE80/(EE81*100) -> #REF! | EG82: =EG80/(EG81*100) -> #REF! | EI82: =EI80/(EI81*100) -> #REF! | EK82: =EK80/(EK81*100) -> #REF!
DW84: cargas y longitudes entrepiso
EE85: C | EG85: D | EI85: E | EK85: F
DX86: A | DZ86: B | EF86: =EF71 -> #REF! | EH86: =EH71 -> #REF! | EJ86: =EJ71 -> #REF! | EL86: =EL71 -> #REF!
DW87: 1 | DY87: =DY70 -> #REF! | EA87: =EA70 -> #REF! | EE87: =EE72 -> #REF! | EF87: =EE71*EF72/EF71 -> #REF! | EG87: =EG72 -> #REF! | EH87: =EG71*EH72/EH71 -> #REF! | EI87: =EI72 -> #REF! | EJ87: =EI71*EJ72/EJ71 -> #REF! | EK87: =EK72 -> #REF! | EL87: =EK71*EL72/EL71 -> #REF!
DX88: =DX71 -> #REF! | DY88: =DY71 -> #REF! | DZ88: =DZ71 -> #REF! | EA88: =EA71 -> #REF! | EE88: =EE73*EE71/EE72 -> #REF! | EG88: =EG73*EG71/EG72 -> #REF! | EI88: =EI73*EI71/EI72 -> #REF! | EK88: =EK73*EK71/EK72 -> #REF!
DX89: =DX72 -> #REF! | DZ89: =DZ72+DX72 -> #REF! | EF89: =EF74 -> #REF! | EH89: =EH74 -> #REF! | EJ89: =EJ74 -> #REF! | EL89: =EL74 -> #REF!
DW90: 2 | DY90: =DY73 -> #REF! | EA90: =EA73 -> #REF! | EE90: =EE75 -> #REF! | EF90: =EE74*EF75/EF74 -> #REF! | EG90: =EG75 -> #REF! | EH90: =EG74*EH75/EH74 -> #REF! | EI90: =EI75 -> #REF! | EJ90: =EI74*EJ75/EJ74 -> #REF! | EK90: =EK75 -> #REF! | EL90: =EK74*EL75/EL74 -> #REF!
DX91: =DX74 -> #REF! | DY91: =DY71+DY74 -> #REF! | DZ91: =DZ74 -> #REF! | EA91: =EA71+EA74 -> #REF! | EE91: =EE76*EE74/EE75 -> #REF! | EG91: =EG76*EG74/EG75 -> #REF! | EI91: =EI76*EI74/EI75 -> #REF! | EK91: =EK76*EK74/EK75 -> #REF!
DX92: =DX75 -> #REF! | DZ92: =DZ75+DX75 -> #REF! | EF92: =EF77 -> #REF! | EH92: =EH77 -> #REF! | EJ92: =EJ77 -> #REF! | EL92: =EL77 -> #REF!
DW93: 3 | DY93: =DY76 -> #REF! | EA93: =EA76 -> #REF! | EE93: =EE78 -> #REF! | EF93: =EE77*EF78/EF77 -> #REF! | EG93: =EG78 -> #REF! | EH93: =EG77*EH78/EH77 -> #REF! | EI93: =EI78 -> #REF! | EJ93: =EI77*EJ78/EJ77 -> #REF! | EK93: =EK78 -> #REF! | EL93: =EK77*EL78/EL77 -> #REF!
DX94: =DX77 -> #REF! | DY94: =DY74+DY77 -> #REF! | DZ94: =DZ77 -> #REF! | EA94: =EA74+EA77 -> #REF! | EE94: =EE79*EE77/EE78 -> #REF! | EG94: =EG79*EG77/EG78 -> #REF! | EI94: =EI79*EI77/EI78 -> #REF! | EK94: =EK79*EK77/EK78 -> #REF!
DX95: =DX78 -> #REF! | DZ95: =DZ78+DX78 -> #REF! | EF95: =EF80 -> #REF! | EH95: =EH80 -> #REF! | EJ95: =EJ80 -> #REF! | EL95: =EL80 -> #REF!
DW96: 4 | DY96: =DY79 -> #REF! | EA96: =EA79 -> #REF! | EE96: =EE81 -> #REF! | EF96: =EE80*EF81/EF80 -> #REF! | EG96: =EG81 -> #REF! | EH96: =EG80*EH81/EH80 -> #REF! | EI96: =EI81 -> #REF! | EJ96: =EI80*EJ81/EJ80 -> #REF! | EK96: =EK81 -> #REF! | EL96: =EK80*EL81/EL80 -> #REF!
DX97: =DX80 -> #REF! | DY97: =DY77+DY80 -> #REF! | DZ97: =DZ80 -> #REF! | EA97: =EA77+EA80 -> #REF! | EE97: =EE82*EE80/EE81 -> #REF! | EG97: =EG82*EG80/EG81 -> #REF! | EI97: =EI82*EI80/EI81 -> #REF! | EK97: =EK82*EK80/EK81 -> #REF!
DX98: =DX81 -> #REF! | DZ98: =DZ81+DX81 -> #REF!
DW99: 5 | DY99: =DY79 -> #REF! | EA99: =EA79 -> #REF!
DY100: =DY80 -> #REF! | EA100: =EA80 -> #REF!
EE102: C | EG102: D | EI102: E | EK102: F
EF103: =EF86 -> #REF! | EH103: =EH86 -> #REF! | EJ103: =EJ86 -> #REF! | EL103: =EL86 -> #REF!
EE104: =EE87 -> #REF! | EF104: =EF87 -> #REF! | EG104: =EG87 -> #REF! | EH104: =EH87 -> #REF! | EI104: =EI87 -> #REF! | EJ104: =EJ87 -> #REF! | EK104: =EK87 -> #REF! | EL104: =EL87 -> #REF!
EE105: =EE88+DZ72 -> #REF! | EG105: =EG88+EE88 -> #REF! | EI105: =EI88+EG88 -> #REF! | EK105: =EK88+EI88 -> #REF!
EF106: =EF89 -> #REF! | EH106: =EH89 -> #REF! | EJ106: =EJ89 -> #REF! | EL106: =EL89 -> #REF!
...

Sheet datos
Y1: f'c | Z1: 200
B2: Se ubicaron dos trabes críticas una en la azotea y otra en el entrepiso | Y2: columnas | Z2: b | AA2: 30 | AB2: d | AC2: 30
Y3: trabes | Z3: b | AA3: 30 | AB3: d | AC3: 40
F4: Estas son: | Y4: portico
Y5: columnas | Z5: b | AA5: 30 | AB5: d | AC5: 20
F6: Trabe azotea eje 4 | Y6: trabes | Z6: b | AA6: 30 | AB6: d | AC6: 20
Y7: muro | Z7: b | AA7: 20 | AB7: d | AC7: 500
F8: armada con
F10: 2 CF 102 x 10 en tension y compresion
Y11: peralte | Z11: 7.5 | AA11: =Z11*100 -> 750 | AB11: =AA11*0.1 -> 75
F12: peralte de 40 centimetros
F14: Trabe entrepiso Nivel 2 eje 2
F16: 2 CF 102 x 10 en tension y compresion
F18: peralte de 50 centimetros
F20: arrojando el siguiente peso
F22: 5.78 | G22: kg x m | H22: x | I22: 5
F24: = | G24: =F22*I22 -> 28.9 | H24: kg x m lin
A78: marcos gral
A79: A | B79: 330979 | L79: 1 | M79: 1.5720609e+08
A80: B | B80: 85531.636 | L80: 2 | M80: 49893.455
A81: C | B81: 30978116 | L81: 3 | M81: 61842189
A82: D | B82: 424490.34 | L82: 4 | M82: 31198280
A83: E | B83: 35638.182 | L83: 5 | M83: 31067343
A84: F | B84: 61820806 | L84: #REF! | M84: 0
A85: G | B85: 30928222 | L85: #REF! | M85: 0
A86: H | B86: 1.0480406e+08 | L86: #REF! | M86: 0
B90: 1 | C90: 2 | D90: 3 | E90: 4 | F90: 5 | G90: 6 | H90: 7 | I90: 8 | J90: 9 | K90: 10
B91: 5.93 | C91: 5.45 | D91: 5.63 | E91: 6.43
B93: a | C93: b | D93: c | E93: d | F93: e | G93: f | H93: g | I93: h | J93: i | K93: j
B94: 5.9 | C94: 5.58 | D94: 5.4 | E94: 5.43 | F94: 5.27 | G94: 5.26 | H94: 5.68

Sheet trabes corregido
A2: W= | B2: 0.387948
E3: momento puro en el claro | G3: Atrib | H3: 3 | K3: momento puro en el claro | Q3: momento puro en el claro | W3: momento puro en el claro | AC3: momento puro en el claro | AI3: momento puro en el claro | AO3: momento puro en el claro | AU3: momento puro en el claro | BA3: momento puro en el claro
F4: momentos generados en los nudos | G4: A | H4: B | L4: momentos generados en los nudos | M4: A | N4: B | R4: momentos generados en los nudos | S4: A | T4: B | X4: momentos generados en los nudos | Y4: A | Z4: B | AD4: momentos generados en los nudos | AE4: A | AF4: B | AJ4: momentos generados en los nudos | AK4: A | AL4: B | AP4: momentos generados en los nudos | AQ4: A | AR4: B | AV4: momentos generados en los nudos | AW4: A | AX4: B | BB4: momentos generados en los nudos | BC4: A | BD4: B
E5: Carga uniformemente Distribuida | F5: =B2 -> 0.387948 | G5: =-1*(IF(G20=0,0,IF(F5=0,0,F5*G20*G20/12))) -> -0.20367593 | H5: =G5*-1 -> 0.20367593 | K5: Carga uniformemente Distribuida | L5: =F5 -> 0.387948 | M5: =-1*(IF(M20=0,0,IF(L5=0,0,L5*M20*M20/12))) -> -0.141622 | N5: =M5*-1 -> 0.141622 | Q5: Carga uniformemente Distribuida | R5: =L5 -> 0.387948 | S5: =-1*(IF(S20=0,0,IF(R5=0,0,R5*S20*S20/12))) -> -0.24626939 | T5: =S5*-1 -> 0.24626939 | W5: Carga uniformemente Distribuida | X5: =R5 -> 0.387948 | Y5: =-1*(IF(Y20=0,0,IF(X5=0,0,X5*Y20*Y20/12))) -> -0.39377045 | Z5: =Y5*-1 -> 0.39377045 | AC5: Carga uniformemente Distribuida | AD5: =X5 -> 0.387948 | AE5: =-1*(IF(AE20=0,0,IF(AD5=0,0,AD5*AE20*AE20/12))) -> 0 | AF5: =AE5*-1 -> 0 | AI5: Carga uniformemente Distribuida | AJ5: =AD5 -> 0.387948 | AK5: =-1*(IF(AK20=0,0,IF(AJ5=0,0,AJ5*AK20*AK20/12))) -> 0 | AL5: =AK5*-1 -> 0 | AO5: Carga uniformemente Distribuida | AP5: =AJ5 -> 0.387948 | AQ5: =-1*(IF(AQ20=0,0,IF(AP5=0,0,AP5*AQ20*AQ20/12))) -> 0 | AR5: =AQ5*-1 -> 0 | AU5: Carga uniformemente Distribuida | AV5: =AP5 -> 0.387948 | AW5: =-1*(IF(AW20=0,0,IF(AV5=0,0,AV5*AW20*AW20/12))) -> 0 | AX5: =AW5*-1 -> 0 | BA5: Carga uniformemente Distribuida | BB5: =AV5 -> 0.387948 | BC5: =-1*(IF(BC20=0,0,IF(BB5=0,0,BB5*BC20*BC20/12))) -> 0 | BD5: =BC5*-1 -> 0
E6: Carga uniforme por peso prop | F6: 0.168209 | G6: =-1*(IF(G20=0,0,IF(F6=0,0,F6*G20*G20/12))) -> -0.088311127 | H6: =G6*-1 -> 0.088311127 | K6: Carga uniforme por peso prop | L6: =F6 -> 0.168209 | M6: =-1*(IF(M20=0,0,IF(L6=0,0,L6*M20*M20/12))) -> -0.061405382 | N6: =M6*-1 -> 0.061405382 | Q6: Carga uniforme por peso prop | R6: =L6 -> 0.168209 | S6: =-1*(IF(S20=0,0,IF(R6=0,0,R6*S20*S20/12))) -> -0.10677907 | T6: =S6*-1 -> 0.10677907 | W6: Carga uniforme por peso prop | X6: =R6 -> 0.168209 | Y6: =-1*(IF(Y20=0,0,IF(X6=0,0,X6*Y20*Y20/12))) -> -0.17073354 | Z6: =Y6*-1 -> 0.17073354 | AC6: Carga uniforme por peso prop | AD6: =X6 -> 0.168209 | AE6: =-1*(IF(AE20=0,0,IF(AD6=0,0,AD6*AE20*AE20/12))) -> 0 | AF6: =AE6*-1 -> 0 | AI6: Carga uniforme por peso prop | AJ6: =AD6 -> 0.168209 | AK6: =-1*(IF(AK20=0,0,IF(AJ6=0,0,AJ6*AK20*AK20/12))) -> 0 | AL6: =AK6*-1 -> 0 | AO6: Carga uniforme por peso prop | AP6: =AJ6 -> 0.168209 | AQ6: =-1*(IF(AQ20=0,0,IF(AP6=0,0,AP6*AQ20*AQ20/12))) -> 0 | AR6: =AQ6*-1 -> 0 | AU6: Carga uniforme por peso prop | AV6: =AP6 -> 0.168209 | AW6: =-1*(IF(AW20=0,0,IF(AV6=0,0,AV6*AW20*AW20/12))) -> 0 | AX6: =AW6*-1 -> 0 | BA6: Carga uniforme por peso prop | BB6: =AV6 -> 0.168209 | BC6: =-1*(IF(BC20=0,0,IF(BB6=0,0,BB6*BC20*BC20/12))) -> 0 | BD6: =BC6*-1 -> 0
E7: Distancia de nudo a carga puntual | G7: =-1*(IF(G20=0,0,IF(F7=0,0,IF(F8=0,0,IF(F7=(G20/2),F8*G20/8,F8*F7*((G20-F7)*(G20-F7))/(G20*G20)))))) -> 0 | H7: =IF(G20=0,0,IF(F7=0,0,IF(F8=0,0,IF(F7=(G20/2),G7*-1,F8*(F7*F7)*(G20-F7)/(G20*G20))))) -> 0 | K7: Distancia de nudo a carga puntual | M7: =-1*(IF(M20=0,0,IF(L7=0,0,IF(L8=0,0,IF(L7=(M20/2),L8*M20/8,L8*L7*((M20-L7)*(M20-L7))/(M20*M20)))))) -> 0 | N7: =IF(M20=0,0,IF(L7=0,0,IF(L8=0,0,IF(L7=(M20/2),M7*-1,L8*(L7*L7)*(M20-L7)/(M20*M20))))) -> 0 | Q7: Distancia de nudo a carga puntual | S7: =-1*(IF(S20=0,0,IF(R7=0,0,IF(R8=0,0,IF(R7=(S20/2),R8*S20/8,R8*R7*((S20-R7)*(S20-R7))/(S20*S20)))))) -> 0 | T7: =IF(S20=0,0,IF(R7=0,0,IF(R8=0,0,IF(R7=(S20/2),S7*-1,R8*(R7*R7)*(S20-R7)/(S20*S20))))) -> 0 | W7: Distancia de nudo a carga puntual | Y7: =-1*(IF(Y20=0,0,IF(X7=0,0,IF(X8=0,0,IF(X7=(Y20/2),X8*Y20/8,X8*X7*((Y20-X7)*(Y20-X7))/(Y20*Y20)))))) -> 0 | Z7: =IF(Y20=0,0,IF(X7=0,0,IF(X8=0,0,IF(X7=(Y20/2),Y7*-1,X8*(X7*X7)*(Y20-X7)/(Y20*Y20))))) -> 0 | AC7: Distancia de nudo a carga puntual | AD7: =AE20/2 -> 0 | AE7: =-1*(IF(AE20=0,0,IF(AD7=0,0,IF(AD8=0,0,IF(AD7=(AE20/2),AD8*AE20/8,AD8*AD7*((AE20-AD7)*(AE20-AD7))/(AE20*AE20)))))) -> 0 | AF7: =IF(AE20=0,0,IF(AD7=0,0,IF(AD8=0,0,IF(AD7=(AE20/2),AE7*-1,AD8*(AD7*AD7)*(AE20-AD7)/(AE20*AE20))))) -> 0 | AI7: Distancia de nudo a carga puntual | AJ7: =AK20/2 -> 0 | AK7: =-1*(IF(AK20=0,0,IF(AJ7=0,0,IF(AJ8=0,0,IF(AJ7=(AK20/2),AJ8*AK20/8,AJ8*AJ7*((AK20-AJ7)*(AK20-AJ7))/(AK20*AK20)))))) -> 0 | AL7: =IF(AK20=0,0,IF(AJ7=0,0,IF(AJ8=0,0,IF(AJ7=(AK20/2),AK7*-1,AJ8*(AJ7*AJ7)*(AK20-AJ7)/(AK20*AK20))))) -> 0 | AO7: Distancia de nudo a carga puntual | AP7: =AQ20/2 -> 0 | AQ7: =-1*(IF(AQ20=0,0,IF(AP7=0,0,IF(AP8=0,0,IF(AP7=(AQ20/2),AP8*AQ20/8,AP8*AP7*((AQ20-AP7)*(AQ20-AP7))/(AQ20*AQ20)))))) -> 0 | AR7: =IF(AQ20=0,0,IF(AP7=0,0,IF(AP8=0,0,IF(AP7=(AQ20/2),AQ7*-1,AP8*(AP7*AP7)*(AQ20-AP7)/(AQ20*AQ20))))) -> 0 | AU7: Distancia de nudo a carga puntual | AV7: =AW20/2 -> 0 | AW7: =-1*(IF(AW20=0,0,IF(AV7=0,0,IF(AV8=0,0,IF(AV7=(AW20/2),AV8*AW20/8,AV8*AV7*((AW20-AV7)*(AW20-AV7))/(AW20*AW20)))))) -> 0 | AX7: =IF(AW20=0,0,IF(AV7=0,0,IF(AV8=0,0,IF(AV7=(AW20/2),AW7*-1,AV8*(AV7*AV7)*(AW20-AV7)/(AW20*AW20))))) -> 0 | BA7: Distancia de nudo a carga puntual | BB7: =BC20/2 -> 0 | BC7: =-1*(IF(BC20=0,0,IF(BB7=0,0,IF(BB8=0,0,IF(BB7=(BC20/2),BB8*BC20/8,BB8*BB7*((BC20-BB7)*(BC20-BB7))/(BC20*BC20)))))) -> 0 | BD7: =IF(BC20=0,0,IF(BB7=0,0,IF(BB8=0,0,IF(BB7=(BC20/2),BC7*-1,BB8*(BB7*BB7)*(BC20-BB7)/(BC20*BC20))))) -> 0
E8: Carga Puntual | K8: Carga Puntual | L8: =F8 -> 0 | Q8: Carga Puntual | R8: =L8 -> 0 | W8: Carga Puntual | X8: =R8 -> 0 | AC8: Carga Puntual | AD8: =X8 -> 0 | AI8: Carga Puntual | AJ8: =AD8 -> 0 | AO8: Carga Puntual | AP8: =AJ8 -> 0 | AU8: Carga Puntual | AV8: =AP8 -> 0 | BA8: Carga Puntual | BB8: =3*2.65*B2 -> 3.0841866
E9: Distancia de nudo a carga puntual | G9: =-1*(IF(G20=0,0,IF(F9=0,0,IF(F10=0,0,IF(F9=(G20/2),F10*G20/8,F10*F9*((G20-F9)*(G20-F9))/(G20*G20)))))) -> 0 | H9: =IF(G20=0,0,IF(F9=0,0,IF(F10=0,0,IF(F9=(G20/2),G9*-1,F10*(F9*F9)*(G20-F9)/(G20*G20))))) -> 0 | K9: Distancia de nudo a carga puntual | M9: =-1*(IF(M20=0,0,IF(L9=0,0,IF(L10=0,0,IF(L9=(M20/2),L10*M20/8,L10*L9*((M20-L9)*(M20-L9))/(M20*M20)))))) -> 0 | N9: =IF(M20=0,0,IF(L9=0,0,IF(L10=0,0,IF(L9=(M20/2),M9*-1,L10*(L9*L9)*(M20-L9)/(M20*M20))))) -> 0 | Q9: Distancia de nudo a carga puntual | S9: =-1*(IF(S20=0,0,IF(R9=0,0,IF(R10=0,0,IF(R9=(S20/2),R10*S20/8,R10*R9*((S20-R9)*(S20-R9))/(S20*S20)))))) -> 0 | T9: =IF(S20=0,0,IF(R9=0,0,IF(R10=0,0,IF(R9=(S20/2),S9*-1,R10*(R9*R9)*(S20-R9)/(S20*S20))))) -> 0 | W9: Distancia de nudo a carga puntual | Y9: =-1*(IF(Y20=0,0,IF(X9=0,0,IF(X10=0,0,IF(X9=(Y20/2),X10*Y20/8,X10*X9*((Y20-X9)*(Y20-X9))/(Y20*Y20)))))) -> 0 | Z9: =IF(Y20=0,0,IF(X9=0,0,IF(X10=0,0,IF(X9=(Y20/2),Y9*-1,X10*(X9*X9)*(Y20-X9)/(Y20*Y20))))) -> 0 | AC9: Distancia de nudo a carga puntual | AE9: =-1*(IF(AE20=0,0,IF(AD9=0,0,IF(AD10=0,0,IF(AD9=(AE20/2),AD10*AE20/8,AD10*AD9*((AE20-AD9)*(AE20-AD9))/(AE20*AE20)))))) -> 0 | AF9: =IF(AE20=0,0,IF(AD9=0,0,IF(AD10=0,0,IF(AD9=(AE20/2),AE9*-1,AD10*(AD9*AD9)*(AE20-AD9)/(AE20*AE20))))) -> 0 | AI9: Distancia de nudo a carga puntual | AK9: =-1*(IF(AK20=0,0,IF(AJ9=0,0,IF(AJ10=0,0,IF(AJ9=(AK20/2),AJ10*AK20/8,AJ10*AJ9*((AK20-AJ9)*(AK20-AJ9))/(AK20*AK20)))))) -> 0 | AL9: =IF(AK20=0,0,IF(AJ9=0,0,IF(AJ10=0,0,IF(AJ9=(AK20/2),AK9*-1,AJ10*(AJ9*AJ9)*(AK20-AJ9)/(AK20*AK20))))) -> 0 | AO9: Distancia de nudo a carga puntual | AQ9: =-1*(IF(AQ20=0,0,IF(AP9=0,0,IF(AP10=0,0,IF(AP9=(AQ20/2),AP10*AQ20/8,AP10*AP9*((AQ20-AP9)*(AQ20-AP9))/(AQ20*AQ20)))))) -> 0 | AR9: =IF(AQ20=0,0,IF(AP9=0,0,IF(AP10=0,0,IF(AP9=(AQ20/2),AQ9*-1,AP10*(AP9*AP9)*(AQ20-AP9)/(AQ20*AQ20))))) -> 0 | AU9: Distancia de nudo a carga puntual | AW9: =-1*(IF(AW20=0,0,IF(AV9=0,0,IF(AV10=0,0,IF(AV9=(AW20/2),AV10*AW20/8,AV10*AV9*((AW20-AV9)*(AW20-AV9))/(AW20*AW20)))))) -> 0 | AX9: =IF(AW20=0,0,IF(AV9=0,0,IF(AV10=0,0,IF(AV9=(AW20/2),AW9*-1,AV10*(AV9*AV9)*(AW20-AV9)/(AW20*AW20))))) -> 0 | BA9: Distancia de nudo a carga puntual | BC9: =-1*(IF(BC20=0,0,IF(BB9=0,0,IF(BB10=0,0,IF(BB9=(BC20/2),BB10*BC20/8,BB10*BB9*((BC20-BB9)*(BC20-BB9))/(BC20*BC20)))))) -> 0 | BD9: =IF(BC20=0,0,IF(BB9=0,0,IF(BB10=0,0,IF(BB9=(BC20/2),BC9*-1,BB10*(BB9*BB9)*(BC20-BB9)/(BC20*BC20))))) -> 0
E10: Carga Puntual | K10: Carga Puntual | Q10: Carga Puntual | W10: Carga Puntual | AC10: Carga Puntual | AI10: Carga Puntual | AO10: Carga Puntual | AU10: Carga Puntual | BA10: Carga Puntual
E11: Distancia de nudo a carga puntual | G11: =-1*(IF(G20=0,0,IF(F11=0,0,IF(F12=0,0,IF(F11=(G20/2),F12*G20/8,F12*F11*((G20-F11)*(G20-F11))/(G20*G20)))))) -> 0 | H11: =IF(G20=0,0,IF(F11=0,0,IF(F12=0,0,IF(F11=(G20/2),G11*-1,F12*(F11*F11)*(G20-F11)/(G20*G20))))) -> 0 | K11: Distancia de nudo a carga puntual | M11: =-1*(IF(M20=0,0,IF(L11=0,0,IF(L12=0,0,IF(L11=(M20/2),L12*M20/8,L12*L11*((M20-L11)*(M20-L11))/(M20*M20)))))) -> 0 | N11: =IF(M20=0,0,IF(L11=0,0,IF(L12=0,0,IF(L11=(M20/2),M11*-1,L12*(L11*L11)*(M20-L11)/(M20*M20))))) -> 0 | Q11: Distancia de nudo a carga puntual | S11: =-1*(IF(S20=0,0,IF(R11=0,0,IF(R12=0,0,IF(R11=(S20/2),R12*S20/8,R12*R11*((S20-R11)*(S20-R11))/(S20*S20)))))) -> 0 | T11: =IF(S20=0,0,IF(R11=0,0,IF(R12=0,0,IF(R11=(S20/2),S11*-1,R12*(R11*R11)*(S20-R11)/(S20*S20))))) -> 0 | W11: Distancia de nudo a carga puntual | Y11: =-1*(IF(Y20=0,0,IF(X11=0,0,IF(X12=0,0,IF(X11=(Y20/2),X12*Y20/8,X12*X11*((Y20-X11)*(Y20-X11))/(Y20*Y20)))))) -> 0 | Z11: =IF(Y20=0,0,IF(X11=0,0,IF(X12=0,0,IF(X11=(Y20/2),Y11*-1,X12*(X11*X11)*(Y20-X11)/(Y20*Y20))))) -> 0 | AC11: Distancia de nudo a carga puntual | AE11: =-1*(IF(AE20=0,0,IF(AD11=0,0,IF(AD12=0,0,IF(AD11=(AE20/2),AD12*AE20/8,AD12*AD11*((AE20-AD11)*(AE20-AD11))/(AE20*AE20)))))) -> 0 | AF11: =IF(AE20=0,0,IF(AD11=0,0,IF(AD12=0,0,IF(AD11=(AE20/2),AE11*-1,AD12*(AD11*AD11)*(AE20-AD11)/(AE20*AE20))))) -> 0 | AI11: Distancia de nudo a carga puntual | AK11: =-1*(IF(AK20=0,0,IF(AJ11=0,0,IF(AJ12=0,0,IF(AJ11=(AK20/2),AJ12*AK20/8,AJ12*AJ11*((AK20-AJ11)*(AK20-AJ11))/(AK20*AK20)))))) -> 0 | AL11: =IF(AK20=0,0,IF(AJ11=0,0,IF(AJ12=0,0,IF(AJ11=(AK20/2),AK11*-1,AJ12*(AJ11*AJ11)*(AK20-AJ11)/(AK20*AK20))))) -> 0 | AO11: Distancia de nudo a carga puntual | AQ11: =-1*(IF(AQ20=0,0,IF(AP11=0,0,IF(AP12=0,0,IF(AP11=(AQ20/2),AP12*AQ20/8,AP12*AP11*((AQ20-AP11)*(AQ20-AP11))/(AQ20*AQ20)))))) -> 0 | AR11: =IF(AQ20=0,0,IF(AP11=0,0,IF(AP12=0,0,IF(AP11=(AQ20/2),AQ11*-1,AP12*(AP11*AP11)*(AQ20-AP11)/(AQ20*AQ20))))) -> 0 | AU11: Distancia de nudo a carga puntual | AW11: =-1*(IF(AW20=0,0,IF(AV11=0,0,IF(AV12=0,0,IF(AV11=(AW20/2),AV12*AW20/8,AV12*AV11*((AW20-AV11)*(AW20-AV11))/(AW20*AW20)))))) -> 0 | AX11: =IF(AW20=0,0,IF(AV11=0,0,IF(AV12=0,0,IF(AV11=(AW20/2),AW11*-1,AV12*(AV11*AV11)*(AW20-AV11)/(AW20*AW20))))) -> 0 | BA11: Distancia de nudo a carga puntual | BC11: =-1*(IF(BC20=0,0,IF(BB11=0,0,IF(BB12=0,0,IF(BB11=(BC20/2),BB12*BC20/8,BB12*BB11*((BC20-BB11)*(BC20-BB11))/(BC20*BC20)))))) -> 0 | BD11: =IF(BC20=0,0,IF(BB11=0,0,IF(BB12=0,0,IF(BB11=(BC20/2),BC11*-1,BB12*(BB11*BB11)*(BC20-BB11)/(BC20*BC20))))) -> 0
E12: Carga Puntual | K12: Carga Puntual | Q12: Carga Puntual | W12: Carga Puntual | AC12: Carga Puntual | AI12: Carga Puntual | AO12: Carga Puntual | AU12: Carga Puntual | BA12: Carga Puntual
E13: Distancia de nudo a carga puntual | G13: =-1*(IF(G20=0,0,IF(F13=0,0,IF(F14=0,0,IF(F13=(G20/2),F14*G20/8,F14*F13*((G20-F13)*(G20-F13))/(G20*G20)))))) -> 0 | H13: =IF(G20=0,0,IF(F13=0,0,IF(F14=0,0,IF(F13=(G20/2),G13*-1,F14*(F13*F13)*(G20-F13)/(G20*G20))))) -> 0 | K13: Distancia de nudo a carga puntual | M13: =-1*(IF(M20=0,0,IF(L13=0,0,IF(L14=0,0,IF(L13=(M20/2),L14*M20/8,L14*L13*((M20-L13)*(M20-L13))/(M20*M20)))))) -> 0 | N13: =IF(M20=0,0,IF(L13=0,0,IF(L14=0,0,IF(L13=(M20/2),M13*-1,L14*(L13*L13)*(M20-L13)/(M20*M20))))) -> 0 | Q13: Distancia de nudo a carga puntual | S13: =-1*(IF(S20=0,0,IF(R13=0,0,IF(R14=0,0,IF(R13=(S20/2),R14*S20/8,R14*R13*((S20-R13)*(S20-R13))/(S20*S20)))))) -> 0 | T13: =IF(S20=0,0,IF(R13=0,0,IF(R14=0,0,IF(R13=(S20/2),S13*-1,R14*(R13*R13)*(S20-R13)/(S20*S20))))) -> 0 | W13: Distancia de nudo a carga puntual | Y13: =-1*(IF(Y20=0,0,IF(X13=0,0,IF(X14=0,0,IF(X13=(Y20/2),X14*Y20/8,X14*X13*((Y20-X13)*(Y20-X13))/(Y20*Y20)))))) -> 0 | Z13: =IF(Y20=0,0,IF(X13=0,0,IF(X14=0,0,IF(X13=(Y20/2),Y13*-1,X14*(X13*X13)*(Y20-X13)/(Y20*Y20))))) -> 0 | AC13: Distancia de nudo a carga puntual | AE13: =-1*(IF(AE20=0,0,IF(AD13=0,0,IF(AD14=0,0,IF(AD13=(AE20/2),AD14*AE20/8,AD14*AD13*((AE20-AD13)*(AE20-AD13))/(AE20*AE20)))))) -> 0 | AF13: =IF(AE20=0,0,IF(AD13=0,0,IF(AD14=0,0,IF(AD13=(AE20/2),AE13*-1,AD14*(AD13*AD13)*(AE20-AD13)/(AE20*AE20))))) -> 0 | AI13: Distancia de nudo a carga puntual | AK13: =-1*(IF(AK20=0,0,IF(AJ13=0,0,IF(AJ14=0,0,IF(AJ13=(AK20/2),AJ14*AK20/8,AJ14*AJ13*((AK20-AJ13)*(AK20-AJ13))/(AK20*AK20)))))) -> 0 | AL13: =IF(AK20=0,0,IF(AJ13=0,0,IF(AJ14=0,0,IF(AJ13=(AK20/2),AK13*-1,AJ14*(AJ13*AJ13)*(AK20-AJ13)/(AK20*AK20))))) -> 0 | AO13: Distancia de nudo a carga puntual | AQ13: =-1*(IF(AQ20=0,0,IF(AP13=0,0,IF(AP14=0,0,IF(AP13=(AQ20/2),AP14*AQ20/8,AP14*AP13*((AQ20-AP13)*(AQ20-AP13))/(AQ20*AQ20)))))) -> 0 | AR13: =IF(AQ20=0,0,IF(AP13=0,0,IF(AP14=0,0,IF(AP13=(AQ20/2),AQ13*-1,AP14*(AP13*AP13)*(AQ20-AP13)/(AQ20*AQ20))))) -> 0 | AU13: Distancia de nudo a carga puntual | AW13: =-1*(IF(AW20=0,0,IF(AV13=0,0,IF(AV14=0,0,IF(AV13=(AW20/2),AV14*AW20/8,AV14*AV13*((AW20-AV13)*(AW20-AV13))/(AW20*AW20)))))) -> 0 | AX13: =IF(AW20=0,0,IF(AV13=0,0,IF(AV14=0,0,IF(AV13=(AW20/2),AW13*-1,AV14*(AV13*AV13)*(AW20-AV13)/(AW20*AW20))))) -> 0 | BA13: Distancia de nudo a carga puntual | BC13: =-1*(IF(BC20=0,0,IF(BB13=0,0,IF(BB14=0,0,IF(BB13=(BC20/2),BB14*BC20/8,BB14*BB13*((BC20-BB13)*(BC20-BB13))/(BC20*BC20)))))) -> 0 | BD13: =IF(BC20=0,0,IF(BB13=0,0,IF(BB14=0,0,IF(BB13=(BC20/2),BC13*-1,BB14*(BB13*BB13)*(BC20-BB13)/(BC20*BC20))))) -> 0
E14: Carga Puntual | K14: Carga Puntual | Q14: Carga Puntual | W14: Carga Puntual | AC14: Carga Puntual | AI14: Carga Puntual | AO14: Carga Puntual | AU14: Carga Puntual | BA14: Carga Puntual
E15: Distancia de nudo a carga puntual | G15: =-1*(IF(G20=0,0,IF(F15=0,0,IF(F16=0,0,IF(F15=(G20/2),F16*G20/8,F16*F15*((G20-F15)*(G20-F15))/(G20*G20)))))) -> 0 | H15: =IF(G20=0,0,IF(F15=0,0,IF(F16=0,0,IF(F15=(G20/2),G15*-1,F16*(F15*F15)*(G20-F15)/(G20*G20))))) -> 0 | K15: Distancia de nudo a carga puntual | M15: =-1*(IF(M20=0,0,IF(L15=0,0,IF(L16=0,0,IF(L15=(M20/2),L16*M20/8,L16*L15*((M20-L15)*(M20-L15))/(M20*M20)))))) -> 0 | N15: =IF(M20=0,0,IF(L15=0,0,IF(L16=0,0,IF(L15=(M20/2),M15*-1,L16*(L15*L15)*(M20-L15)/(M20*M20))))) -> 0 | Q15: Distancia de nudo a carga puntual | S15: =-1*(IF(S20=0,0,IF(R15=0,0,IF(R16=0,0,IF(R15=(S20/2),R16*S20/8,R16*R15*((S20-R15)*(S20-R15))/(S20*S20)))))) -> 0 | T15: =IF(S20=0,0,IF(R15=0,0,IF(R16=0,0,IF(R15=(S20/2),S15*-1,R16*(R15*R15)*(S20-R15)/(S20*S20))))) -> 0 | W15: Distancia de nudo a carga puntual | Y15: =-1*(IF(Y20=0,0,IF(X15=0,0,IF(X16=0,0,IF(X15=(Y20/2),X16*Y20/8,X16*X15*((Y20-X15)*(Y20-X15))/(Y20*Y20)))))) -> 0 | Z15: =IF(Y20=0,0,IF(X15=0,0,IF(X16=0,0,IF(X15=(Y20/2),Y15*-1,X16*(X15*X15)*(Y20-X15)/(Y20*Y20))))) -> 0 | AC15: Distancia de nudo a carga puntual | AE15: =-1*(IF(AE20=0,0,IF(AD15=0,0,IF(AD16=0,0,IF(AD15=(AE20/2),AD16*AE20/8,AD16*AD15*((AE20-AD15)*(AE20-AD15))/(AE20*AE20)))))) -> 0 | AF15: =IF(AE20=0,0,IF(AD15=0,0,IF(AD16=0,0,IF(AD15=(AE20/2),AE15*-1,AD16*(AD15*AD15)*(AE20-AD15)/(AE20*AE20))))) -> 0 | AI15: Distancia de nudo a carga puntual | AK15: =-1*(IF(AK20=0,0,IF(AJ15=0,0,IF(AJ16=0,0,IF(AJ15=(AK20/2),AJ16*AK20/8,AJ16*AJ15*((AK20-AJ15)*(AK20-AJ15))/(AK20*AK20)))))) -> 0 | AL15: =IF(AK20=0,0,IF(AJ15=0,0,IF(AJ16=0,0,IF(AJ15=(AK20/2),AK15*-1,AJ16*(AJ15*AJ15)*(AK20-AJ15)/(AK20*AK20))))) -> 0 | AO15: Distancia de nudo a carga puntual | AQ15: =-1*(IF(AQ20=0,0,IF(AP15=0,0,IF(AP16=0,0,IF(AP15=(AQ20/2),AP16*AQ20/8,AP16*AP15*((AQ20-AP15)*(AQ20-AP15))/(AQ20*AQ20)))))) -> 0 | AR15: =IF(AQ20=0,0,IF(AP15=0,0,IF(AP16=0,0,IF(AP15=(AQ20/2),AQ15*-1,AP16*(AP15*AP15)*(AQ20-AP15)/(AQ20*AQ20))))) -> 0 | AU15: Distancia de nudo a carga puntual | AW15: =-1*(IF(AW20=0,0,IF(AV15=0,0,IF(AV16=0,0,IF(AV15=(AW20/2),AV16*AW20/8,AV16*AV15*((AW20-AV15)*(AW20-AV15))/(AW20*AW20)))))) -> 0 | AX15: =IF(AW20=0,0,IF(AV15=0,0,IF(AV16=0,0,IF(AV15=(AW20/2),AW15*-1,AV16*(AV15*AV15)*(AW20-AV15)/(AW20*AW20))))) -> 0 | BA15: Distancia de nudo a carga puntual | BC15: =-1*(IF(BC20=0,0,IF(BB15=0,0,IF(BB16=0,0,IF(BB15=(BC20/2),BB16*BC20/8,BB16*BB15*((BC20-BB15)*(BC20-BB15))/(BC20*BC20)))))) -> 0 | BD15: =IF(BC20=0,0,IF(BB15=0,0,IF(BB16=0,0,IF(BB15=(BC20/2),BC15*-1,BB16*(BB15*BB15)*(BC20-BB15)/(BC20*BC20))))) -> 0
E16: Carga Puntual | K16: Carga Puntual | Q16: Carga Puntual | W16: Carga Puntual | AC16: Carga Puntual | AI16: Carga Puntual | AO16: Carga Puntual | AU16: Carga Puntual | BA16: Carga Puntual
A17: trabes 1-2 | E17: Distancia de nudo a carga puntual | G17: =-1*(IF(G20=0,0,IF(F17=0,0,IF(F18=0,0,IF(F17=(G20/2),F18*G20/8,F18*F17*((G20-F17)*(G20-F17))/(G20*G20)))))) -> 0 | H17: =IF(G20=0,0,IF(F17=0,0,IF(F18=0,0,IF(F17=(G20/2),G17*-1,F18*(F17*F17)*(G20-F17)/(G20*G20))))) -> 0 | K17: Distancia de nudo a carga puntual | M17: =-1*(IF(M20=0,0,IF(L17=0,0,IF(L18=0,0,IF(L17=(M20/2),L18*M20/8,L18*L17*((M20-L17)*(M20-L17))/(M20*M20)))))) -> 0 | N17: =IF(M20=0,0,IF(L17=0,0,IF(L18=0,0,IF(L17=(M20/2),M17*-1,L18*(L17*L17)*(M20-L17)/(M20*M20))))) -> 0 | Q17: Distancia de nudo a carga puntual | S17: =-1*(IF(S20=0,0,IF(R17=0,0,IF(R18=0,0,IF(R17=(S20/2),R18*S20/8,R18*R17*((S20-R17)*(S20-R17))/(S20*S20)))))) -> 0 | T17: =IF(S20=0,0,IF(R17=0,0,IF(R18=0,0,IF(R17=(S20/2),S17*-1,R18*(R17*R17)*(S20-R17)/(S20*S20))))) -> 0 | W17: Distancia de nudo a carga puntual | Y17: =-1*(IF(Y20=0,0,IF(X17=0,0,IF(X18=0,0,IF(X17=(Y20/2),X18*Y20/8,X18*X17*((Y20-X17)*(Y20-X17))/(Y20*Y20)))))) -> 0 | Z17: =IF(Y20=0,0,IF(X17=0,0,IF(X18=0,0,IF(X17=(Y20/2),Y17*-1,X18*(X17*X17)*(Y20-X17)/(Y20*Y20))))) -> 0 | AC17: Distancia de nudo a carga puntual | AE17: =-1*(IF(AE20=0,0,IF(AD17=0,0,IF(AD18=0,0,IF(AD17=(AE20/2),AD18*AE20/8,AD18*AD17*((AE20-AD17)*(AE20-AD17))/(AE20*AE20)))))) -> 0 | AF17: =IF(AE20=0,0,IF(AD17=0,0,IF(AD18=0,0,IF(AD17=(AE20/2),AE17*-1,AD18*(AD17*AD17)*(AE20-AD17)/(AE20*AE20))))) -> 0 | AI17: Distancia de nudo a carga puntual | AK17: =-1*(IF(AK20=0,0,IF(AJ17=0,0,IF(AJ18=0,0,IF(AJ17=(AK20/2),AJ18*AK20/8,AJ18*AJ17*((AK20-AJ17)*(AK20-AJ17))/(AK20*AK20)))))) -> 0 | AL17: =IF(AK20=0,0,IF(AJ17=0,0,IF(AJ18=0,0,IF(AJ17=(AK20/2),AK17*-1,AJ18*(AJ17*AJ17)*(AK20-AJ17)/(AK20*AK20))))) -> 0 | AO17: Distancia de nudo a carga puntual | AQ17: =-1*(IF(AQ20=0,0,IF(AP17=0,0,IF(AP18=0,0,IF(AP17=(AQ20/2),AP18*AQ20/8,AP18*AP17*((AQ20-AP17)*(AQ20-AP17))/(AQ20*AQ20)))))) -> 0 | AR17: =IF(AQ20=0,0,IF(AP17=0,0,IF(AP18=0,0,IF(AP17=(AQ20/2),AQ17*-1,AP18*(AP17*AP17)*(AQ20-AP17)/(AQ20*AQ20))))) -> 0 | AU17: Distancia de nudo a carga puntual | AW17: =-1*(IF(AW20=0,0,IF(AV17=0,0,IF(AV18=0,0,IF(AV17=(AW20/2),AV18*AW20/8,AV18*AV17*((AW20-AV17)*(AW20-AV17))/(AW20*AW20)))))) -> 0 | AX17: =IF(AW20=0,0,IF(AV17=0,0,IF(AV18=0,0,IF(AV17=(AW20/2),AW17*-1,AV18*(AV17*AV17)*(AW20-AV17)/(AW20*AW20))))) -> 0 | BA17: Distancia de nudo a carga puntual | BC17: =-1*(IF(BC20=0,0,IF(BB17=0,0,IF(BB18=0,0,IF(BB17=(BC20/2),BB18*BC20/8,BB18*BB17*((BC20-BB17)*(BC20-BB17))/(BC20*BC20)))))) -> 0 | BD17: =IF(BC20=0,0,IF(BB17=0,0,IF(BB18=0,0,IF(BB17=(BC20/2),BC17*-1,BB18*(BB17*BB17)*(BC20-BB17)/(BC20*BC20))))) -> 0
A18: long | E18: Carga Puntual | K18: Carga Puntual | Q18: Carga Puntual | W18: Carga Puntual | AC18: Carga Puntual | AI18: Carga Puntual | AO18: Carga Puntual | AU18: Carga Puntual | BA18: Carga Puntual | BH18: long.
A19: w | F19: Momento total en Nudos = suma. | G19: =SUM(G5:G18) -> -0.29198706 | H19: =SUM(H5:H18) -> 0.29198706 | L19: Momento total en Nudos = suma. | M19: =SUM(M5:M18) -> -0.20302738 | N19: =SUM(N5:N18) -> 0.20302738 | R19: Momento total en Nudos = suma. | S19: =SUM(S5:S18) -> -0.35304846 | T19: =SUM(T5:T18) -> 0.35304846 | X19: Momento total en Nudos = suma. | Y19: =SUM(Y5:Y18) -> -0.56450399 | Z19: =SUM(Z5:Z18) -> 0.56450399 | AD19: Momento total en Nudos = suma. | AE19: =SUM(AE5:AE18) -> 0 | AF19: =SUM(AF5:AF18) -> 0 | AJ19: Momento total en Nudos = suma. | AK19: =SUM(AK5:AK18) -> 0 | AL19: =SUM(AL5:AL18) -> 0 | AP19: Momento total en Nudos = suma. | AQ19: =SUM(AQ5:AQ18) -> 0 | AR19: =SUM(AR5:AR18) -> 0 | AV19: Momento total en Nudos = suma. | AW19: =SUM(AW5:AW18) -> 0 | AX19: =SUM(AX5:AX18) -> 0 | BB19: Momento total en Nudos = suma. | BC19: =SUM(BC5:BC18) -> 0 | BD19: =SUM(BD5:BD18) -> 0 | BH19: w
E20: =D20+C21+D22+E21 -> -0.5 | G20: 2.51 | H20: 0 | K20: =J20+I21+J22+K21 -> -0.5 | M20: 2.093 | Q20: =P20+O21+P22+Q21 -> -0.5 | R20: 0 | S20: 2.76 | T20: 0 | W20: =V20+U21+V22+W21 -> -0.5 | Y20: 3.49 | AC20: =AB20+AA21+AB22+AC21 -> -0.5 | AD20: 0 | AE20: 0 | AI20: =AH20+AG21+AH22+AI21 -> 0 | AJ20: 0 | AK20: =AE20 -> 0 | AO20: =AN20+AM21+AN22+AO21 -> 0 | AP20: 0 | AQ20: =AK20 -> 0 | AU20: =AT20+AS21+AT22+AU21 -> 0 | AV20: 0 | AW20: =AQ20 -> 0 | BA20: =AZ20+AY21+AZ22+BA21 -> 0 | BB20: 0 | BC20: 0 | BG20: =BF20+BE21+BF22+BG21 -> 0 | BI20: =BI19*BI18 -> 0
A21: momento | D21: =B21+F21 -> -0.29198706 | E21: =IF(G22=0,0,IF(F20=3,0,IF(H20=3,0,IF(H20=2,-0.5,IF(H20=1,0,-0.5))))) -> -0.5 | F21: =G19 -> -0.29198706 | G21: 3 | H21: =H19 -> 0.29198706 | I21: =IF(G22=0,0,IF(H20=3,0,IF(F20=3,0,IF(F20=2,-0.5,IF(F20=1,0,(G22/(G22+M22))*(-0.5)))))) -> -0.22735173 | J21: =IF(G20=0,H22+L21,IF(M20=0,L22+H21,H21+L21)) -> 0.088959676 | K21: =IF(M22=0,0,IF(L20=3,0,IF(N20=3,0,IF(N20=2,-0.5,IF(N20=1,0,(M22/(M22+G22))*(-0.5)))))) -> -0.27264827 | L21: =M19 -> -0.20302738 | M21: 3 | N21: =N19 -> 0.20302738 | O21: =IF(M22=0,0,IF(N20=3,0,IF(L20=3,0,IF(L20=2,-0.5,IF(L20=1,0,(M22/(M22+S22))*(-0.5)))))) -> -0.28436019 | P21: =IF(M20=0,N22+R21,IF(S20=0,R22+N21,N21+R21)) -> -0.15002108 | Q21: =IF(S22=0,0,IF(R20=3,0,IF(T20=3,0,IF(T20=2,-0.5,IF(T20=1,0,(S22/(S22+M22))*(-0.5)))))) -> -0.21563981 | R21: =S19 -> -0.35304846 | S21: 3 | T21: =T19 -> 0.35304846 | U21: =IF(S22=0,0,IF(T20=3,0,IF(R20=3,0,IF(R20=2,-0.5,IF(R20=1,0,(S22/(S22+Y22))*(-0.5)))))) -> -0.2792 | V21: =IF(S20=0,T22+X21,IF(Y20=0,X22+T21,T21+X21)) -> -0.21145553 | W21: =IF(Y22=0,0,IF(X20=3,0,IF(Z20=3,0,IF(Z20=2,-0.5,IF(Z20=1,0,(Y22/(Y22+S22))*(-0.5)))))) -> -0.2208 | X21: =Y19 -> -0.56450399 | Y21: 3 | Z21: =Z19 -> 0.56450399 | AA21: =IF(Y22=0,0,IF(Z20=3,0,IF(X20=3,0,IF(X20=2,-0.5,IF(X20=1,0,(Y22/(Y22+AE22))*(-0.5)))))) -> -0.5 | AB21: =IF(Y20=0,Z22+AD21,IF(AE20=0,AD22+Z21,Z21+AD21)) -> 0.56450399 | AC21: =IF(AE22=0,0,IF(AD20=3,0,IF(AF20=3,0,IF(AF20=2,-0.5,IF(AF20=1,0,(AE22/(AE22+Y22))*(-0.5)))))) -> 0 | AD21: =AE19 -> 0 | AE21: 2 | AF21: =AF19 -> 0 | AG21: =IF(AE22=0,0,IF(AF20=3,0,IF(AD20=3,0,IF(AD20=2,-0.5,IF(AD20=1,0,(AE22/(AE22+AK22))*(-0.5)))))) -> 0 | AH21: =IF(AE20=0,AF22+AJ21,IF(AK20=0,AJ22+AF21,AF21+AJ21)) -> 0 | AI21: =IF(AK22=0,0,IF(AJ20=3,0,IF(AL20=3,0,IF(AL20=2,-0.5,IF(AL20=1,0,(AK22/(AK22+AE22))*(-0.5)))))) -> 0 | AJ21: =AK19 -> 0 | AK21: 2 | AL21: =AL19 -> 0 | AM21: =IF(AK22=0,0,IF(AL20=3,0,IF(AJ20=3,0,IF(AJ20=2,-0.5,IF(AJ20=1,0,(AK22/(AK22+AQ22))*(-0.5)))))) -> 0 | AN21: =IF(AK20=0,AL22+AP21,IF(AQ20=0,AP22+AL21,AL21+AP21)) -> 0 | AO21: =IF(AQ22=0,0,IF(AP20=3,0,IF(AR20=3,0,IF(AR20=2,-0.5,IF(AR20=1,0,(AQ22/(AQ22+AK22))*(-0.5)))))) -> 0 | AP21: =AQ19 -> 0 | AQ21: 2 | AR21: =AR19 -> 0 | AS21: =IF(AQ22=0,0,IF(AR20=3,0,IF(AP20=3,0,IF(AP20=2,-0.5,IF(AP20=1,0,(AQ22/(AQ22+AW22))*(-0.5)))))) -> 0 | AT21: =IF(AQ20=0,AR22+AV21,IF(AW20=0,AV22+AR21,AR21+AV21)) -> 0 | AU21: =IF(AW22=0,0,IF(AV20=3,0,IF(AX20=3,0,IF(AX20=2,-0.5,IF(AX20=1,0,(AW22/(AW22+AQ22))*(-0.5)))))) -> 0 | AV21: =AW19 -> 0 | AW21: 2 | AX21: =AX19 -> 0 | AY21: =IF(AW22=0,0,IF(AX20=3,0,IF(AV20=3,0,IF(AV20=2,-0.5,IF(AV20=1,0,(AW22/(AW22+BC22))*(-0.5)))))) -> 0 | AZ21: =IF(AW20=0,AX22+BB21,IF(BC20=0,BB22+AX21,AX21+BB21)) -> 0 | BA21: =IF(BC22=0,0,IF(BB20=3,0,IF(BD20=3,0,IF(BD20=2,-0.5,IF(BD20=1,0,(BC22/(BC22+AW22))*(-0.5)))))) -> 0 | BB21: =BC19 -> 0 | BC21: 2 | BD21: =BD19 -> 0 | BE21: =IF(BC22=0,0,IF(BD20=3,0,IF(BB20=3,0,IF(BB20=2,-0.5,IF(BB20=1,0,-0.5))))) -> 0 | BF21: =BD21+BH21 -> 0 | BH21: 0
G22: =IF(G20=0,0,G21/G20) -> 1.1952191 | M22: =IF(M20=0,0,M21/M20) -> 1.4333493 | S22: =IF(S20=0,0,S21/S20) -> 1.0869565 | X22: =1.5*1.5*(X5+X6)/-2 -> -0.62567662 | Y22: =IF(Y20=0,0,Y21/Y20) -> 0.85959885 | AE22: =IF(AE20=0,0,AE21/AE20) -> 0 | AK22: =IF(AK20=0,0,AK21/AK20) -> 0 | AQ22: =IF(AQ20=0,0,AQ21/AQ20) -> 0 | AW22: =IF(AW20=0,0,AW21/AW20) -> 0 | BC22: =IF(BC20=0,0,BC21/BC20) -> 0
A23: voladizo | B23: =B18*B19 -> 0 | D23: =B23 -> 0 | E23: =(D21+I23)*E21 -> 0.1590471 | G23: momento puro: | H23: =F3 -> 0 | I23: =(J21+O23)*I21 -> -0.026107147 | J23: reacción | K23: =(J21+O23)*K21 -> -0.031308619 | M23: momento puro: | N23: =L3 -> 0 | O23: =(P21+U23)*O21 -> 0.025871857 | P23: reacción | Q23: =(P21+U23)*Q21 -> 0.019619492 | S23: momento puro: | T23: =R3 -> 0 | U23: =(V21)*U21 -> 0.059038383 | V23: reacción | W23: =(V21)*W21 -> 0.04668938 | Y23: momento puro: | Z23: =X3 -> 0 | AA23: =(AB21+W23)*AA21 -> -0.30559668 | AB23: reacción | AC23: =(AB21+W23)*AC21 -> 0 | AE23: momento puro: | AF23: =AD3 -> 0 | AG23: =(AH21+AC23)*AG21 -> 0 | AH23: reacción | AI23: =(AH21+AC23)*AI21 -> 0 | AK23: momento puro: | AL23: =AJ3 -> 0 | AM23: =(AN21+AI23)*AM21 -> 0 | AN23: reacción | AO23: =(AN21+AI23)*AO21 -> 0 | AQ23: momento puro: | AR23: =AP3 -> 0 | AS23: =(AT21+AO23)*AS21 -> 0 | AT23: reacción | AU23: =(AT21+AO23)*AU21 -> 0 | AW23: momento puro: | AX23: =AV3 -> 0 | AY23: =(AZ21+AU23)*AY21 -> 0 | AZ23: reacción | BA23: =(AZ21+AU23)*BA21 -> 0 | BC23: momento puro: | BD23: =BB3 -> 0 | BE23: =(BF21+BA23)*BE21 -> 0 | BF23: =BI20 -> 0
C24: reacciones en el nudo | D24: =F34+B23 -> 0.56297435 | E24: =(D21+I24)*E21 -> 0.17555799 | F24: =IF(G20=0,0,IF(H23=0,0,-1*(H23/G20))) -> 0 | G24: reacciones | H24: =IF(G20=0,0,IF(H23=0,0,H23/G20)) -> 0 | I24: =(J21+E23+O24)*I21 -> -0.059128925 | J24: =IF(G20=0,L34+H35,IF(M20=0,L35+H34,H34+L34)) -> 1.496098 | K24: =(J21+E23+O24)*K21 -> -0.070909509 | L24: =IF(M20=0,0,IF(N23=0,0,-1*(N23/M20))) -> 0 | M24: reacciones | N24: =IF(M20=0,0,IF(N23=0,0,N23/M20)) -> 0 | O24: =(P21+K23+U24)*O21 -> 0.01207009 | P24: =IF(M20=0,R34+N35,IF(S20=0,R35+N34,N34+R34)) -> 1.0871711 | Q24: =(P21+K23+U24)*Q21 -> 0.0091531517 | R24: =IF(S20=0,0,IF(T23=0,0,-1*(T23/S20))) -> 0 | S24: reacciones | T24: =IF(S20=0,0,IF(T23=0,0,T23/S20)) -> 0 | U24: =(V21+Q23+AA23)*U21 -> 0.13888322 | V24: =IF(S20=0,X34+T35,IF(Y20=0,X35+T34,T34+X34)) -> 2.1110245 | W24: =(V21+Q23+AA23)*W21 -> 0.10983314 | X24: =IF(Y20=0,0,IF(Z23=0,0,-1*(Z23/Y20))) -> 0 | Y24: reacciones | Z24: =IF(Y20=0,0,IF(Z23=0,0,Z23/Y20)) -> 0 | AA24: =(AB21+W24+AG23)*AA21 -> -0.33716857 | AB24: =IF(Y20=0,AD34+Z35,IF(AE20=0,AD35+Z34,Z34+AD34)) -> 0.77870388 | AC24: =(AB21+W24+AG23)*AC21 -> 0 | AD24: =IF(AE20=0,0,IF(AF23=0,0,-1*(AF23/AE20))) -> 0 | AE24: reacciones | AF24: =IF(AE20=0,0,IF(AF23=0,0,AF23/AE20)) -> 0 | AG24: =(AH21+AC24+AM23)*AG21 -> 0 | AH24: =IF(AE20=0,AJ34+AF35,IF(AK20=0,AJ35+AF34,AF34+AJ34)) -> 0 | AI24: =(AH21+AC24+AM23)*AI21 -> 0 | AJ24: =IF(AK20=0,0,IF(AL23=0,0,-1*(AL23/AK20))) -> 0 | AK24: reacciones | AL24: =IF(AK20=0,0,IF(AL23=0,0,AL23/AK20)) -> 0 | AM24: =(AN21+AI24+AS23)*AM21 -> 0 | AN24: =IF(AK20=0,AP34+AL35,IF(AQ20=0,AP35+AL34,AL34+AP34)) -> 0 | AO24: =(AN21+AI24+AS23)*AO21 -> 0 | AP24: =IF(AQ20=0,0,IF(AR23=0,0,-1*(AR23/AQ20))) -> 0 | AQ24: reacciones | AR24: =IF(AQ20=0,0,IF(AR23=0,0,AR23/AQ20)) -> 0 | AS24: =(AT21+AO24+AY23)*AS21 -> 0 | AT24: =IF(AQ20=0,AV34+AR35,IF(AW20=0,AV35+AR34,AR34+AV34)) -> 0 | AU24: =(AT21+AO24+AY23)*AU21 -> 0 | AV24: =IF(AW20=0,0,IF(AX23=0,0,-1*(AX23/AW20))) -> 0 | AW24: reacciones | AX24: =IF(AW20=0,0,IF(AX23=0,0,AX23/AW20)) -> 0 | AY24: =(AZ21+AU24+BE23)*AY21 -> 0 | AZ24: =IF(AW20=0,BB34+AX35,IF(BC20=0,BB35+AX34,AX34+BB34)) -> 0 | BA24: =(AZ21+AU24+BE23)*BA21 -> 0 | BB24: =IF(BC20=0,0,IF(BD23=0,0,-1*(BD23/BC20))) -> 0 | BC24: reacciones | BD24: =IF(BC20=0,0,IF(BD23=0,0,BD23/BC20)) -> 0 | BE24: =(BF21+BA24)*BE21 -> 0 | BF24: =BD34+BF23 -> 0 | BG24: Cortante en el nudo
E25: =(D21+I25)*E21 -> 0.17833558 | G25: Reacciones por cargas | I25: =(J21+E24+O25)*I21 -> -0.064684094 | K25: =(J21+E24+O25)*K21 -> -0.077571465 | M25: Reacciones por cargas | O25: =(P21+K24+U25)*O21 -> 0.019993451 | Q25: =(P21+K24+U25)*Q21 -> 0.0151617 | S25: Reacciones por cargas | U25: =(V21+Q24+AA24)*U21 -> 0.15062029 | W25: =(V21+Q24+AA24)*W21 -> 0.11911518 | Y25: Reacciones por cargas | AA25: =(AB21+W25+AG24)*AA21 -> -0.34180959 | AC25: =(AB21+W25+AG24)*AC21 -> 0 | AE25: Reacciones por cargas | AG25: =(AH21+AC25+AM24)*AG21 -> 0 | AI25: =(AH21+AC25+AM24)*AI21 -> 0 | AK25: Reacciones por cargas | AM25: =(AN21+AI25+AS24)*AM21 -> 0 | AO25: =(AN21+AI25+AS24)*AO21 -> 0 | AQ25: Reacciones por cargas | AS25: =(AT21+AO25+AY24)*AS21 -> 0 | AU25: =(AT21+AO25+AY24)*AU21 -> 0 | AW25: Reacciones por cargas | AY25: =(AZ21+AU25+BE24)*AY21 -> 0 | BA25: =(AZ21+AU25+BE24)*BA21 -> 0 | BC25: Reacciones por cargas | BE25: =(BF21+BA25)*BE21 -> 0
E26: =(D21+I26)*E21 -> 0.17887901 | F26: =IF(G20=0,0,IF(F7=0,0,IF(F8=0,0,F8*(G20-F7)/G20))) -> 0 | G26: puntual 1 | H26: =IF(G20=0,0,IF(F7=0,0,IF(F8=0,0,F8*F7/G20))) -> 0 | I26: =(J21+E25+O26)*I21 -> -0.065770961 | K26: =(J21+E25+O26)*K21 -> -0.078874875 | L26: =IF(M20=0,0,IF(L7=0,0,IF(L8=0,0,L8*(M20-L7)/M20))) -> 0 | M26: puntual 1 | N26: =IF(M20=0,0,IF(L7=0,0,IF(L8=0,0,L8*L7/M20))) -> 0 | O26: =(P21+K25+U26)*O21 -> 0.021996419 | Q26: =(P21+K25+U26)*Q21 -> 0.016680617 | R26: =IF(S20=0,0,IF(R7=0,0,IF(R8=0,0,R8*(S20-R7)/S20))) -> 0 | S26: puntual 1 | T26: =IF(S20=0,0,IF(R7=0,0,IF(R8=0,0,R8*R7/S20))) -> 0 | U26: =(V21+Q25+AA25)*U21 -> 0.15023847 | W26: =(V21+Q25+AA25)*W21 -> 0.11881323 | X26: =IF(Y20=0,0,IF(X7=0,0,IF(X8=0,0,X8*(Y20-X7)/Y20))) -> 0 | Y26: puntual 1 | Z26: =IF(Y20=0,0,IF(X7=0,0,IF(X8=0,0,X8*X7/Y20))) -> 0 | AA26: =(AB21+W26+AG25)*AA21 -> -0.34165861 | AC26: =(AB21+W26+AG25)*AC21 -> 0 | AD26: =IF(AE20=0,0,IF(AD7=0,0,IF(AD8=0,0,AD8*(AE20-AD7)/AE20))) -> 0 | AE26: puntual 1 | AF26: =IF(AE20=0,0,IF(AD7=0,0,IF(AD8=0,0,AD8*AD7/AE20))) -> 0 | AG26: =(AH21+AC26+AM25)*AG21 -> 0 | AI26: =(AH21+AC26+AM25)*AI21 -> 0 | AJ26: =IF(AK20=0,0,IF(AJ7=0,0,IF(AJ8=0,0,AJ8*(AK20-AJ7)/AK20))) -> 0 | AK26: puntual 1 | AL26: =IF(AK20=0,0,IF(AJ7=0,0,IF(AJ8=0,0,AJ8*AJ7/AK20))) -> 0 | AM26: =(AN21+AI26+AS25)*AM21 -> 0 | AO26: =(AN21+AI26+AS25)*AO21 -> 0 | AP26: =IF(AQ20=0,0,IF(AP7=0,0,IF(AP8=0,0,AP8*(AQ20-AP7)/AQ20))) -> 0 | AQ26: puntual 1 | AR26: =IF(AQ20=0,0,IF(AP7=0,0,IF(AP8=0,0,AP8*AP7/AQ20))) -> 0 | AS26: =(AT21+AO26+AY25)*AS21 -> 0 | AU26: =(AT21+AO26+AY25)*AU21 -> 0 | AV26: =IF(AW20=0,0,IF(AV7=0,0,IF(AV8=0,0,AV8*(AW20-AV7)/AW20))) -> 0 | AW26: puntual 1 | AX26: =IF(AW20=0,0,IF(AV7=0,0,IF(AV8=0,0,AV8*AV7/AW20))) -> 0 | AY26: =(AZ21+AU26+BE25)*AY21 -> 0 | BA26: =(AZ21+AU26+BE25)*BA21 -> 0 | BB26: =IF(BC20=0,0,IF(BB7=0,0,IF(BB8=0,0,BB8*(BC20-BB7)/BC20))) -> 0 | BC26: puntual 1 | BD26: =IF(BC20=0,0,IF(BB7=0,0,IF(BB8=0,0,BB8*BB7/BC20))) -> 0 | BE26: =(BF21+BA26)*BE21 -> 0
E27: =(D21+I27)*E21 -> 0.17899799 | F27: =IF(G20=0,0,IF(F9=0,0,IF(F10=0,0,F10*(G20-F9)/G20))) -> 0 | G27: puntual 2 | H27: =IF(G20=0,0,IF(F9=0,0,IF(F10=0,0,F10*F9/G20))) -> 0 | I27: =(J21+E26+O27)*I21 -> -0.066008919 | K27: =(J21+E26+O27)*K21 -> -0.079160242 | L27: =IF(M20=0,0,IF(L9=0,0,IF(L10=0,0,L10*(M20-L9)/M20))) -> 0 | M27: puntual 2 | N27: =IF(M20=0,0,IF(L9=0,0,IF(L10=0,0,L10*L9/M20))) -> 0 | O27: =(P21+K26+U27)*O21 -> 0.022499635 | Q27: =(P21+K26+U27)*Q21 -> 0.017062223 | R27: =IF(S20=0,0,IF(R9=0,0,IF(R10=0,0,R10*(S20-R9)/S20))) -> 0 | S27: puntual 2 | T27: =IF(S20=0,0,IF(R9=0,0,IF(R10=0,0,R10*R9/S20))) -> 0 | U27: =(V21+Q26+AA26)*U21 -> 0.14977224 | W27: =(V21+Q26+AA26)*W21 -> 0.11844452 | X27: =IF(Y20=0,0,IF(X9=0,0,IF(X10=0,0,X10*(Y20-X9)/Y20))) -> 0 | Y27: puntual 2 | Z27: =IF(Y20=0,0,IF(X9=0,0,IF(X10=0,0,X10*X9/Y20))) -> 0 | AA27: =(AB21+W27+AG26)*AA21 -> -0.34147426 | AC27: =(AB21+W27+AG26)*AC21 -> 0 | AD27: =IF(AE20=0,0,IF(AD9=0,0,IF(AD10=0,0,AD10*(AE20-AD9)/AE20))) -> 0 | AE27: puntual 2 | AF27: =IF(AE20=0,0,IF(AD9=0,0,IF(AD10=0,0,AD10*AD9/AE20))) -> 0 | AG27: =(AH21+AC27+AM26)*AG21 -> 0 | AI27: =(AH21+AC27+AM26)*AI21 -> 0 | AJ27: =IF(AK20=0,0,IF(AJ9=0,0,IF(AJ10=0,0,AJ10*(AK20-AJ9)/AK20))) -> 0 | AK27: puntual 2 | AL27: =IF(AK20=0,0,IF(AJ9=0,0,IF(AJ10=0,0,AJ10*AJ9/AK20))) -> 0 | AM27: =(AN21+AI27+AS26)*AM21 -> 0 | AO27: =(AN21+AI27+AS26)*AO21 -> 0 | AP27: =IF(AQ20=0,0,IF(AP9=0,0,IF(AP10=0,0,AP10*(AQ20-AP9)/AQ20))) -> 0 | AQ27: puntual 2 | AR27: =IF(AQ20=0,0,IF(AP9=0,0,IF(AP10=0,0,AP10*AP9/AQ20))) -> 0 | AS27: =(AT21+AO27+AY26)*AS21 -> 0 | AU27: =(AT21+AO27+AY26)*AU21 -> 0 | AV27: =IF(AW20=0,0,IF(AV9=0,0,IF(AV10=0,0,AV10*(AW20-AV9)/AW20))) -> 0 | AW27: puntual 2 | AX27: =IF(AW20=0,0,IF(AV9=0,0,IF(AV10=0,0,AV10*AV9/AW20))) -> 0 | AY27: =(AZ21+AU27+BE26)*AY21 -> 0 | BA27: =(AZ21+AU27+BE26)*BA21 -> 0 | BB27: =IF(BC20=0,0,IF(BB9=0,0,IF(BB10=0,0,BB10*(BC20-BB9)/BC20))) -> 0 | BC27: puntual 2 | BD27: =IF(BC20=0,0,IF(BB9=0,0,IF(BB10=0,0,BB10*BB9/BC20))) -> 0 | BE27: =(BF21+BA27)*BE21 -> 0
E28: =(D21+I28)*E21 -> 0.17902585 | F28: =IF(G20=0,0,IF(F11=0,0,IF(F12=0,0,F12*(G20-F11)/G20))) -> 0 | G28: puntual 3 | H28: =IF(G20=0,0,IF(F11=0,0,IF(F12=0,0,F12*F11/G20))) -> 0 | I28: =(J21+E27+O28)*I21 -> -0.066064633 | K28: =(J21+E27+O28)*K21 -> -0.079227057 | L28: =IF(M20=0,0,IF(L11=0,0,IF(L12=0,0,L12*(M20-L11)/M20))) -> 0 | M28: puntual 3 | N28: =IF(M20=0,0,IF(L11=0,0,IF(L12=0,0,L12*L11/M20))) -> 0 | O28: =(P21+K27+U28)*O21 -> 0.022625715 | Q28: =(P21+K27+U28)*Q21 -> 0.017157834 | R28: =IF(S20=0,0,IF(R11=0,0,IF(R12=0,0,R12*(S20-R11)/S20))) -> 0 | S28: puntual 3 | T28: =IF(S20=0,0,IF(R11=0,0,IF(R12=0,0,R12*R11/S20))) -> 0 | U28: =(V21+Q27+AA27)*U21 -> 0.14961422 | W28: =(V21+Q27+AA27)*W21 -> 0.11831956 | X28: =IF(Y20=0,0,IF(X11=0,0,IF(X12=0,0,X12*(Y20-X11)/Y20))) -> 0 | Y28: puntual 3 | Z28: =IF(Y20=0,0,IF(X11=0,0,IF(X12=0,0,X12*X11/Y20))) -> 0 | AA28: =(AB21+W28+AG27)*AA21 -> -0.34141177 | AC28: =(AB21+W28+AG27)*AC21 -> 0 | AD28: =IF(AE20=0,0,IF(AD11=0,0,IF(AD12=0,0,AD12*(AE20-AD11)/AE20))) -> 0 | AE28: puntual 3 | AF28: =IF(AE20=0,0,IF(AD11=0,0,IF(AD12=0,0,AD12*AD11/AE20))) -> 0 | AG28: =(AH21+AC28+AM27)*AG21 -> 0 | AI28: =(AH21+AC28+AM27)*AI21 -> 0 | AJ28: =IF(AK20=0,0,IF(AJ11=0,0,IF(AJ12=0,0,AJ12*(AK20-AJ11)/AK20))) -> 0 | AK28: puntual 3 | AL28: =IF(AK20=0,0,IF(AJ11=0,0,IF(AJ12=0,0,AJ12*AJ11/AK20))) -> 0 | AM28: =(AN21+AI28+AS27)*AM21 -> 0 | AO28: =(AN21+AI28+AS27)*AO21 -> 0 | AP28: =IF(AQ20=0,0,IF(AP11=0,0,IF(AP12=0,0,AP12*(AQ20-AP11)/AQ20))) -> 0 | AQ28: puntual 3 | AR28: =IF(AQ20=0,0,IF(AP11=0,0,IF(AP12=0,0,AP12*AP11/AQ20))) -> 0 | AS28: =(AT21+AO28+AY27)*AS21 -> 0 | AU28: =(AT21+AO28+AY27)*AU21 -> 0 | AV28: =IF(AW20=0,0,IF(AV11=0,0,IF(AV12=0,0,AV12*(AW20-AV11)/AW20))) -> 0 | AW28: puntual 3 | AX28: =IF(AW20=0,0,IF(AV11=0,0,IF(AV12=0,0,AV12*AV11/AW20))) -> 0 | AY28: =(AZ21+AU28+BE27)*AY21 -> 0 | BA28: =(AZ21+AU28+BE27)*BA21 -> 0 | BB28: =IF(BC20=0,0,IF(BB11=0,0,IF(BB12=0,0,BB12*(BC20-BB11)/BC20))) -> 0 | BC28: puntual 3 | BD28: =IF(BC20=0,0,IF(BB11=0,0,IF(BB12=0,0,BB12*BB11/BC20))) -> 0 | BE28: =(BF21+BA28)*BE21 -> 0
E29: =(D21+I29)*E21 -> 0.1790326 | F29: =IF(G20=0,0,IF(F13=0,0,IF(F14=0,0,F14*(G20-F13)/G20))) -> 0 | G29: puntual 4 | H29: =IF(G20=0,0,IF(F13=0,0,IF(F14=0,0,F14*F13/G20))) -> 0 | I29: =(J21+E28+O29)*I21 -> -0.06607814 | K29: =(J21+E28+O29)*K21 -> -0.079243254 | L29: =IF(M20=0,0,IF(L13=0,0,IF(L14=0,0,L14*(M20-L13)/M20))) -> 0 | M29: puntual 4 | N29: =IF(M20=0,0,IF(L13=0,0,IF(L14=0,0,L14*L13/M20))) -> 0 | O29: =(P21+K28+U29)*O21 -> 0.022657267 | Q29: =(P21+K28+U29)*Q21 -> 0.01718176 | R29: =IF(S20=0,0,IF(R13=0,0,IF(R14=0,0,R14*(S20-R13)/S20))) -> 0 | S29: puntual 4 | T29: =IF(S20=0,0,IF(R13=0,0,IF(R14=0,0,R14*R13/S20))) -> 0 | U29: =(V21+Q28+AA28)*U21 -> 0.14957008 | W29: =(V21+Q28+AA28)*W21 -> 0.11828465 | X29: =IF(Y20=0,0,IF(X13=0,0,IF(X14=0,0,X14*(Y20-X13)/Y20))) -> 0 | Y29: puntual 4 | Z29: =IF(Y20=0,0,IF(X13=0,0,IF(X14=0,0,X14*X13/Y20))) -> 0 | AA29: =(AB21+W29+AG28)*AA21 -> -0.34139432 | AC29: =(AB21+W29+AG28)*AC21 -> 0 | AD29: =IF(AE20=0,0,IF(AD13=0,0,IF(AD14=0,0,AD14*(AE20-AD13)/AE20))) -> 0 | AE29: puntual 4 | AF29: =IF(AE20=0,0,IF(AD13=0,0,IF(AD14=0,0,AD14*AD13/AE20))) -> 0 | AG29: =(AH21+AC29+AM28)*AG21 -> 0 | AI29: =(AH21+AC29+AM28)*AI21 -> 0 | AJ29: =IF(AK20=0,0,IF(AJ13=0,0,IF(AJ14=0,0,AJ14*(AK20-AJ13)/AK20))) -> 0 | AK29: puntual 4 | AL29: =IF(AK20=0,0,IF(AJ13=0,0,IF(AJ14=0,0,AJ14*AJ13/AK20))) -> 0 | AM29: =(AN21+AI29+AS28)*AM21 -> 0 | AO29: =(AN21+AI29+AS28)*AO21 -> 0 | AP29: =IF(AQ20=0,0,IF(AP13=0,0,IF(AP14=0,0,AP14*(AQ20-AP13)/AQ20))) -> 0 | AQ29: puntual 4 | AR29: =IF(AQ20=0,0,IF(AP13=0,0,IF(AP14=0,0,AP14*AP13/AQ20))) -> 0 | AS29: =(AT21+AO29+AY28)*AS21 -> 0 | AU29: =(AT21+AO29+AY28)*AU21 -> 0 | AV29: =IF(AW20=0,0,IF(AV13=0,0,IF(AV14=0,0,AV14*(AW20-AV13)/AW20))) -> 0 | AW29: puntual 4 | AX29: =IF(AW20=0,0,IF(AV13=0,0,IF(AV14=0,0,AV14*AV13/AW20))) -> 0 | AY29: =(AZ21+AU29+BE28)*AY21 -> 0 | BA29: =(AZ21+AU29+BE28)*BA21 -> 0 | BB29: =IF(BC20=0,0,IF(BB13=0,0,IF(BB14=0,0,BB14*(BC20-BB13)/BC20))) -> 0 | BC29: puntual 4 | BD29: =IF(BC20=0,0,IF(BB13=0,0,IF(BB14=0,0,BB14*BB13/BC20))) -> 0 | BE29: =(BF21+BA29)*BE21 -> 0
E30: =(D21+I30)*E21 -> 0.17903426 | F30: =IF(G20=0,0,IF(F15=0,0,IF(F16=0,0,F16*(G20-F15)/G20))) -> 0 | G30: puntual 5 | H30: =IF(G20=0,0,IF(F15=0,0,IF(F16=0,0,F16*F15/G20))) -> 0 | I30: =(J21+E29+O30)*I21 -> -0.066081469 | K30: =(J21+E29+O30)*K21 -> -0.079247247 | L30: =IF(M20=0,0,IF(L15=0,0,IF(L16=0,0,L16*(M20-L15)/M20))) -> 0 | M30: puntual 5 | N30: =IF(M20=0,0,IF(L15=0,0,IF(L16=0,0,L16*L15/M20))) -> 0 | O30: =(P21+K29+U30)*O21 -> 0.022665158 | Q30: =(P21+K29+U30)*Q21 -> 0.017187745 | R30: =IF(S20=0,0,IF(R15=0,0,IF(R16=0,0,R16*(S20-R15)/S20))) -> 0 | S30: puntual 5 | T30: =IF(S20=0,0,IF(R15=0,0,IF(R16=0,0,R16*R15/S20))) -> 0 | U30: =(V21+Q29+AA29)*U21 -> 0.14955853 | W30: =(V21+Q29+AA29)*W21 -> 0.11827551 | X30: =IF(Y20=0,0,IF(X15=0,0,IF(X16=0,0,X16*(Y20-X15)/Y20))) -> 0 | Y30: puntual 5 | Z30: =IF(Y20=0,0,IF(X15=0,0,IF(X16=0,0,X16*X15/Y20))) -> 0 | AA30: =(AB21+W30+AG29)*AA21 -> -0.34138975 | AC30: =(AB21+W30+AG29)*AC21 -> 0 | AD30: =IF(AE20=0,0,IF(AD15=0,0,IF(AD16=0,0,AD16*(AE20-AD15)/AE20))) -> 0 | AE30: puntual 5 | AF30: =IF(AE20=0,0,IF(AD15=0,0,IF(AD16=0,0,AD16*AD15/AE20))) -> 0 | AG30: =(AH21+AC30+AM29)*AG21 -> 0 | AI30: =(AH21+AC30+AM29)*AI21 -> 0 | AJ30: =IF(AK20=0,0,IF(AJ15=0,0,IF(AJ16=0,0,AJ16*(AK20-AJ15)/AK20))) -> 0 | AK30: puntual 5 | AL30: =IF(AK20=0,0,IF(AJ15=0,0,IF(AJ16=0,0,AJ16*AJ15/AK20))) -> 0 | AM30: =(AN21+AI30+AS29)*AM21 -> 0 | AO30: =(AN21+AI30+AS29)*AO21 -> 0 | AP30: =IF(AQ20=0,0,IF(AP15=0,0,IF(AP16=0,0,AP16*(AQ20-AP15)/AQ20))) -> 0 | AQ30: puntual 5 | AR30: =IF(AQ20=0,0,IF(AP15=0,0,IF(AP16=0,0,AP16*AP15/AQ20))) -> 0 | AS30: =(AT21+AO30+AY29)*AS21 -> 0 | AU30: =(AT21+AO30+AY29)*AU21 -> 0 | AV30: =IF(AW20=0,0,IF(AV15=0,0,IF(AV16=0,0,AV16*(AW20-AV15)/AW20))) -> 0 | AW30: puntual 5 | AX30: =IF(AW20=0,0,IF(AV15=0,0,IF(AV16=0,0,AV16*AV15/AW20))) -> 0 | AY30: =(AZ21+AU30+BE29)*AY21 -> 0 | BA30: =(AZ21+AU30+BE29)*BA21 -> 0 | BB30: =IF(BC20=0,0,IF(BB15=0,0,IF(BB16=0,0,BB16*(BC20-BB15)/BC20))) -> 0 | BC30: puntual 5 | BD30: =IF(BC20=0,0,IF(BB15=0,0,IF(BB16=0,0,BB16*BB15/BC20))) -> 0 | BE30: =(BF21+BA30)*BE21 -> 0
E31: =(D21+I31)*E21 -> 0.17903468 | F31: =IF(G20=0,0,IF(F5=0,0,F5*G20/2)) -> 0.48687474 | G31: uniforme | H31: =F31 -> 0.48687474 | I31: =(J21+E30+O31)*I21 -> -0.066082297 | K31: =(J21+E30+O31)*K21 -> -0.079248239 | L31: =IF(M20=0,0,IF(L5=0,0,L5*M20/2)) -> 0.40598758 | M31: uniforme | N31: =L31 -> 0.40598758 | O31: =(P21+K30+U31)*O21 -> 0.022667131 | Q31: =(P21+K30+U31)*Q21 -> 0.017189241 | R31: =IF(S20=0,0,IF(R5=0,0,R5*S20/2)) -> 0.53536824 | S31: uniforme | T31: =R31 -> 0.53536824 | U31: =(V21+Q30+AA30)*U21 -> 0.14955558 | W31: =(V21+Q30+AA30)*W21 -> 0.11827318 | X31: =IF(Y20=0,0,IF(X5=0,0,X5*Y20/2)) -> 0.67696926 | Y31: uniforme | Z31: =X31 -> 0.67696926 | AA31: =(AB21+W31+AG30)*AA21 -> -0.34138859 | AC31: =(AB21+W31+AG30)*AC21 -> 0 | AD31: =IF(AE20=0,0,IF(AD5=0,0,AD5*AE20/2)) -> 0 | AE31: uniforme | AF31: =AD31 -> 0 | AG31: =(AH21+AC31+AM30)*AG21 -> 0 | AI31: =(AH21+AC31+AM30)*AI21 -> 0 | AJ31: =IF(AK20=0,0,IF(AJ5=0,0,AJ5*AK20/2)) -> 0 | AK31: uniforme | AL31: =AJ31 -> 0 | AM31: =(AN21+AI31+AS30)*AM21 -> 0 | AO31: =(AN21+AI31+AS30)*AO21 -> 0 | AP31: =IF(AQ20=0,0,IF(AP5=0,0,AP5*AQ20/2)) -> 0 | AQ31: uniforme | AR31: =AP31 -> 0 | AS31: =(AT21+AO31+AY30)*AS21 -> 0 | AU31: =(AT21+AO31+AY30)*AU21 -> 0 | AV31: =IF(AW20=0,0,IF(AV5=0,0,AV5*AW20/2)) -> 0 | AW31: uniforme | AX31: =AV31 -> 0 | AY31: =(AZ21+AU31+BE30)*AY21 -> 0 | BA31: =(AZ21+AU31+BE30)*BA21 -> 0 | BB31: =IF(BC20=0,0,IF(BB5=0,0,BB5*BC20/2)) -> 0 | BC31: uniforme | BD31: =BB31 -> 0 | BE31: =(BF21+BA31)*BE21 -> 0
E32: =(D21+I32)*E21 -> 0.17903478 | F32: =IF(G20=0,0,IF(F6=0,0,F6*G20/2)) -> 0.21110229 | G32: p.p | H32: =F32 -> 0.21110229 | I32: =(J21+E31+O32)*I21 -> -0.066082503 | J32: =2.44*36/12 -> 7.32 | K32: =(J21+E31+O32)*K21 -> -0.079248486 | L32: =IF(M20=0,0,IF(L6=0,0,L6*M20/2)) -> 0.17603072 | M32: p.p | N32: =L32 -> 0.17603072 | O32: =(P21+K31+U32)*O21 -> 0.022667624 | Q32: =(P21+K31+U32)*Q21 -> 0.017189615 | R32: =IF(S20=0,0,IF(R6=0,0,R6*S20/2)) -> 0.23212842 | S32: p.p | T32: =R32 -> 0.23212842 | U32: =(V21+Q31+AA31)*U21 -> 0.14955484 | W32: =(V21+Q31+AA31)*W21 -> 0.1182726 | X32: =IF(Y20=0,0,IF(X6=0,0,X6*Y20/2)) -> 0.2935247 | Y32: p.p | Z32: =X32 -> 0.2935247 | AA32: =(AB21+W32+AG31)*AA21 -> -0.34138829 | AC32: =(AB21+W32+AG31)*AC21 -> 0 | AD32: =IF(AE20=0,0,IF(AD6=0,0,AD6*AE20/2)) -> 0 | AE32: p.p | AF32: =AD32 -> 0 | AG32: =(AH21+AC32+AM31)*AG21 -> 0 | AI32: =(AH21+AC32+AM31)*AI21 -> 0 | AJ32: =IF(AK20=0,0,IF(AJ6=0,0,AJ6*AK20/2)) -> 0 | AK32: p.p | AL32: =AJ32 -> 0 | AM32: =(AN21+AI32+AS31)*AM21 -> 0 | AO32: =(AN21+AI32+AS31)*AO21 -> 0 | AP32: =IF(AQ20=0,0,IF(AP6=0,0,AP6*AQ20/2)) -> 0 | AQ32: p.p | AR32: =AP32 -> 0 | AS32: =(AT21+AO32+AY31)*AS21 -> 0 | AU32: =(AT21+AO32+AY31)*AU21 -> 0 | AV32: =IF(AW20=0,0,IF(AV6=0,0,AV6*AW20/2)) -> 0 | AW32: p.p | AX32: =AV32 -> 0 | AY32: =(AZ21+AU32+BE31)*AY21 -> 0 | BA32: =(AZ21+AU32+BE31)*BA21 -> 0 | BB32: =IF(BC20=0,0,IF(BB6=0,0,BB6*BC20/2)) -> 0 | BC32: p.p | BD32: =BB32 -> 0 | BE32: =(BF21+BA32)*BE21 -> 0
E33: =(D21+I33)*E21 -> 0.17903481 | F33: =IF(G20=0,0,-1*(E38+I38)/G20) -> -0.13500268 | G33: dif. Mom. | H33: =IF(G20=0,0,(E38+I38)/G20) -> 0.13500268 | I33: =(J21+E32+O33)*I21 -> -0.066082554 | J33: =2.44*6/2 -> 7.32 | K33: =(J21+E32+O33)*K21 -> -0.079248548 | L33: =IF(M20=0,0,-1*(K38+O38)/M20) -> 0.081100019 | M33: reacciones | N33: =IF(M20=0,0,(K38+O38)/M20) -> -0.081100019 | O33: =(P21+K32+U33)*O21 -> 0.022667748 | Q33: =(P21+K32+U33)*Q21 -> 0.017189709 | R33: =IF(S20=0,0,-1*(Q38+U38)/S20) -> -0.18124384 | S33: reacciones | T33: =IF(S20=0,0,(Q38+U38)/S20) -> 0.18124384 | U33: =(V21+Q32+AA32)*U21 -> 0.14955465 | W33: =(V21+Q32+AA32)*W21 -> 0.11827245 | X33: =IF(Y20=0,0,-1*(W38+AA38)/Y20) -> 0.19179008 | Y33: reacciones | Z33: =IF(Y20=0,0,(W38+AA38)/Y20) -> -0.19179008 | AA33: =(AB21+W33+AG32)*AA21 -> -0.34138822 | AC33: =(AB21+W33+AG32)*AC21 -> 0 | AD33: =IF(AE20=0,0,-1*(AC38+AG38)/AE20) -> 0 | AE33: reacciones | AF33: =IF(AE20=0,0,(AC38+AG38)/AE20) -> 0 | AG33: =(AH21+AC33+AM32)*AG21 -> 0 | AI33: =(AH21+AC33+AM32)*AI21 -> 0 | AJ33: =IF(AK20=0,0,-1*(AI38+AM38)/AK20) -> 0 | AK33: reacciones | AL33: =IF(AK20=0,0,(AI38+AM38)/AK20) -> 0 | AM33: =(AN21+AI33+AS32)*AM21 -> 0 | AO33: =(AN21+AI33+AS32)*AO21 -> 0 | AP33: =IF(AQ20=0,0,-1*(AO38+AS38)/AQ20) -> 0 | AQ33: reacciones | AR33: =IF(AQ20=0,0,(AO38+AS38)/AQ20) -> 0 | AS33: =(AT21+AO33+AY32)*AS21 -> 0 | AU33: =(AT21+AO33+AY32)*AU21 -> 0 | AV33: =IF(AW20=0,0,-1*(AU38+AY38)/AW20) -> 0 | AW33: reacciones | AX33: =IF(AW20=0,0,(AU38+AY38)/AW20) -> 0 | AY33: =(AZ21+AU33+BE32)*AY21 -> 0 | BA33: =(AZ21+AU33+BE32)*BA21 -> 0 | BB33: =IF(BC20=0,0,-1*(BA38+BE38)/BC20) -> 0 | BC33: reacciones | BD33: =IF(BC20=0,0,(BA38+BE38)/BC20) -> 0 | BE33: =(BF21+BA33)*BE21 -> 0
E34: =(D21+I34)*E21 -> 0.17903481 | F34: =SUM(F24:F33) -> 0.56297435 | G34: suma | H34: =SUM(H24:H33) -> 0.83297972 | I34: =(J21+E33+O34)*I21 -> -0.066082567 | K34: =(J21+E33+O34)*K21 -> -0.079248564 | L34: =SUM(L24:L33) -> 0.66311832 | M34: suma | N34: =SUM(N24:N33) -> 0.50091828 | O34: =(P21+K33+U34)*O21 -> 0.022667778 | Q34: =(P21+K33+U34)*Q21 -> 0.017189732 | R34: =SUM(R24:R33) -> 0.58625282 | S34: suma | T34: =SUM(T24:T33) -> 0.9487405 | U34: =(V21+Q33+AA33)*U21 -> 0.14955461 | W34: =(V21+Q33+AA33)*W21 -> 0.11827241 | X34: =SUM(X24:X33) -> 1.162284 | Y34: suma | Z34: =SUM(Z24:Z33) -> 0.77870388 | AA34: =(AB21+W34+AG33)*AA21 -> -0.3413882 | AC34: =(AB21+W34+AG33)*AC21 -> 0 | AD34: =SUM(AD24:AD33) -> 0 | AE34: suma | AF34: =SUM(AF24:AF33) -> 0 | AG34: =(AH21+AC34+AM33)*AG21 -> 0 | AI34: =(AH21+AC34+AM33)*AI21 -> 0 | AJ34: =SUM(AJ24:AJ33) -> 0 | AK34: suma | AL34: =SUM(AL24:AL33) -> 0 | AM34: =(AN21+AI34+AS33)*AM21 -> 0 | AO34: =(AN21+AI34+AS33)*AO21 -> 0 | AP34: =SUM(AP24:AP33) -> 0 | AQ34: suma | AR34: =SUM(AR24:AR33) -> 0 | AS34: =(AT21+AO34+AY33)*AS21 -> 0 | AU34: =(AT21+AO34+AY33)*AU21 -> 0 | AV34: =SUM(AV24:AV33) -> 0 | AW34: suma | AX34: =SUM(AX24:AX33) -> 0 | AY34: =(AZ21+AU34+BE33)*AY21 -> 0 | BA34: =(AZ21+AU34+BE33)*BA21 -> 0 | BB34: =SUM(BB24:BB33) -> 0 | BC34: suma | BD34: =SUM(BD24:BD33) -> 0 | BE34: =(BF21+BA34)*BE21 -> 0
E35: =(D21+I35)*E21 -> 0.17903481 | G35: cantiliver w | I35: =(J21+E34+O35)*I21 -> -0.06608257 | K35: =(J21+E34+O35)*K21 -> -0.079248567 | M35: cantiliver w | O35: =(P21+K34+U35)*O21 -> 0.022667786 | Q35: =(P21+K34+U35)*Q21 -> 0.017189738 | S35: cantiliver w | U35: =(V21+Q34+AA34)*U21 -> 0.1495546 | W35: =(V21+Q34+AA34)*W21 -> 0.1182724 | X35: =1.5*(X5+X6) -> 0.8342355 | Y35: cantiliver w | AA35: =(AB21+W35+AG34)*AA21 -> -0.3413882 | AC35: =(AB21+W35+AG34)*AC21 -> 0 | AE35: cantiliver w | AG35: =(AH21+AC35+AM34)*AG21 -> 0 | AI35: =(AH21+AC35+AM34)*AI21 -> 0 | AK35: cantiliver w | AM35: =(AN21+AI35+AS34)*AM21 -> 0 | AO35: =(AN21+AI35+AS34)*AO21 -> 0 | AQ35: cantiliver w | AS35: =(AT21+AO35+AY34)*AS21 -> 0 | AU35: =(AT21+AO35+AY34)*AU21 -> 0 | AW35: cantiliver w | AY35: =(AZ21+AU35+BE34)*AY21 -> 0 | BA35: =(AZ21+AU35+BE34)*BA21 -> 0 | BC35: cantiliver w | BE35: =(BF21+BA35)*BE21 -> 0
E36: =(D21+I36)*E21 -> 0.17903482 | I36: =(J21+E35+O36)*I21 -> -0.066082571 | K36: =(J21+E35+O36)*K21 -> -0.079248568 | O36: =(P21+K35+U36)*O21 -> 0.022667788 | Q36: =(P21+K35+U36)*Q21 -> 0.017189739 | U36: =(V21+Q35+AA35)*U21 -> 0.14955459 | W36: =(V21+Q35+AA35)*W21 -> 0.1182724 | AA36: =(AB21+W36+AG35)*AA21 -> -0.34138819 | AC36: =(AB21+W36+AG35)*AC21 -> 0 | AG36: =(AH21+AC36+AM35)*AG21 -> 0 | AI36: =(AH21+AC36+AM35)*AI21 -> 0 | AM36: =(AN21+AI36+AS35)*AM21 -> 0 | AO36: =(AN21+AI36+AS35)*AO21 -> 0 | AS36: =(AT21+AO36+AY35)*AS21 -> 0 | AU36: =(AT21+AO36+AY35)*AU21 -> 0 | AY36: =(AZ21+AU36+BE35)*AY21 -> 0 | BA36: =(AZ21+AU36+BE35)*BA21 -> 0 | BE36: =(BF21+BA36)*BE21 -> 0
A37: M neg max | B37: M pos max | C37: M max | E37: =(D21+I37)*E21 -> 0.17903482 | I37: =(J21+E36+O37)*I21 -> -0.066082571 | K37: =(J21+E36+O37)*K21 -> -0.079248569 | O37: =(P21+K36+U37)*O21 -> 0.022667789 | Q37: =(P21+K36+U37)*Q21 -> 0.01718974 | U37: =(V21+Q36+AA36)*U21 -> 0.14955459 | W37: =(V21+Q36+AA36)*W21 -> 0.1182724 | AA37: =(AB21+W37+AG36)*AA21 -> -0.34138819 | AC37: =(AB21+W37+AG36)*AC21 -> 0 | AG37: =(AH21+AC37+AM36)*AG21 -> 0 | AI37: =(AH21+AC37+AM36)*AI21 -> 0 | AM37: =(AN21+AI37+AS36)*AM21 -> 0 | AO37: =(AN21+AI37+AS36)*AO21 -> 0 | AS37: =(AT21+AO37+AY36)*AS21 -> 0 | AU37: =(AT21+AO37+AY36)*AU21 -> 0 | AY37: =(AZ21+AU37+BE36)*AY21 -> 0 | BA37: =(AZ21+AU37+BE36)*BA21 -> 0 | BE37: =(BF21+BA37)*BE21 -> 0
A38: =MIN(E38:CY38) -> -0.66934739 | B38: =MAX(E38:CY38) -> 1.0717419 | C38: =MAX(B38:B39) -> 1.0717419 | E38: =F21+(2*E37)+I37 -> 0 | G38: =G50 -> 0.40848274 | I38: =H21+(2*I37)+E37 -> 0.33885673 | K38: =L21+(2*K37)+O37 -> -0.33885673 | M38: =M50 -> 0.22787632 | O38: =N21+(2*O37)+K37 -> 0.16911439 | Q38: =R21+(2*Q37)+U37 -> -0.16911439 | S38: =S50 -> 0.27384751 | U38: =T21+(2*U37)+Q37 -> 0.66934739 | W38: =X21+(2*W37)+AA37 -> -0.66934739 | Y38: =Y50 -> 1.0717419 | AA38: =Z21+(2*AA37)+W37 -> 0 | AC38: =AD21+(2*AC37)+AG37 -> 0 | AE38: =AE50 -> 0 | AG38: =AF21+(2*AG37)+AC37 -> 0 | AI38: =AJ21+(2*AI37)+AM37 -> 0 | AK38: =AK50 -> 0 | AM38: =AL21+(2*AM37)+AI37 -> 0 | AO38: =AP21+(2*AO37)+AS37 -> 0 | AQ38: =AQ50 -> 0 | AS38: =AR21+(2*AS37)+AO37 -> 0 | AU38: =AV21+(2*AU37)+AY37 -> 0 | AW38: =AW50 -> 0 | AY38: =AX21+(2*AY37)+AU37 -> 0 | BA38: =BB21+(2*BA37)+BE37 -> 0 | BC38: =BC50 -> 0 | BE38: =BD21+(2*BE37)+BA37 -> 0
B39: =A38*-1 -> 0.66934739 | K39: =I38+K38 -> 1.0044598e-10 | Q39: =O38+Q38 -> -2.4091673e-10 | W39: =U38+W38 -> 6.5428851e-10 | AC39: =AA38+AC38 -> 0 | AI39: =AG38+AI38 -> 0 | AO39: =AM38+AO38 -> 0 | AU39: =AS38+AU38 -> 0 | BA39: =AY38+BA38 -> 0
D41: cortante alto | BF41: =IF(BF42<0.01,IF(BF42>-0.01,"Cierra de diagrama","No Cierra"),"No Cierra") -> Cierra de diagrama
A42: V pos max | B42: V neg max | C42: V max | D42: =D46+D43 -> 0.56297435 | G42: =IF(G45=0,0,D42-E44) -> 0 | J42: =J46+J43 -> 0.66311832 | M42: =IF(M45=0,0,J42-K44) -> 0 | P42: =P46+P43 -> 0.58625282 | S42: =IF(S45=0,0,P42-Q44) -> 0 | V42: =V46+V43 -> 1.162284 | Y42: =IF(Y45=0,0,V42-W44) -> 0 | AB42: =AB46+AB43 -> 0 | AE42: =IF(AE45=0,0,AB42-AC44) -> 0 | AH42: =AH46+AH43 -> 0 | AK42: =IF(AK45=0,0,AH42-AI44) -> 0 | AN42: =AN46+AN43 -> 0 | AQ42: =IF(AQ45=0,0,AN42-AO44) -> 0 | AT42: =AT46+AT43 -> 0 | AW42: =IF(AW45=0,0,AT42-AU44) -> 0 | AZ42: =AZ46+AZ43 -> 0 | BC42: =IF(BC45=0,0,AZ42-BA44) -> 0 | BF42: =BF46+BF43 -> 0
A43: =MAX(E42:CY43) -> 2.1110245 | B43: =MIN(E46:CY46) -> -3.0841866 | C43: =MAX(A43:A44) -> 3.0841866 | D43: =D24 -> 0.56297435 | J43: =J24 -> 1.496098 | P43: =P24 -> 1.0871711 | V43: =V24 -> 2.1110245 | AB43: =AB24 -> 0.77870388 | AH43: =AH24 -> 0 | AN43: =AN24 -> 0 | AT43: =AT24 -> 0 | AZ43: =AZ24 -> 0 | BF43: =BF24 -> 0
A44: =B43*-1 -> 3.0841866 | E44: =G44*G20/2 -> 0.48687474 | F44: w | G44: =F5 -> 0.387948 | I44: =E44 -> 0.48687474 | K44: =M44*M20/2 -> 0.40598758 | L44: w | M44: =L5 -> 0.387948 | O44: =K44 -> 0.40598758 | Q44: =S44*S20/2 -> 0.53536824 | R44: w | S44: =R5 -> 0.387948 | U44: =Q44 -> 0.53536824 | W44: =Y44*Y20/2 -> 0.67696926 | X44: w | Y44: =X5 -> 0.387948 | AA44: =W44 -> 0.67696926 | AC44: =AE44*AE20/2 -> 0 | AD44: w | AE44: =AD5 -> 0.387948 | AG44: =AC44 -> 0 | AI44: =AK44*AK20/2 -> 0 | AJ44: w | AK44: =AJ5 -> 0.387948 | AM44: =AI44 -> 0 | AO44: =AQ44*AQ20/2 -> 0 | AP44: w | AQ44: =AP5 -> 0.387948 | AS44: =AO44 -> 0 | AU44: =AW44*AW20/2 -> 0 | AV44: w | AW44: =AV5 -> 0.387948 | AY44: =AU44 -> 0 | BA44: =BC44*BC20/2 -> 0 | BB44: w | BC44: =BB5 -> 0.387948 | BE44: =BA44 -> 0
F45: p | G45: =F8 -> 0 | I45: =G44*G20 -> 0.97374948 | L45: p | M45: =L8 -> 0 | O45: =M44*M20 -> 0.81197516 | R45: p | S45: =R8 -> 0 | U45: =S44*S20 -> 1.0707365 | X45: p | Y45: =X8 -> 0 | AA45: =Y44*Y20 -> 1.3539385 | AD45: p | AE45: =AD8 -> 0 | AG45: =AE44*AE20 -> 0 | AJ45: p | AK45: =AJ8 -> 0 | AM45: =AK44*AK20 -> 0 | AP45: p | AQ45: =AP8 -> 0 | AS45: =AQ44*AQ20 -> 0 | AV45: p | AW45: =AV8 -> 0 | AY45: =AW44*AW20 -> 0 | BB45: p | BC45: =BB8 -> 3.0841866 | BE45: =BC44*BC20 -> 0
D46: =B23*(-1) -> 0 | G46: =IF(G45=0,0,G42-G45) -> 0 | J46: =IF(G20=0,-1*H35,IF(G45=0,D42-H34-F34,G46-I44)) -> -0.83297972 | M46: =IF(M45=0,0,M42-M45) -> 0 | P46: =IF(M20=0,-1*N35,IF(M45=0,J42-N34-L34,M46-O44)) -> -0.50091828 | S46: =IF(S45=0,0,S42-S45) -> 0 | V46: =IF(S20=0,-1*T35,IF(S45=0,P42-T34-R34,S46-U44)) -> -0.9487405 | Y46: =IF(Y45=0,0,Y42-Y45) -> 0 | AB46: =IF(Y20=0,-1*Z35,IF(Y45=0,V42-Z34-X34,Y46-AA44)) -> -0.77870388 | AE46: =IF(AE45=0,0,AE42-AE45) -> 0 | AH46: =IF(AE20=0,-1*AF35,IF(AE45=0,AB42-AF34-AD34,AE46-AG44)) -> 0 | AK46: =IF(AK45=0,0,AK42-AK45) -> 0 | AN46: =IF(AK20=0,-1*AL35,IF(AK45=0,AH42-AL34-AJ34,AK46-AM44)) -> 0 | AQ46: =IF(AQ45=0,0,AQ42-AQ45) -> 0 | AT46: =IF(AQ20=0,-1*AR35,IF(AQ45=0,AN42-AR34-AP34,AQ46-AS44)) -> 0 | AW46: =IF(AW45=0,0,AW42-AW45) -> 0 | AZ46: =IF(AW20=0,-1*AX35,IF(AW45=0,AT42-AX34-AV34,AW46-AY44)) -> 0 | BC46: =IF(BC45=0,0,BC42-BC45) -> -3.0841866 | BF46: =IF(BC20=0,-1*BD35,IF(BC45=0,AZ42-BD34-BB34,BC46-BE44)) -> 0
F47: Distancia del nudo anterior al punto de inverción o cortante cero
G48: Momento Máximo al centro del claro
H49: distancia del punto de inverción o cortante cero al nudo siguiente
C50: =B21 -> 0 | D50: =D42 -> 0.56297435 | E50: =E38 -> 0 | F50: =IF(D50=0,0,IF(G44=0,0,IF(G45=0,D50/G44,F7))) -> 1.4511593 | G50: =E50+IF(G45=0,D50*F50/2,(D42+G42)*F50/2) -> 0.40848274 | H50: =IF(G20=0,0,G20-F50) -> 1.0588407 | I50: =I38 -> 0.33885673 | J50: =J42 -> 0.66311832 | K50: =K38 -> -0.33885673 | L50: =IF(J50=0,0,IF(M44=0,0,IF(M45=0,J50/M44,L7))) -> 1.7092969 | M50: =K50+IF(M45=0,J50*L50/2,(J42+M42)*L50/2) -> 0.22787632 | N50: =IF(M20=0,0,M20-L50) -> 0.38370308 | O50: =O38 -> 0.16911439 | P50: =P42 -> 0.58625282 | Q50: =Q38 -> -0.16911439 | R50: =IF(P50=0,0,IF(S44=0,0,IF(S45=0,P50/S44,R7))) -> 1.5111634 | S50: =Q50+IF(S45=0,P50*R50/2,(P42+S42)*R50/2) -> 0.27384751 | T50: =IF(S20=0,0,S20-R50) -> 1.2488366 | U50: =U38 -> 0.66934739 | V50: =V42 -> 1.162284 | W50: =W38 -> -0.66934739 | X50: =IF(V50=0,0,IF(Y44=0,0,IF(Y45=0,V50/Y44,X7))) -> 2.995979 | Y50: =W50+IF(Y45=0,V50*X50/2,(V42+Y42)*X50/2) -> 1.0717419 | Z50: =IF(Y20=0,0,Y20-X50) -> 0.49402104 | AA50: =AA38 -> 0 | AB50: =AB42 -> 0 | AC50: =AC38 -> 0 | AD50: =IF(AB50=0,0,IF(AE44=0,0,IF(AE45=0,AB50/AE44,AD7))) -> 0 | AE50: =IF(AE45=0,AB50*AD50/2,(AB42+AE42)*AD50/2) -> 0 | AF50: =IF(AE20=0,0,AE20-AD50) -> 0 | AG50: =AG38 -> 0 | AH50: =AH42 -> 0 | AI50: =AI38 -> 0 | AJ50: =IF(AH50=0,0,IF(AK44=0,0,IF(AK45=0,AH50/AK44,AJ7))) -> 0 | AK50: =IF(AK45=0,AH50*AJ50/2,(AH42+AK42)*AJ50/2) -> 0 | AL50: =IF(AK20=0,0,AK20-AJ50) -> 0 | AM50: =AM38 -> 0 | AN50: =AN42 -> 0 | AO50: =AO38 -> 0 | AP50: =IF(AN50=0,0,IF(AQ44=0,0,IF(AQ45=0,AN50/AQ44,AP7))) -> 0 | AQ50: =IF(AQ45=0,AN50*AP50/2,(AN42+AQ42)*AP50/2) -> 0 | AR50: =IF(AQ20=0,0,AQ20-AP50) -> 0 | AS50: =AS38 -> 0 | AT50: =AT42 -> 0 | AU50: =AU38 -> 0 | AV50: =IF(AT50=0,0,IF(AW44=0,0,IF(AW45=0,AT50/AW44,AV7))) -> 0 | AW50: =IF(AW45=0,AT50*AV50/2,(AT42+AW42)*AV50/2) -> 0 | AX50: =IF(AW20=0,0,AW20-AV50) -> 0 | AY50: =AY38 -> 0 | AZ50: =AZ42 -> 0 | BA50: =BA38 -> 0 | BB50: =IF(AZ50=0,0,IF(BC44=0,0,IF(BC45=0,AZ50/BC44,BB7))) -> 0 | BC50: =IF(BC45=0,AZ50*BB50/2,(AZ42+BC42)*BB50/2) -> 0 | BD50: =IF(BC20=0,0,BC20-BB50) -> 0 | BE50: =BE38 -> 0 | BF50: =BF42 -> 0 | BG50: =BH21 -> 0
D51: Nudo | G51: Barra | H51: =((D42+J46)/2)*G41 -> 0 | K51: Momento en este extremo de la barra
J52: Cortante alto en este extremo de la barra
I53: momento | J53: en este extremo

Sheet formulas
B4: Memoria de Calculo | K4: Antecedentes Geológicos. | AC4: Análisis Histórico | AL4: Estudio de Mecánica de Suelos | AU4: Bajando Cargas: | BD4: Recomendaciones de Estructuracion | BM4: Edificio 1.- Centro De Gravedad | BW4: Edificio 2.- Centro De Gravedad | CG4: Losa en Y Edificio 1 Entre ejes A y B | DC4: Analisando el perfil de la franja de Vigueta y Bobedilla | DM4: Momento Positivo | DY4: Losa Entre Ejes B y C | FA4: Momento Positivo | FM4: Losa Critica Sobre "X" Edificio 2 | GH4: Momento Positivo | GT4: Marco 3 Edificio 1 | HD4: Momento Positivo Máximo | HM4: Análisis de Columnas | HV4: Marco 2 y 3 en Edificio 2 | IF4: Momento Positivo Máximo | IO4: Análisis de Columnas | KN4: Torsión y Sismo Edificio 2 | KU4: =KN6 -> Marco | KV4: =KO6 -> nivel 1 | KW4: Vnat | KX4: V tor | KY4: % inc. | KZ4: V tot | LA4: V r | LD4: =KU4 -> Marco | LE4: nivel 1 | LF4: Vnat | LG4: V tor | LH4: % inc. | LI4: V tot | LJ4: V r | LM4: Marco en B Edificio 1 T1 | LW4: Momento Negativo Máximo | MF4: Análisis de Columnas Bajo Condiciones de Cargas Gravitacionales | MW4: Marco en 3 Edificio 1 T1 | NG4: Momento Negativo Máximo | NP4: Análisis de Columnas Bajo Condiciones de Cargas Gravitacionales | OH4: Análisis de Columnas Bajo Efectos Sísmicos | PH4: Marco en 1 y 4 Edificio 2 T3 | PR4: Momento Negativo Máximo | QA4: Análisis de Columnas Bajo Condiciones de Cargas Gravitacionales | QS4: Análisis de Columnas Bajo Efectos Sísmicos | RT4: Inversión de Cortantes | SC4: Acero en lecho superior por inversión de cortante durante sismo | SL4: Losa de Cimentación | TG4: Momento Positivo | TR4: Zapata Corrida | UB4: mom | UC4: -0.38791114 | US4: Muros de Contención | VK4: Análisis Dinámico SAP2000 | WD4: Recomendaciones: | WM4: Especificaciones: Perfiles | XE4: Especificaciones: Materiales | XN4: Detalles: | ZH4: Losas | ZR4: Levantamiento
B5: Proyecto Locales Comerciales en Tres niveles con Sótano | T5: La hidrología histórica nos habla de dos arroyos que confluyen en el Rio Tijuana pasando justo por debajo de lo que ahora es el predio. Esto nos ayuda a entender la presencia de un suelo a base de arenas con boleo que se puede apreciar en la excavación ya realizada y que documenta ampliamente el estudio de mecánica de suelos. Hablamos de un suelo de deposito o aluvión. Esto seria el origen de que la zona se encuentre marcada como de una baja aptitud territorial según el IMPLAN y nos conduce a tener sumo cuidado al recomendar una cimentación. | AL5: Se nos entrego Estudio de Mecánica de suelos elaborado por el Ing. David Becerra (anexo) | AU5: Área de construcción | AZ5: =AQ35 -> 73.6 | BM5: Calculo de Áreas y Centro de Gravedad | BW5: Calculo de Áreas y Centro de Gravedad | DC5: Vigueta y Bovedilla: Armadura de 18 cm con 3 varillas 5/16 en el patin (inferior) y caseton de 20 para tener 20 cm de peralte de vigueta y 5 cm en compresion. Malla electrosoldada 6-6/6-6 y bastones abase de 1 varilla 3/16 @ 15 cm. Peso propio de 215 kg/m2 separacion de 67 cm entre vigueta, ancho de 12 cm. Se armara con su sentido largo sobre "Y" en ambos edificios | DM5: Momento Positivo Máximo Acero DA6000 | FA5: =DC5 -> Vigueta y Bovedilla: Armadura de 18 cm con 3 varillas 5/16 en el patin (inferior) y caseton de 20 para tener 20 cm de peralte de vigueta y 5 cm en compresion. Malla electrosoldada 6-6/6-6 y bastones abase de 1 varilla 3/16 @ 15 cm. Peso propio de 215 kg/m2 separacion de 67 cm entre vigueta, ancho de 12 cm. Se armara con su sentido largo sobre "Y" en ambos edificios | GT5: M= | GU5: -4.6236429 | GW5: w= | GX5: 3.3581798 | HA5: M= | HB5: 9.2165761 | HD5: por nacional plástico | HM5: 48.194542 | HV5: M= | HW5: -3.7619549 | HY5: w= | HZ5: 2.38 | IC5: M= | ID5: 2.7402912 | IF5: por nacional plástico | IO5: 41.858841 | IX5: pu | IY5: =HM5 -> 48.194542 | JA5: f'c | JB5: 200 | JC5: fy | JD5: =HN29*HN28 -> 3360 | JG5: pu | JH5: =IY5 -> 48.194542 | JJ5: f'c | JK5: 200 | JL5: fy | JM5: =JD5 -> 3360 | KN5: Rigidez en Marcos: | KU5: =KN7 -> A | KV5: =KO7 -> 28963094 | KW5: 3.6657104 | KX5: 0.84859383 | KY5: =IF(KW5=0,"",KX5/KW5) -> 0.23149506 | KZ5: =KX5+KW5 -> 4.5143042 | LA5: 60 | LB5: =IF(KZ5=0,"",IF(LA5>KZ5,"pasa","no pasa")) -> pasa | LD5: =KR7 -> 1 | LE5: =KS7 -> 13111060 | LF5: 4.8246988 | LG5: 0.37983614 | LH5: =IF(LF5=0,"",LG5/LF5) -> 0.078727431 | LI5: =LG5+LF5 -> 5.2045349 | LJ5: 40 | LK5: =IF(LI5=0,"",IF(LJ5>LI5,"pasa","no pasa")) -> pasa | LM5: M= | LN5: -1.6333878 | LP5: w= | LQ5: 3.3581798 | LT5: M= | LU5: 4.1383771 | LW5: por nacional plástico | MF5: 25.258368 | MO5: pu | MP5: =MF5 -> 25.258368 | MR5: f'c | MS5: 200 | MT5: fy | MU5: =MG28 -> 4200 | MW5: M= | MX5: -2.3531218 | MZ5: w= | NA5: 3.3581798 | ND5: M= | NE5: 4.1740757 | NG5: por nacional plástico | NP5: 12.4752 | NY5: pu | NZ5: =NP5 -> 12.4752 | OB5: f'c | OC5: 200 | OD5: fy | OE5: =NQ28 -> 4200 | OH5: =MF5 -> 25.258368 | OQ5: pu | OR5: =OH5 -> 25.258368 | OT5: f'c | OU5: 200 | OV5: fy | OW5: =OI28 -> 4200 | OZ5: d=Vu / (0.85 x (F'c^0.5) x b | PH5: M= | PI5: 8.2451098 | PK5: w= | PL5: =JG36/JN30 -> 2.534087 | PO5: M= | PP5: 9.0540729 | PR5: por nacional plástico | QA5: 27.436181 | QJ5: pu | QK5: =QA5 -> 27.436181 | QM5: f'c | QN5: 200 | QO5: fy | QP5: =QB25 -> 4200 | QS5: 32.442761 | RB5: pu | RC5: =QS5 -> 32.442761 | RE5: f'c | RF5: 200 | RG5: fy | RH5: =QT28 -> 4200 | RK5: d=Vu / (0.85 x (F'c^0.5) x b | SD5: 100 | SG5: Pu | SH5: -11.35455 | SJ5: =SH5*1000 -> -11354.55 | TH5: La Losa de Cimentación se Armara con Varilla No. 5 @ 15 en ambas direcciones Lecho Superior. El acero inferior de las zapatas invertidas será de varilla No. 5 @ 10 | UB5: pu | UC5: 55.206786 | UE5: f'c | UF5: 200 | UG5: fy | UH5: =UC4 -> -0.38791114 | UK5: d=Vu / (0.85 x (F'c^0.5) x b | VU5: El Analisis por SAP es una verificacion por elemento finito. Constituye el Estado del Arte en Analisis Estructural y es por lo tanto mucho mas severo que cualquier metodo tradicional. Al correr dicho analisis para el edificio 1 este nos arroja las siguientes recomendaciones. Armar las viguetas y bovedillas entre los ejes 3 y 4 sobre "x" y agregar una trabe adicional sobre entre A y B a 2.345m del eje A en el punto donde inicia la curva de la losa para reducir claro en voladizo de la vigueta y bovedilla. Para cargas gravitacionale la misma no presenta problema, sin embargo, una vez agregando el efecto sismico el voladizo de 3.2 mts generaba un movimiento excesivo. Esta nueva Trabe nos forza a | WD5: Edificio 1 | WF5: Edificio 2 | WM5: Muros Estructurales Sotano y Nivel 1 (ME1) | WV5: Losa Fronteriada tablero en Voladizo | XE5: Zapatas y Cimentación: | XN5: ME1 | XR5: ME2 | XW5: Estribos en Columnas Trabes y Contratrabes espaciados a 10 cm en los 1/4's extremos | ZH5: Las losas se armaran para un momento máximo positivo y otro negativo de moda ya que este agrupa el 80% de las mismas, armándose solo dos para momentos mayores como se ve a continuación. | AAB5: Losas
B6: Dirección: | K6: Se verifico la aptitud territorial de la zona de acuerdo a la información del IMPLAN. Encontrando lo siguiente: | AU6: Área Planta Alta | AZ6: =AZ5 -> 73.6 | CG6: W= | CH6: =AZ32*0.67/1000 -> 0.46766 | DM6: por nacional plástico | DY6: W= | DZ6: =CH6 -> 0.46766 | FM6: W= | FN6: =CH6 -> 0.46766 | HD6: f'c = | HE6: 200 | HF6: f"c = | HG6: =HE6*0.8*0.85 -> 136 | HJ6: Mu | HK6: =GX26 -> 5.3384659 | IF6: f'c = | IG6: 200 | IH6: f"c = | II6: =IG6*0.8*0.85 -> 136 | IL6: Mu | IM6: =HZ26 -> 2.0092081 | IZ6: ex = | JA6: =HQ9 -> 0.49619081 | JB6: / | JC6: =HM5 -> 48.194542 | JD6: = | JE6: =JA6/(JC6) -> 0.010295581 | JI6: ex = | JJ6: =JB31 -> 2.0400841 | JK6: / | JL6: =IX27 -> 38.812753 | JM6: = | JN6: =JJ6/(JL6) -> 0.05256221 | KN6: Marco | KO6: nivel 1 | KP6: nivel 2 | KR6: Marco | KS6: nivel 1 | KT6: nivel 2 | KU6: =KN8 -> B | KV6: =KO8 -> 21064591 | KW6: 2.6660374 | KX6: 0.035543858 | KY6: =IF(KW6=0,"",KX6/KW6) -> 0.013332093 | KZ6: =KX6+KW6 -> 2.7015813 | LA6: 34.9 | LB6: =IF(KZ6=0,"",IF(LA6>KZ6,"pasa","no pasa")) -> pasa | LD6: =KR8 -> 2 | LE6: =KS8 -> 472925.28 | LF6: 0.17403033 | LG6: 0.003756877 | LH6: =IF(LF6=0,"",LG6/LF6) -> 0.021587485 | LI6: =LG6+LF6 -> 0.1777872 | LJ6: 13.5 | LK6: =IF(LI6=0,"",IF(LJ6>LI6,"pasa","no pasa")) -> pasa | LW6: f'c = | LX6: 200 | LY6: f"c = | LZ6: =LX6*0.8*0.85 -> 136 | MC6: Mu | MD6: =LQ26 -> 2.5669868 | MQ6: ex = | MR6: =MP5 -> 25.258368 | MS6: / | MT6: =MJ9 -> -2.0802045 | MU6: = | MV6: =MR6/(MT6) -> -12.142252 | NG6: f'c = | NH6: 200 | NI6: f"c = | NJ6: =NH6*0.8*0.85 -> 136 | NM6: Mu | NN6: =NA26 -> 2.1548942 | OA6: ex = | OB6: =NZ5 -> 12.4752 | OC6: / | OD6: =NT9 -> -4.6881876 | OE6: = | OF6: =OB6/(OD6) -> -2.6609857 | OS6: ex = | OT6: =OR5 -> 25.258368 | OU6: / | OV6: =OG10 -> -2.0802045 | OW6: = | OX6: =OT6/(OV6) -> -12.142252 | PR6: f'c = | PS6: 250 | PT6: f"c = | PU6: =PS6*0.8*0.85 -> 170 | PX6: Mu | PY6: =PP29 -> 9.0540729 | QL6: ex = | QM6: =QK5 -> 27.436181 | QN6: / | QO6: =QE9 -> -0.075990196 | QP6: = | QQ6: =QM6/(QO6) -> -361.04896 | RD6: ex = | RE6: =RC5 -> 32.442761 | RF6: / | RG6: =QW9 -> 26.938858 | RH6: = | RI6: =RE6/(RG6) -> 1.2043109 | RT6: Ante efectos Sísmicos se noto una inversión total del cortante vertical en la columnas-muros de extremo de suerte que estas pasaran de la compresión normal a tensión directa. Este Fenómeno se ha observado en diversas estructuras sujetas a sismo y nos lleva a tener mucho mas cuidado con el confinamiento apropiado del concreto así como del acero de refuerzo principal que forma parte de las columnas, pilas y muros de carga particularmente de los pisos inferiores para evitar fallas como las registradas en Chile. La falta de confinamiento puede llevar al colapso. | SC6: =SD5-SE8 -> 80 | SG6: CC | SH6: =SH5/(1*2.86) -> -3.9701222 | SJ6: =SH6*1000/10000 -> -0.39701222 | SL6: W= | SM6: =JF41/(JN30*JK41) -> 4.4684976 | TT6: 100 | TW6: Pu | TX6: =3 -> 3 | TZ6: =TX6*1000 -> 3000 | UD6: ex = | UE6: =UH5 -> -0.38791114 | UF6: / | UG6: =UC5 -> 55.206786 | UH6: = | UI6: =UE6/(UG6) -> -0.0070265118 | UT6: Analizamos una Franja de Muro de 1 metro y tenemos. | WM6: Armado con todas las celdas coladas Varilla vertical #4 , varilla longitudinal en cada hilada amarrada a las varillas verticales. Block 1 | WV6: Colocar frontera de cimbra para dar forma, Armar esta zona con varillas #4 @ 20 cm en curva amarradas a la malla solo para garantizar que la losa funcionara en conjunto y 2#4 a 10 cm de extremo. | XE6: Debajo de todos los muros y sobre los ejes de marco se colocaran zapatas corridas invertidas aumentando el espesor de la losa de cimentación a 30 cm con un ancho de 1 metro y colocando el armado que se indica en el apartado correspondiente a la losa de cimentación. El Concreto se considera estructural resistentes a sulfatos on impermeabilizante integrado. Puede emplearse xypex
B7: Calle 7ma entre Madero y Quintanar roo | AU7: Área Planta baja | AZ7: =AZ6 -> 73.6 | CK7: momento puro en el claro | CM7: Atrib | CN7: 3 | CQ7: momento puro en el claro | DM7: f'c = | DN7: 200 | DO7: f"c = | DP7: =DN7*0.8*0.85 -> 136 | DS7: Mu | DT7: =CH42 -> 0.61026434 | EC7: momento puro en el claro | EE7: Atrib | EF7: 3 | EI7: momento puro en el claro | EO7: momento puro en el claro | FQ7: momento puro en el claro | FS7: Atrib | FT7: 3 | FW7: momento puro en el claro | HD7: fy = | HE7: 4200 | HF7: Ro max = | HG7: =0.75*(HG6/HE7)*(4800/(6000+HE7)) -> 0.011428571 | HK7: =HG71 -> 0.16852421 | IF7: fy = | IG7: 4200 | IH7: Ro max = | II7: =0.75*(II6/IG7)*(4800/(6000+IG7)) -> 0.011428571 | IM7: =II71 -> 0.10086942 | IZ7: ey = | JA7: =JA6 -> 0.49619081 | JB7: / | JC7: =JC6 -> 48.194542 | JD7: = | JE7: =JE6 -> 0.010295581 | JI7: ey = | JJ7: =JJ6 -> 2.0400841 | JK7: / | JL7: =JL6 -> 38.812753 | JM7: = | JN7: =JN6 -> 0.05256221 | KN7: A | KO7: 28963094 | KP7: 28963094 | KR7: 1 | KS7: 13111060 | KT7: 13111060 | KU7: =KN9 -> C | KV7: =KO9 -> 28963094 | KW7: 3.6657104 | KX7: 0.88413769 | KY7: =IF(KW7=0,"",KX7/KW7) -> 0.24119136 | KZ7: =KX7+KW7 -> 4.5498481 | LA7: 60 | LB7: =IF(KZ7=0,"",IF(LA7>KZ7,"pasa","no pasa")) -> pasa | LD7: =KR9 -> 3 | LE7: =KS9 -> 472925.28 | LF7: 0.17403033 | LG7: 0.0040477219 | LH7: =IF(LF7=0,"",LG7/LF7) -> 0.023258716 | LI7: =LG7+LF7 -> 0.17807805 | LJ7: 13.5 | LK7: =IF(LI7=0,"",IF(LJ7>LI7,"pasa","no pasa")) -> pasa | LW7: fy = | LX7: 4200 | LY7: Ro max = | LZ7: =0.75*(LZ6/LX7)*(4800/(6000+LX7)) -> 0.011428571 | MD7: =LX70 -> 0.035139388 | MQ7: ey = | MR7: =MR6 -> 25.258368 | MS7: / | MT7: =MT6 -> -2.0802045 | MU7: = | MV7: =MV6 -> -12.142252 | NG7: fy = | NH7: 4200 | NI7: Ro max = | NJ7: =0.75*(NJ6/NH7)*(4800/(6000+NH7)) -> 0.011428571 | NN7: =NH70 -> 0.029412541 | OA7: ey = | OB7: =OB6 -> 12.4752 | OC7: / | OD7: =OD6 -> -4.6881876 | OE7: = | OF7: =OF6 -> -2.6609857 | OS7: ey = | OT7: =OT6 -> 25.258368 | OU7: / | OV7: =OV6 -> -2.0802045 | OW7: = | OX7: =OX6 -> -12.142252 | PA7: =OR26 -> 100 | PE7: =PA7 -> 100 | PR7: fy = | PS7: 4200 | PT7: Ro max = | PU7: =0.75*(PU6/PS7)*(4800/(6000+PS7)) -> 0.014285714 | PY7: =PS70 -> 0.10268246 | QL7: ey = | QM7: =QM6 -> 27.436181 | QN7: / | QO7: =QO6 -> -0.075990196 | QP7: = | QQ7: =QQ6 -> -361.04896 | RD7: ey = | RE7: =RE6 -> 32.442761 | RF7: / | RG7: =RG6 -> 26.938858 | RH7: = | RI7: =RI6 -> 1.2043109 | RL7: =RC26 -> 100 | RP7: =RL7 -> 100 | SG7: área min | SH7: =SH5/SH6 -> 2.86 | SI7: m^2 | SP7: momento puro en el claro | SR7: Atrib | SS7: 3 | SV7: momento puro en el claro | TS7: =TT6-TU9 -> 80 | TW7: CC | TX7: =TX6/(1*2.86) -> 1.048951 | TZ7: =TX7*1000/10000 -> 0.1048951 | UD7: ey = | UE7: =UH5 -> -0.38791114 | UF7: / | UG7: =UG6 -> 55.206786 | UH7: = | UI7: =UI6 -> -0.0070265118 | UL7: =UC26 -> 100 | UP7: =UL7 -> 100 | UT7: sobre carga | UU7: =SM6 -> 4.4684976 | UV7: ton/m2 | VG7: =VC16*VD17/VE14 -> 3.6774192
AL8: En este estudio se aprecian los resultados de 4 sondeos, hubiéramos preferido una distribución mas amplia de los mismos en el área de estudio sin embargo suponemos que la falta de protección en la excavación disuadió a CONSAT de acercarse a las paredes en sus sondeos. | AU8: Capacidad de carca: | AZ8: =AQ39 -> 1304.6778 | CL8: momentos generados en los nudos | CM8: A | CN8: B | CR8: momentos generados en los nudos | CS8: A | CT8: B | DM8: fy = | DN8: 6000 | DO8: Ro max = | DP8: =0.75*(DP7/DN8)*(4800/(6000+DN8)) -> 0.0068 | DT8: =DN69 -> 0.045231208 | ED8: momentos generados en los nudos | EE8: A | EF8: B | EJ8: momentos generados en los nudos | EK8: A | EL8: B | EP8: momentos generados en los nudos | EQ8: A | ER8: B | FA8: Momento Positivo Máximo | FR8: momentos generados en los nudos | FS8: A | FT8: B | FX8: momentos generados en los nudos | FY8: A | FZ8: B | GH8: Momento Positivo Máximo | GV8: l= | GW8: 5.38 | HD8: Fr = | HE8: 0.8 | HF8: Ro min= | HG8: =0.8*(SQRT(HG6))/HE7 -> 0.002221315 | HK8: =HG72 -> 0.16852421 | HX8: l= | HY8: 4.2 | IF8: Fr = | IG8: 0.8 | IH8: Ro min= | II8: =0.8*(SQRT(II6))/IG7 -> 0.002221315 | IM8: =II72 -> 0.10086942 | IZ8: f"c | JA8: =0.8*(JB5^0.5) -> 11.313708 | JI8: f"c | JJ8: =JA8 -> 11.313708 | KN8: B | KO8: 21064591 | KP8: 21064591 | KR8: 2 | KS8: 472925.28 | KT8: 472925.28 | KU8: =KN10 -> 0 | KV8: =KO10 -> 0 | KW8: 0 | KX8: 0 | KY8: =IF(KW8=0,"",KX8/KW8) | KZ8: =KX8+KW8 -> 0 | LA8: 0 | LB8: =IF(KZ8=0,"",IF(LA8>KZ8,"pasa","no pasa")) | LD8: =KR10 -> 4 | LE8: =KS10 -> 13111060 | LF8: 4.8246988 | LG8: 0.3795453 | LH8: =IF(LF8=0,"",LG8/LF8) -> 0.078667149 | LI8: =LG8+LF8 -> 5.2042441 | LJ8: 40 | LK8: =IF(LI8=0,"",IF(LJ8>LI8,"pasa","no pasa")) -> pasa | LO8: l= | LP8: 3.58 | LW8: Fr = | LX8: 0.8 | LY8: Ro min= | LZ8: =0.8*(SQRT(LZ6))/LX7 -> 0.002221315 | MD8: =LX71 -> 0.035139388 | MQ8: f"c | MR8: =0.85*((MS5)^0.5) -> 12.020815 | MY8: l= | MZ8: 3.58 | NG8: Fr = | NH8: 0.8 | NI8: Ro min= | NJ8: =0.8*(SQRT(NJ6))/NH7 -> 0.002221315 | NN8: =NH71 -> 0.029412541 | OA8: f"c | OB8: =0.85*((OC5)^0.5) -> 12.020815 | OS8: f"c | OT8: =0.85*((OU5)^0.5) -> 12.020815 | OZ8: =OQ27 -> 80 | PJ8: l= | PK8: 1.6 | PR8: Fr = | PS8: 0.8 | PT8: Ro min= | PU8: =0.8*(SQRT(PU6))/PS7 -> 0.0024835057 | PY8: =PS71 -> 0.10268246 | QL8: f"c | QM8: =0.85*((QN5)^0.5) -> 12.020815 | RD8: f"c | RE8: =0.85*((RF5)^0.5) -> 12.020815 | RK8: =RB27 -> 80 | SE8: 20 | SL8: m cuad | SM8: 0.7 | SQ8: momentos generados en los nudos | SR8: A | SS8: B | SW8: momentos generados en los nudos | SX8: A | SY8: B | TG8: Momento Positivo Máximo | TW8: área min | TX8: =TX6/TX7 -> 2.86 | TY8: m^2 | UD8: f"c | UE8: =0.85*((UF5)^0.5) -> 12.020815 | UK8: 40 | VG8: =VH15+VG7 -> 0 | VH8: =VI88 -> 2.7068481 | WM8: Muros Estructurales Niveles 2 (ME2) | ZH8: Momento Positivo de Moda
AU9: Peso propio Vigueta y Bovedilla | AZ9: 215 | CK9: Carga uniformemente Distribuida | CL9: =CH6 -> 0.46766 | CM9: =-1*(IF(CM24=0,0,IF(CL9=0,0,CL9*CM24*CM24/12))) -> -0.26142584 | CN9: =CM9*-1 -> 0.26142584 | CQ9: Carga uniformemente Distribuida | CR9: =CL9 -> 0.46766 | CS9: =-1*(IF(CS24=0,0,IF(CR9=0,0,CR9*CS24*CS24/12))) -> -0.42440145 | CT9: =CS9*-1 -> 0.42440145 | DM9: Fr = | DN9: 0.8 | DO9: Ro min= | DP9: =0.8*(SQRT(DP7))/DN8 -> 0.0015549205 | DT9: =DN70 -> 0.045231208 | EC9: Carga uniformemente Distribuida | ED9: =DZ6 -> 0.46766 | EE9: =-1*(IF(EE24=0,0,IF(ED9=0,0,ED9*EE24*EE24/12))) -> -0.39906987 | EF9: =EE9*-1 -> 0.39906987 | EI9: Carga uniformemente Distribuida | EJ9: =ED9 -> 0.46766 | EK9: =-1*(IF(EK24=0,0,IF(EJ9=0,0,EJ9*EK24*EK24/12))) -> -0.26142584 | EL9: =EK9*-1 -> 0.26142584 | EO9: Carga uniformemente Distribuida | EP9: =EJ9 -> 0.46766 | EQ9: =-1*(IF(EQ24=0,0,IF(EP9=0,0,EP9*EQ24*EQ24/12))) -> -0.42440145 | ER9: =EQ9*-1 -> 0.42440145 | FA9: por nacional plástico | FQ9: Carga uniformemente Distribuida | FR9: =FN6 -> 0.46766 | FS9: =-1*(IF(FS24=0,0,IF(FR9=0,0,FR9*FS24*FS24/12))) -> -0.5050728 | FT9: =FS9*-1 -> 0.5050728 | FW9: Carga uniformemente Distribuida | FX9: =FR9 -> 0.46766 | FY9: =-1*(IF(FY24=0,0,IF(FX9=0,0,FX9*FY24*FY24/12))) -> -0.6874602 | FZ9: =FY9*-1 -> 0.6874602 | GH9: por nacional plástico | GT9: RN= | GU9: =-GX5*GW8/2 -> -9.0335036 | HA9: RN= | HB9: =GU9 -> -9.0335036 | HD9: peso conc | HE9: 2400 | HF9: q ro max= | HG9: =HG7*HE7/HG6 -> 0.35294118 | HH9: =HG9*(1-(0.5*HG9)) -> 0.29065744 | HJ9: q real | HK9: =HG73 -> 0.16852421 | HO9: 0 | HQ9: =HR23-(HO23*HL15) -> 0.49619081 | HR9: -2.7402912 | HV9: RN= | HW9: =-HZ5*HY8/2 -> -4.998 | IC9: RN= | ID9: =HW9 -> -4.998 | IF9: peso conc | IG9: 2400 | IH9: q ro max= | II9: =II7*IG7/II6 -> 0.35294118 | IJ9: =II9*(1-(0.5*II9)) -> 0.29065744 | IL9: q real | IM9: =II73 -> 0.10086942 | IQ9: 0 | IS9: =IT23-(IQ23*IN15) -> -0.20309443 | IT9: =IN10 -> -1.7718385 | IZ9: d/h | JA9: =HN32/(HN33) -> 0.83333333 | JI9: d/h | JJ9: =JA27/(JB27) -> 0.83333333 | KN9: C | KO9: 28963094 | KP9: 28963094 | KR9: 3 | KS9: 472925.28 | KT9: 472925.28 | KU9: =KN11 -> 0 | KV9: =KO11 -> 0 | KW9: 0 | KX9: 0 | KY9: =IF(KW9=0,"",KX9/KW9) | KZ9: =KX9+KW9 -> 0 | LA9: 0 | LB9: =IF(KZ9=0,"",IF(LA9>KZ9,"pasa","no pasa")) | LD9: =KR11 -> 0 | LE9: =KS11 -> 0 | LF9: 0 | LG9: 0 | LH9: =IF(LF9=0,"",LG9/LF9) | LI9: =LG9+LF9 -> 0 | LJ9: 0 | LK9: =IF(LI9=0,"",IF(LJ9>LI9,"pasa","no pasa")) | LM9: RN= | LN9: =-LQ5*LP8/2 -> -6.0111418 | LT9: RN= | LU9: =LN9 -> -6.0111418 | LW9: peso conc | LX9: 2400 | LY9: q ro max= | LZ9: =LZ7*LX7/LZ6 -> 0.35294118 | MA9: =LZ9*(1-(0.5*LZ9)) -> 0.29065744 | MC9: q real | MD9: =LX72 -> 0.035139388 | MH9: 0 | MJ9: =ME10 -> -2.0802045 | MK9: 0 | MQ9: k= Pu / (Fr b h f"c ) | MS9: =MP5*1000/(0.9*(0.85*((200)^0.5))*MG32*MG33) -> 2.5940978 | MW9: RN= | MX9: =-NA5*MZ8/2 -> -6.0111418 | ND9: RN= | NE9: =MX9 -> -6.0111418 | NG9: peso conc | NH9: 2400 | NI9: q ro max= | NJ9: =NJ7*NH7/NJ6 -> 0.35294118 | NK9: =NJ9*(1-(0.5*NJ9)) -> 0.29065744 | NM9: q real | NN9: =NH72 -> 0.029412541 | NR9: 0 | NT9: =NO10 -> -4.6881876 | NU9: 0 | OA9: k= Pu / (Fr b h f"c ) | OC9: =NZ5*1000/(0.9*(0.85*((200)^0.5))*NQ32*NQ33) -> 1.2812344 | OJ9: 0 | OL9: =OM23-(OJ23*OG15) -> 0 | OM9: =OG10 -> -2.0802045 | OS9: k= Pu / (Fr b h f"c ) | OU9: =OR5*1000/(0.9*(0.85*((200)^0.5))*OI32*OI33) -> 1.2287832 | OY9: 1 | PC9: 2 | PH9: RN= | PI9: =-PL5*PK8/2 -> -2.0272696 | PO9: RN= | PP9: =PI9 -> -2.0272696 | PR9: peso conc | PS9: 2400 | PT9: q ro max= | PU9: =PU7*PS7/PU6 -> 0.35294118 | PV9: =PU9*(1-(0.5*PU9)) -> 0.29065744 | PX9: q real | PY9: =PS72 -> 0.10268246 | QC9: 0 | QE9: =QF20-(QC20*PZ15) -> -0.075990196 | QF9: 0 | QL9: k= Pu / (Fr b h f"c ) | QN9: =QK5*1000/(0.9*(0.85*((200)^0.5))*QB29*QB30) -> 1.3347306 | QU9: 0 | QW9: =QX23-(QU23*QR15) -> 26.938858 | QX9: =QR10 -> -8.5831379 | RD9: k= Pu / (Fr b h f"c ) | RF9: =RC5*1000/(0.9*(0.85*((200)^0.5))*QT32*QT33) -> 1.5782935 | RJ9: 1 | RN9: 2 | SG9: Mu= | SH9: =ABS(SJ6*SC6*SC6*SB11/2) -> 374695.93 | SP9: Carga uniformemente Distribuida | SQ9: =SM6 -> 4.4684976 | SR9: =-1*(IF(SR24=0,0,IF(SQ9=0,0,SQ9*SR24*SR24/12))) -> -4.8259774 | SS9: =SR9*-1 -> 4.8259774 | SV9: Carga uniformemente Distribuida | SW9: =SQ9 -> 4.4684976 | SX9: =-1*(IF(SX24=0,0,IF(SW9=0,0,SW9*SX24*SX24/12))) -> -6.5686915 | SY9: =SX9*-1 -> 6.5686915 | TG9: por nacional plástico | TU9: 20 | UD9: k= Pu / (Fr b h f"c ) | UF9: =UC5*1000/(0.9*(0.85*((200)^0.5))*UB14*UB15) -> 5.6698755 | UJ9: 1 | UN9: 2 | UX9: Se supone que los muros de contención del sótano serán rigidizados por las losas de cimentación y de entrepiso del nivel 1 por lo tanto podemos suponer que actúa como una trabe doblemente empotrada. | WM9: Armado con celdas coladas @2er celda Varilla vertical #4 , varilla longitudinal @2 hiladas amarrada a las varillas verticales. Block 1 | WV9: 20 x 20 cm, Armado Vertical con cuatro varilla #4 y Estribos de Varilla #3 @ 20 cm | ZH9: por nacional plástico
AU10: Techumbre | CK10: Carga uniforme por peso prop | CM10: =-1*(IF(CM24=0,0,IF(CL10=0,0,CL10*CM24*CM24/12))) -> 0 | CN10: =CM10*-1 -> 0 | CQ10: Carga uniforme por peso prop | CS10: =-1*(IF(CS24=0,0,IF(CR10=0,0,CR10*CS24*CS24/12))) -> 0 | CT10: =CS10*-1 -> 0 | DM10: peso conc | DN10: 2400 | DO10: q ro max= | DP10: =DP8*DN8/DP7 -> 0.3 | DQ10: =DP10*(1-(0.5*DP10)) -> 0.255 | DS10: q real | DT10: =DN71 -> 0.045231208 | EC10: Carga uniforme por peso prop | EE10: =-1*(IF(EE24=0,0,IF(ED10=0,0,ED10*EE24*EE24/12))) -> 0 | EF10: =EE10*-1 -> 0 | EI10: Carga uniforme por peso prop | EK10: =-1*(IF(EK24=0,0,IF(EJ10=0,0,EJ10*EK24*EK24/12))) -> 0 | EL10: =EK10*-1 -> 0 | EO10: Carga uniforme por peso prop | EP10: =EJ10 -> 0 | EQ10: =-1*(IF(EQ24=0,0,IF(EP10=0,0,EP10*EQ24*EQ24/12))) -> 0 | ER10: =EQ10*-1 -> 0 | FA10: f'c = | FB10: =DN7 -> 200 | FC10: f"c = | FD10: =FB10*0.8*0.85 -> 136 | FG10: Mu | FH10: =EG42 -> 0.42469736 | FQ10: Carga uniforme por peso prop | FS10: =-1*(IF(FS24=0,0,IF(FR10=0,0,FR10*FS24*FS24/12))) -> 0 | FT10: =FS10*-1 -> 0 | FW10: Carga uniforme por peso prop | FY10: =-1*(IF(FY24=0,0,IF(FX10=0,0,FX10*FY24*FY24/12))) -> 0 | FZ10: =FY10*-1 -> 0 | GH10: f'c = | GI10: 200 | GJ10: f"c = | GK10: =GI10*0.8*0.85 -> 136 | GN10: Mu | GO10: =FN42 -> 0.63605112 | GT10: RDM= | GU10: =(GU5+HB5)/GW8 -> 0.85370505 | HA10: =GT10 -> RDM= | HB10: =GU10*-1 -> -0.85370505 | HF10: q ro min= | HG10: =HG8*HE7/HG6 -> 0.068599434 | HH10: =HG10*(1-(0.5*HG10)) -> 0.066246493 | HJ10: Ro real | HK10: =HK9*HG6/HE7 -> 0.0054569744 | HL10: -1.7718385 | HV10: RDM= | HW10: =(HW5+ID5)/HY8 -> -0.24325327 | IC10: =HV10 -> RDM= | ID10: =HW10*-1 -> 0.24325327 | IH10: q ro min= | II10: =II8*IG7/II6 -> 0.068599434 | IJ10: =II10*(1-(0.5*II10)) -> 0.066246493 | IL10: Ro real | IM10: =IM9*II6/IG7 -> 0.0032662478 | IN10: -1.7718385 | IZ10: k= Pu / (Fr b h f"c ) | JB10: =IY5*1000/(0.9*(0.85*((200)^0.5))*HN32*HN33) -> 5.9396405 | JI10: k= Pu / (Fr b h f"c ) | JK10: =JH5*1000/(0.9*(0.85*((200)^0.5))*JA27*JB27) -> 5.9396405 | KN10: 0 | KO10: 0 | KP10: 0 | KR10: 4 | KS10: 13111060 | KT10: 13111060 | KU10: =KN12 -> 0 | KV10: =KO12 -> 0 | KW10: 0 | KX10: 0 | KY10: =IF(KW10=0,"",KX10/KW10) | KZ10: =KX10+KW10 -> 0 | LA10: 0 | LB10: =IF(KZ10=0,"",IF(LA10>KZ10,"pasa","no pasa")) | LD10: =KR12 -> 0 | LE10: =KS12 -> 0 | LF10: 0 | LG10: 0 | LH10: =IF(LF10=0,"",LG10/LF10) | LI10: =LG10+LF10 -> 0 | LJ10: 0 | LK10: =IF(LI10=0,"",IF(LJ10>LI10,"pasa","no pasa")) | LM10: RDM= | LN10: =(LN5+LU5)/LP8 -> 0.69971769 | LT10: =LM10 -> RDM= | LU10: =LN10*-1 -> -0.69971769 | LW10: rec | LX10: 5 | LY10: q ro min= | LZ10: =LZ8*LX7/LZ6 -> 0.068599434 | MA10: =LZ10*(1-(0.5*LZ10)) -> 0.066246493 | MC10: Ro real | MD10: =MD9*LZ6/LX7 -> 0.0011378468 | ME10: -2.0802045 | MW10: RDM= | MX10: =(MX5+NE5)/MZ8 -> 0.50864633 | ND10: =MW10 -> RDM= | NE10: =MX10*-1 -> -0.50864633 | NG10: rec | NH10: 5 | NI10: q ro min= | NJ10: =NJ8*NH7/NJ6 -> 0.068599434 | NK10: =NJ10*(1-(0.5*NJ10)) -> 0.066246493 | NM10: Ro real | NN10: =NN9*NJ6/NH7 -> 0.00095240608 | NO10: -4.6881876 | OG10: =ME10 -> -2.0802045 | PB10: =OS29 -> 20 | PF10: =PB10 -> 20 | PH10: RDM= | PI10: =(PI5+PP5)/PK8 -> 10.811989 | PO10: =PH10 -> RDM= | PP10: =PI10*-1 -> -10.811989 | PR10: rec | PS10: 5 | PT10: q ro min= | PU10: =PU8*PS7/PU6 -> 0.061357199 | PV10: =PU10*(1-(0.5*PU10)) -> 0.059474846 | PX10: Ro real | PY10: =PY9*PU6/PS7 -> 0.0041561946 | PZ10: 0.050660131 | QR10: -8.5831379 | RM10: =RD29 -> 20 | RQ10: =RM10 -> 20 | SG10: . \/ selecciona varilla | SL10: M'max Tcm | SM10: =SN42*100 -> 845.8866 | SP10: Carga uniforme por peso prop | SR10: =-1*(IF(SR24=0,0,IF(SQ10=0,0,SQ10*SR24*SR24/12))) -> 0 | SS10: =SR10*-1 -> 0 | SV10: Carga uniforme por peso prop | SX10: =-1*(IF(SX24=0,0,IF(SW10=0,0,SW10*SX24*SX24/12))) -> 0 | SY10: =SX10*-1 -> 0 | TG10: f'c = | TH10: 250 | TI10: f"c = | TJ10: =TH10*0.8*0.85 -> 170 | TM10: Mu | TN10: =SM42 -> 6.0774771 | TW10: Mu= | TX10: =ABS(TZ7*TS7*TS7*TR12/2) -> 33566.434 | UM10: =UD29 -> 20 | UQ10: =UM10 -> 20 | XE10: Del Procedimiento de Construcción | ZH10: f'c = | ZI10: 200 | ZJ10: f"c = | ZK10: =ZI10*0.8*0.85 -> 136 | ZN10: Mu | ZO10: 0.639
AU11: carga viva | AZ11: 100 | BA11: kg | CK11: Distancia de nudo a carga puntual | CM11: =-1*(IF(CM24=0,0,IF(CL11=0,0,IF(CL12=0,0,IF(CL11=(CM24/2),CL12*CM24/8,CL12*CL11*((CM24-CL11)*(CM24-CL11))/(CM24*CM24)))))) -> 0 | CN11: =IF(CM24=0,0,IF(CL11=0,0,IF(CL12=0,0,IF(CL11=(CM24/2),CM11*-1,CL12*(CL11*CL11)*(CM24-CL11)/(CM24*CM24))))) -> 0 | CQ11: Distancia de nudo a carga puntual | CS11: =-1*(IF(CS24=0,0,IF(CR11=0,0,IF(CR12=0,0,IF(CR11=(CS24/2),CR12*CS24/8,CR12*CR11*((CS24-CR11)*(CS24-CR11))/(CS24*CS24)))))) -> 0 | CT11: =IF(CS24=0,0,IF(CR11=0,0,IF(CR12=0,0,IF(CR11=(CS24/2),CS11*-1,CR12*(CR11*CR11)*(CS24-CR11)/(CS24*CS24))))) -> 0 | DO11: q ro min= | DP11: =DP9*DN8/DP7 -> 0.068599434 | DQ11: =DP11*(1-(0.5*DP11)) -> 0.066246493 | DS11: Ro real | DT11: =DT10*DP7/DN8 -> 0.0010252407 | EC11: Distancia de nudo a carga puntual | EE11: =-1*(IF(EE24=0,0,IF(ED11=0,0,IF(ED12=0,0,IF(ED11=(EE24/2),ED12*EE24/8,ED12*ED11*((EE24-ED11)*(EE24-ED11))/(EE24*EE24)))))) -> 0 | EF11: =IF(EE24=0,0,IF(ED11=0,0,IF(ED12=0,0,IF(ED11=(EE24/2),EE11*-1,ED12*(ED11*ED11)*(EE24-ED11)/(EE24*EE24))))) -> 0 | EI11: Distancia de nudo a carga puntual | EK11: =-1*(IF(EK24=0,0,IF(EJ11=0,0,IF(EJ12=0,0,IF(EJ11=(EK24/2),EJ12*EK24/8,EJ12*EJ11*((EK24-EJ11)*(EK24-EJ11))/(EK24*EK24)))))) -> 0 | EL11: =IF(EK24=0,0,IF(EJ11=0,0,IF(EJ12=0,0,IF(EJ11=(EK24/2),EK11*-1,EJ12*(EJ11*EJ11)*(EK24-EJ11)/(EK24*EK24))))) -> 0 | EO11: Distancia de nudo a carga puntual | EQ11: =-1*(IF(EQ24=0,0,IF(EP11=0,0,IF(EP12=0,0,IF(EP11=(EQ24/2),EP12*EQ24/8,EP12*EP11*((EQ24-EP11)*(EQ24-EP11))/(EQ24*EQ24)))))) -> 0 | ER11: =IF(EQ24=0,0,IF(EP11=0,0,IF(EP12=0,0,IF(EP11=(EQ24/2),EQ11*-1,EP12*(EP11*EP11)*(EQ24-EP11)/(EQ24*EQ24))))) -> 0 | FA11: fy = | FB11: =DN8 -> 6000 | FC11: Ro max = | FD11: =0.75*(FD10/FB11)*(4800/(6000+FB11)) -> 0.0068 | FH11: =FC69 -> 0.047189738 | FQ11: Distancia de nudo a carga puntual | FS11: =-1*(IF(FS24=0,0,IF(FR11=0,0,IF(FR12=0,0,IF(FR11=(FS24/2),FR12*FS24/8,FR12*FR11*((FS24-FR11)*(FS24-FR11))/(FS24*FS24)))))) -> 0 | FT11: =IF(FS24=0,0,IF(FR11=0,0,IF(FR12=0,0,IF(FR11=(FS24/2),FS11*-1,FR12*(FR11*FR11)*(FS24-FR11)/(FS24*FS24))))) -> 0 | FW11: Distancia de nudo a carga puntual | FY11: =-1*(IF(FY24=0,0,IF(FX11=0,0,IF(FX12=0,0,IF(FX11=(FY24/2),FX12*FY24/8,FX12*FX11*((FY24-FX11)*(FY24-FX11))/(FY24*FY24)))))) -> 0 | FZ11: =IF(FY24=0,0,IF(FX11=0,0,IF(FX12=0,0,IF(FX11=(FY24/2),FY11*-1,FX12*(FX11*FX11)*(FY24-FX11)/(FY24*FY24))))) -> 0 | GH11: fy = | GI11: 4200 | GJ11: Ro max = | GK11: =0.75*(GK10/GI11)*(4800/(6000+GI11)) -> 0.011428571 | GO11: =GJ69 -> 0.047189738 | GT11: Rtot= | GU11: =GU9+GU10 -> -8.1797986 | HA11: Rtot= | HB11: =HB9+HB10 -> -9.8872087 | HD11: d prop = | HE11: =GV34 -> 35 | HF11: d ro max | HG11: =SQRT((HE13)/(HE8*HG6*HE12*HH9)) -> 25.985619 | HH11: =IF(HG11<HE11,"pasa el peralte con ro max","no pasa el peralte") -> pasa el peralte con ro max | HJ11: As | HK11: =IF(HK10<HG8,HG8*HE11*HE12,IF(HK10>HG7,"peralte no pasa",HK10*HE12*HE11)) -> 4.7748526 | HL11: momento | HV11: Rtot= | HW11: =HW9+HW10 -> -5.2412533 | IC11: Rtot= | ID11: =ID9+ID10 -> -4.7547467 | IF11: d prop = | IG11: =HX34 -> 30 | IH11: d ro max | II11: =SQRT((IG13)/(IG8*II6*IG12*IJ9)) -> 17.823471 | IJ11: =IF(II11<IG11,"pasa el peralte con ro max","no pasa el peralte") -> pasa el peralte con ro max | IL11: As | IM11: =IF(IM10<II8,II8*IG11*IG12,IF(IM10>II7,"peralte no pasa",IM10*IG12*IG11)) -> 1.9597487 | IN11: momento | IZ11: Rx = Mu / (Fr h^2 b f"c) | JB11: =HN34/(0.9*HN32*HN32*HN33*JA8) -> 1.4353174 | JI11: Rx = Mu / (Fr h^2 b f"c) | JK11: =JB31*100000/(0.9*JA27*JA27*JB27*JJ8) -> 1.068561 | KN11: 0 | KO11: 0 | KP11: 0 | KR11: 0 | KS11: 0 | KT11: 0 | KU11: =KN13 -> 0 | KV11: =KO13 -> 0 | KW11: 0 | KX11: 0 | KY11: =IF(KW11=0,"",KX11/KW11) | KZ11: =KX11+KW11 -> 0 | LA11: 0 | LB11: =IF(KZ11=0,"",IF(LA11>KZ11,"pasa","no pasa")) | LD11: =KR13 -> 0 | LE11: =KS13 -> 0 | LF11: 0 | LG11: 0 | LH11: =IF(LF11=0,"",LG11/LF11) | LI11: =LG11+LF11 -> 0 | LJ11: 0 | LK11: =IF(LI11=0,"",IF(LJ11>LI11,"pasa","no pasa")) | LM11: Rtot= | LN11: =LN9+LN10 -> -5.3114241 | LT11: Rtot= | LU11: =LU9+LU10 -> -6.7108595 | LW11: d prop = | LX11: =LO34 -> 45 | LY11: d ro max | LZ11: =SQRT((LX13)/(LX8*LZ6*LX12*MA9)) -> 16.449247 | MA11: =IF(LZ11<LX11,"pasa el peralte con ro max","no pasa el peralte") -> pasa el peralte con ro max | MC11: As | MD11: =IF(MD10<LZ8,LZ8*LX11*LX12,IF(MD10>LZ7,"peralte no pasa",MD10*LX12*LX11)) -> 2.9987753 | ME11: momento | MQ11: Rx = Mu / (Fr h^2 b f"c) | MS11: =MG34/(0.9*MG32*MG32*MG33*MR8) -> 0.82069038 | MW11: Rtot= | MX11: =MX9+MX10 -> -5.5024955 | ND11: Rtot= | NE11: =NE9+NE10 -> -6.5197881 | NG11: d prop = | NH11: =MY34 -> 45 | NI11: d ro max | NJ11: =SQRT((NH13)/(NH8*NJ6*NH12*NK9)) -> 15.071177 | NK11: =IF(NJ11<NH11,"pasa el peralte con ro max","no pasa el peralte") -> pasa el peralte con ro max | NM11: As | NN11: =IF(NN10<NJ8,NJ8*NH11*NH12,IF(NN10>NJ7,"peralte no pasa",NN10*NH12*NH11)) -> 2.9987753 | NO11: momento | OA11: Rx = Mu / (Fr h^2 b f"c) | OC11: =NQ34/(0.9*NQ32*NQ32*NQ33*OB8) -> 2.270187 | OG11: momento | OS11: Rx = Mu / (Fr h^2 b f"c) | OU11: =OI34/(0.9*OI32*OI32*OI33*OT8) -> 0.12276255 | PH11: Rtot= | PI11: =PI9+PI10 -> 8.7847196 | PO11: Rtot= | PP11: =PP9+PP10 -> -12.839259 | PR11: d prop = | PS11: =PJ34 -> 45 | PT11: d ro max | PU11: =SQRT((PS13)/(PS8*PU6*PS12*PV9)) -> 27.631292 | PV11: =IF(PU11<PS11,"pasa el peralte con ro max","no pasa el peralte") -> pasa el peralte con ro max | PX11: As | PY11: =IF(PY10<PU8,PU8*PS11*PS12,IF(PY10>PU7,"peralte no pasa",PY10*PS12*PS11)) -> 5.6108627 | PZ11: momento | QL11: Rx = Mu / (Fr h^2 b f"c) | QN11: =QB31/(0.9*QB29*QB29*QB30*QM8) -> 0.002594255 | QR11: momento | RD11: Rx = Mu / (Fr h^2 b f"c) | RF11: =QT34/(0.9*QT32*QT32*QT33*RE8) -> 0.4598374 | SB11: =RJ13 -> 294.93419 | SG11: 5 | SH11: nominal | SI11: diam. cm's | SJ11: área cm^2 | SL11: S req | SM11: =SM10/2.31 -> 366.18467 | SP11: Distancia de nudo a carga puntual | SR11: =-1*(IF(SR24=0,0,IF(SQ11=0,0,IF(SQ12=0,0,IF(SQ11=(SR24/2),SQ12*SR24/8,SQ12*SQ11*((SR24-SQ11)*(SR24-SQ11))/(SR24*SR24)))))) -> 0 | SS11: =IF(SR24=0,0,IF(SQ11=0,0,IF(SQ12=0,0,IF(SQ11=(SR24/2),SR11*-1,SQ12*(SQ11*SQ11)*(SR24-SQ11)/(SR24*SR24))))) -> 0 | SV11: Distancia de nudo a carga puntual | SX11: =-1*(IF(SX24=0,0,IF(SW11=0,0,IF(SW12=0,0,IF(SW11=(SX24/2),SW12*SX24/8,SW12*SW11*((SX24-SW11)*(SX24-SW11))/(SX24*SX24)))))) -> 0 | SY11: =IF(SX24=0,0,IF(SW11=0,0,IF(SW12=0,0,IF(SW11=(SX24/2),SX11*-1,SW12*(SW11*SW11)*(SX24-SW11)/(SX24*SX24))))) -> 0 | TG11: fy = | TH11: 4200 | TI11: Ro max = | TJ11: =0.75*(TJ10/TH11)*(4800/(6000+TH11)) -> 0.014285714 | TN11: =TH69 -> 0.065714514 | TW11: . \/ selecciona varilla | UD11: Rx = Mu / (Fr h^2 b f"c) | UF11: =UH5*100000/(0.9*UB14*UB14*UB15*UE8) -> -0.13279816 | WM11: Muros Estructurales Niveles 3 (ME3) | WV11: Columnas C1 50 x 30 | XE11: Se procurara colar Monolíticamente Trabes Losas y Columnas en cada nivel. Particularmente en el nivel sótano para evitar juntas frías que conduzcan a filtraciones. Se empleara Block dala para colocar la varilla horizontal . Para ganchos y traslapes referirse a manual ACI. | XY11: Espaciamiento a 20 cm al centro | ZH11: fy = | ZI11: 4200 | ZJ11: Ro max = | ZK11: =0.75*(ZK10/ZI11)*(4800/(6000+ZI11)) -> 0.011428571 | ZO11: =ZI68 -> 0.053644763
AL12: Paralelamente encontramos solo peso volumétrico en dos de los cuatro sondeos así que emplearemos el mayor y el menos cando sean mas desfavorables a la estabilidad de la estructura como marca la norma. | AU12: carga muerta | AW12: losa + acabados | AZ12: =AZ9+100 -> 315 | BA12: kg | CK12: Carga Puntual | CQ12: Carga Puntual | DF12: 67 | DJ12: =67/2.54 -> 26.377953 | DM12: d prop = | DN12: =DE38 -> 12.974155 | DO12: d ro max | DP12: =SQRT((DN14)/(DN9*DP7*DN13*DQ10)) -> 5.7297682 | DQ12: =IF(DP12<DN12,"pasa el peralte con ro max","no pasa el peralte") -> pasa el peralte con ro max | DS12: As | DT12: =IF(DT11<DP9,DP9*DN12*DN13,IF(DT11>DP8,"peralte no pasa",DT11*DN13*DN12)) -> 1.3516433 | EC12: Carga Puntual | EI12: Carga Puntual | EO12: Carga Puntual | EP12: =3*2.65*CP6 -> 0 | FA12: Fr = | FB12: =DN9 -> 0.8 | FC12: Ro min= | FD12: =0.8*(SQRT(FD10))/FB11 -> 0.0015549205 | FH12: =FC70 -> 0.047189738 | FQ12: Carga Puntual | FW12: Carga Puntual | GH12: Fr = | GI12: 0.8 | GJ12: Ro min= | GK12: =0.8*(SQRT(GK10))/GI11 -> 0.002221315 | GO12: =GJ70 -> 0.047189738 | HD12: ancho b= | HE12: =GV35 -> 25 | HF12: d ro min | HG12: =SQRT((HE13)/(HE8*HG6*HE12*HH10)) -> 54.430502 | HH12: =IF(HG12<HE11,"pasa el peralte con ro min","no pasa el peralte") -> no pasa el peralte | HJ12: as | HK12: =IF(HD16=HD17,HG17,IF(HD16=HD18,HG18,IF(HD16=HD19,HG19,IF(HD16=HD20,HG20,IF(HD16=HD21,HG21,IF(HD16=HD22,HG22,"escribe as")))))) -> 1.2667717 | HL12: =HL10+HL8 -> -1.7718385 | IF12: ancho b= | IG12: =HX35 -> 20 | IH12: d ro min | II12: =SQRT((IG13)/(IG8*II6*IG12*IJ10)) -> 37.333746 | IJ12: =IF(II12<IG11,"pasa el peralte con ro min","no pasa el peralte") -> no pasa el peralte | IL12: as | IM12: =IF(IF16=IF17,II17,IF(IF16=IF18,II18,IF(IF16=IF19,II19,IF(IF16=IF20,II20,IF(IF16=IF21,II21,IF(IF16=IF22,II22,"escribe as")))))) -> 1.2667717 | IN12: =IN10+IN8 -> -1.7718385 | KN12: 0 | KO12: 0 | KP12: 0 | KR12: 0 | KS12: 0 | KT12: 0 | KU12: =KN14 -> 0 | KV12: =KO14 -> 0 | KW12: 0 | KX12: 0 | KY12: =IF(KW12=0,"",KX12/KW12) | KZ12: =KX12+KW12 -> 0 | LA12: 0 | LB12: =IF(KZ12=0,"",IF(LA12>KZ12,"pasa","no pasa")) | LD12: =KR14 -> 0 | LE12: =KS14 -> 0 | LF12: 0 | LG12: 0 | LH12: =IF(LF12=0,"",LG12/LF12) | LI12: =LG12+LF12 -> 0 | LJ12: 0 | LK12: =IF(LI12=0,"",IF(LJ12>LI12,"pasa","no pasa")) | LW12: ancho b= | LX12: =LO35 -> 30 | LY12: d ro min | LZ12: =SQRT((LX13)/(LX8*LZ6*LX12*MA10)) -> 34.455242 | MA12: =IF(LZ12<LX11,"pasa el peralte con ro min","no pasa el peralte") -> pasa el peralte con ro min | MC12: as | MD12: =IF(LW16=LW17,LZ17,IF(LW16=LW18,LZ18,IF(LW16=LW19,LZ19,IF(LW16=LW20,LZ20,IF(LW16=LW21,LZ21,IF(LW16=LW22,LZ22,"escribe as")))))) -> 1.2667717 | ME12: =ME10+ME8 -> -2.0802045 | NG12: ancho b= | NH12: =MY35 -> 30 | NI12: d ro min | NJ12: =SQRT((NH13)/(NH8*NJ6*NH12*NK10)) -> 31.568683 | NK12: =IF(NJ12<NH11,"pasa el peralte con ro min","no pasa el peralte") -> pasa el peralte con ro min | NM12: as | NN12: =IF(NG16=NG17,NJ17,IF(NG16=NG18,NJ18,IF(NG16=NG19,NJ19,IF(NG16=NG20,NJ20,IF(NG16=NG21,NJ21,IF(NG16=NG22,NJ22,"escribe as")))))) -> 1.2667717 | NO12: =NO10+NO8 -> -4.6881876 | OG12: =OG10+OG8 -> -2.0802045 | PR12: ancho b= | PS12: =PJ35 -> 30 | PT12: d ro min | PU12: =SQRT((PS13)/(PS8*PU6*PS12*PV10)) -> 61.083688 | PV12: =IF(PU12<PS11,"pasa el peralte con ro min","no pasa el peralte") -> no pasa el peralte | PX12: as | PY12: =IF(PR16=PR17,PU17,IF(PR16=PR18,PU18,IF(PR16=PR19,PU19,IF(PR16=PR20,PU20,IF(PR16=PR21,PU21,IF(PR16=PR22,PU22,"escribe as")))))) -> 1.2667717 | PZ12: =PZ10+PZ8 -> 0.050660131 | QR12: =QR10+QR8 -> -8.5831379 | SE12: 100 | SG12: 2 | SH12: #2 - 1/4 | SI12: =2.54*0.25 -> 0.635 | SJ12: =3.1416*((SI12/2)^2) -> 0.31669292 | SL12: Z req | SM12: =SM10/(2.53*0.9) -> 371.4917 | SP12: Carga Puntual | SV12: Carga Puntual | TG12: Fr = | TH12: 0.8 | TI12: Ro min= | TJ12: =0.8*(SQRT(TJ10))/TH11 -> 0.0024835057 | TN12: =TH70 -> 0.065714514 | TR12: =100 -> 100 | TW12: 5 | TX12: nominal | TY12: diam. cm's | TZ12: área cm^2 | WM12: Armado con celdas coladas @3er celda Varilla vertical #4 , varilla longitudinal @3 hiladas amarrada a las varillas verticales. Block 1 | WV12: Columna de 50 x 30 armada con 8 # 5 y Estrios #3 @ 20 cm al centro y @ 10 cm en cada 1/3 extremo. Todas se colocan con su Eje largo de Este a Oeste en el sentido de los marcos rigidos principales. Sobre eje X | XW12: C1 | XY12: C2 | YB12: arriostramiento lateral | ZH12: Fr = | ZI12: 0.8 | ZJ12: Ro min= | ZK12: =0.8*(SQRT(ZK10))/ZI11 -> 0.002221315 | ZO12: =ZI69 -> 0.053644763
AU13: viento | AZ13: 50 | BA13: kg | CK13: Distancia de nudo a carga puntual | CM13: =-1*(IF(CM24=0,0,IF(CL13=0,0,IF(CL14=0,0,IF(CL13=(CM24/2),CL14*CM24/8,CL14*CL13*((CM24-CL13)*(CM24-CL13))/(CM24*CM24)))))) -> 0 | CN13: =IF(CM24=0,0,IF(CL13=0,0,IF(CL14=0,0,IF(CL13=(CM24/2),CM13*-1,CL14*(CL13*CL13)*(CM24-CL13)/(CM24*CM24))))) -> 0 | CQ13: Distancia de nudo a carga puntual | CS13: =-1*(IF(CS24=0,0,IF(CR13=0,0,IF(CR14=0,0,IF(CR13=(CS24/2),CR14*CS24/8,CR14*CR13*((CS24-CR13)*(CS24-CR13))/(CS24*CS24)))))) -> 0 | CT13: =IF(CS24=0,0,IF(CR13=0,0,IF(CR14=0,0,IF(CR13=(CS24/2),CS13*-1,CR14*(CR13*CR13)*(CS24-CR13)/(CS24*CS24))))) -> 0 | DM13: ancho b= | DN13: 67 | DO13: d ro min | DP13: =SQRT((DN14)/(DN9*DP7*DN13*DQ11)) -> 11.241537 | DQ13: =IF(DP13<DN12,"pasa el peralte con ro min","no pasa el peralte") -> pasa el peralte con ro min | DS13: as | DT13: =IF(DM17=DM18,DP18,IF(DM17=DM19,DP19,IF(DM17=DM20,DP20,IF(DM17=DM21,DP21,IF(DM17=DM22,DP22,IF(DM17=DM23,DP23,"escribe as")))))) -> 0.49483268 | EC13: Distancia de nudo a carga puntual | EE13: =-1*(IF(EE24=0,0,IF(ED13=0,0,IF(ED14=0,0,IF(ED13=(EE24/2),ED14*EE24/8,ED14*ED13*((EE24-ED13)*(EE24-ED13))/(EE24*EE24)))))) -> 0 | EF13: =IF(EE24=0,0,IF(ED13=0,0,IF(ED14=0,0,IF(ED13=(EE24/2),EE13*-1,ED14*(ED13*ED13)*(EE24-ED13)/(EE24*EE24))))) -> 0 | EI13: Distancia de nudo a carga puntual | EK13: =-1*(IF(EK24=0,0,IF(EJ13=0,0,IF(EJ14=0,0,IF(EJ13=(EK24/2),EJ14*EK24/8,EJ14*EJ13*((EK24-EJ13)*(EK24-EJ13))/(EK24*EK24)))))) -> 0 | EL13: =IF(EK24=0,0,IF(EJ13=0,0,IF(EJ14=0,0,IF(EJ13=(EK24/2),EK13*-1,EJ14*(EJ13*EJ13)*(EK24-EJ13)/(EK24*EK24))))) -> 0 | EO13: Distancia de nudo a carga puntual | EQ13: =-1*(IF(EQ24=0,0,IF(EP13=0,0,IF(EP14=0,0,IF(EP13=(EQ24/2),EP14*EQ24/8,EP14*EP13*((EQ24-EP13)*(EQ24-EP13))/(EQ24*EQ24)))))) -> 0 | ER13: =IF(EQ24=0,0,IF(EP13=0,0,IF(EP14=0,0,IF(EP13=(EQ24/2),EQ13*-1,EP14*(EP13*EP13)*(EQ24-EP13)/(EQ24*EQ24))))) -> 0 | FA13: peso conc | FB13: =DN10 -> 2400 | FC13: q ro max= | FD13: =FD11*FB11/FD10 -> 0.3 | FE13: =FD13*(1-(0.5*FD13)) -> 0.255 | FG13: q real | FH13: =FC71 -> 0.047189738 | FQ13: Distancia de nudo a carga puntual | FS13: =-1*(IF(FS24=0,0,IF(FR13=0,0,IF(FR14=0,0,IF(FR13=(FS24/2),FR14*FS24/8,FR14*FR13*((FS24-FR13)*(FS24-FR13))/(FS24*FS24)))))) -> 0 | FT13: =IF(FS24=0,0,IF(FR13=0,0,IF(FR14=0,0,IF(FR13=(FS24/2),FS13*-1,FR14*(FR13*FR13)*(FS24-FR13)/(FS24*FS24))))) -> 0 | FW13: Distancia de nudo a carga puntual | FY13: =-1*(IF(FY24=0,0,IF(FX13=0,0,IF(FX14=0,0,IF(FX13=(FY24/2),FX14*FY24/8,FX14*FX13*((FY24-FX13)*(FY24-FX13))/(FY24*FY24)))))) -> 0 | FZ13: =IF(FY24=0,0,IF(FX13=0,0,IF(FX14=0,0,IF(FX13=(FY24/2),FY13*-1,FX14*(FX13*FX13)*(FY24-FX13)/(FY24*FY24))))) -> 0 | GH13: peso conc | GI13: 2400 | GJ13: q ro max= | GK13: =GK11*GI11/GK10 -> 0.35294118 | GL13: =GK13*(1-(0.5*GK13)) -> 0.29065744 | GN13: q real | GO13: =GJ71 -> 0.047189738 | HD13: Mmax | HE13: =ABS(HK6*100000) -> 533846.59 | HJ13: # varillas | HK13: =ROUNDUP((HK11/HK12),0) -> 4 | HL13: total | IF13: Mmax | IG13: =ABS(IM6*100000) -> 200920.81 | IL13: # varillas | IM13: =ROUNDUP((IM11/IM12),0) -> 2 | IN13: total | IZ13: Q= | JA13: 1.2 | JC13: Q= As fy / (bh f"c) | JI13: Q= | JJ13: 1.8 | JL13: Q= As fy / (bh f"c) | KN13: 0 | KO13: 0 | KP13: 0 | KR13: 0 | KS13: 0 | KT13: 0 | KU13: =KN15 -> 0 | KV13: =KO15 -> 0 | KW13: 0 | KX13: 0 | KY13: =IF(KW13=0,"",KX13/KW13) | KZ13: =KX13+KW13 -> 0 | LA13: 0 | LB13: =IF(KZ13=0,"",IF(LA13>KZ13,"pasa","no pasa")) | LD13: =KR15 -> 0 | LE13: =KS15 -> 0 | LF13: 0 | LG13: 0 | LH13: =IF(LF13=0,"",LG13/LF13) | LI13: =LG13+LF13 -> 0 | LJ13: 0 | LK13: =IF(LI13=0,"",IF(LJ13>LI13,"pasa","no pasa")) | LW13: Mmax | LX13: =ABS(MD6*100000) -> 256698.68 | MC13: # varillas | MD13: =ROUNDUP((MD11/MD12),0) -> 3 | ME13: total | MQ13: Q= | MR13: 1.2 | MT13: Q= As fy / (bh f"c) | NG13: Mmax | NH13: =ABS(NN6*100000) -> 215489.42 | NM13: # varillas | NN13: =ROUNDUP((NN11/NN12),0) -> 3 | NO13: total | OA13: Q= | OB13: 1.2 | OD13: Q= As fy / (bh f"c) | OG13: total | OS13: Q= | OT13: 1.2 | OV13: Q= As fy / (bh f"c) | OY13: =OP32 -> 229.62153 | PB13: =OI32+OI31 -> 100 | PC13: =OY13 -> 229.62153 | PF13: =PB13 -> 100 | PR13: Mmax | PS13: =ABS(PY6*100000) -> 905407.29 | PX13: # varillas | PY13: =ROUNDUP((PY11/PY12),0) -> 5 | PZ13: total | QL13: Q= | QM13: 1.2 | QO13: Q= As fy / (bh f"c) | QR13: total | RD13: Q= | RE13: 1.2 | RG13: Q= As fy / (bh f"c) | RJ13: =RA32 -> 294.93419 | RM13: =QT32+QT31 -> 100 | RN13: =RJ13 -> 294.93419 | RQ13: =RM13 -> 100 | RT13: Cargas Gravitacionales | SG13: 3 | SH13: #3 - 3/8 | SI13: =2.54*3/8 -> 0.9525 | SJ13: =3.1416*((SI13/2)^2) -> 0.71255906 | SP13: Distancia de nudo a carga puntual | SR13: =-1*(IF(SR24=0,0,IF(SQ13=0,0,IF(SQ14=0,0,IF(SQ13=(SR24/2),SQ14*SR24/8,SQ14*SQ13*((SR24-SQ13)*(SR24-SQ13))/(SR24*SR24)))))) -> 0 | SS13: =IF(SR24=0,0,IF(SQ13=0,0,IF(SQ14=0,0,IF(SQ13=(SR24/2),SR13*-1,SQ14*(SQ13*SQ13)*(SR24-SQ13)/(SR24*SR24))))) -> 0 | SV13: Distancia de nudo a carga puntual | SX13: =-1*(IF(SX24=0,0,IF(SW13=0,0,IF(SW14=0,0,IF(SW13=(SX24/2),SW14*SX24/8,SW14*SW13*((SX24-SW13)*(SX24-SW13))/(SX24*SX24)))))) -> 0 | SY13: =IF(SX24=0,0,IF(SW13=0,0,IF(SW14=0,0,IF(SW13=(SX24/2),SX13*-1,SW14*(SW13*SW13)*(SX24-SW13)/(SX24*SX24))))) -> 0 | TG13: peso conc | TH13: 2400 | TI13: q ro max= | TJ13: =TJ11*TH11/TJ10 -> 0.35294118 | TK13: =TJ13*(1-(0.5*TJ13)) -> 0.29065744 | TM13: q real | TN13: =TH71 -> 0.065714514 | TU13: 100 | TW13: 2 | TX13: #2 - 1/4 | TY13: =2.54*0.25 -> 0.635 | TZ13: =3.1416*((TY13/2)^2) -> 0.31669292 | UD13: Q= | UE13: 1.2 | UG13: Q= As fy / (bh f"c) | UJ13: =UN13 -> 100 | UM13: =UM10 -> 20 | UN13: =UP7 -> 100 | UQ13: =UM13 -> 20 | ZH13: peso conc | ZI13: 2400 | ZJ13: q ro max= | ZK13: =ZK11*ZI11/ZK10 -> 0.35294118 | ZL13: =ZK13*(1-(0.5*ZK13)) -> 0.29065744 | ZN13: q real | ZO13: =ZI70 -> 0.053644763
AU14: lluvia | AW14: I cm | AZ14: 10 | BA14: kg | CK14: Carga Puntual | CQ14: Carga Puntual | DI14: 5 | DJ14: =12/2.54 -> 4.7244094 | DM14: Mmax | DN14: =ABS(DT7*100000) -> 61026.434 | DS14: # varillas | DT14: =ROUNDUP((DT12/DT13),0) -> 3 | EC14: Carga Puntual | EI14: Carga Puntual | EO14: Carga Puntual | FC14: q ro min= | FD14: =FD12*FB11/FD10 -> 0.068599434 | FE14: =FD14*(1-(0.5*FD14)) -> 0.066246493 | FG14: Ro real | FH14: =FH13*FD10/FB11 -> 0.0010696341 | FQ14: Carga Puntual | FW14: Carga Puntual | GJ14: q ro min= | GK14: =GK12*GI11/GK10 -> 0.068599434 | GL14: =GK14*(1-(0.5*GK14)) -> 0.066246493 | GN14: Ro real | GO14: =GO13*GK10/GI11 -> 0.0015280487 | KN14: 0 | KO14: 0 | KP14: 0 | KR14: 0 | KS14: 0 | KT14: 0 | KU14: =KN16 -> 0 | KV14: =KO16 -> 0 | KW14: 0 | KX14: 0 | KY14: =IF(KW14=0,"",KX14/KW14) | KZ14: =KX14+KW14 -> 0 | LA14: 0 | LB14: =IF(KZ14=0,"",IF(LA14>KZ14,"pasa","no pasa")) | LD14: =KR16 -> 0 | LE14: =KS16 -> 0 | LF14: 0 | LG14: 0 | LH14: =IF(LF14=0,"",LG14/LF14) | LI14: =LG14+LF14 -> 0 | LJ14: 0 | LK14: =IF(LI14=0,"",IF(LJ14>LI14,"pasa","no pasa")) | SG14: 4 | SH14: #4 - 1/2 | SI14: =SI12*2 -> 1.27 | SJ14: =3.1416*((SI14/2)^2) -> 1.2667717 | SL14: d prop | SM14: 30 | SP14: Carga Puntual | SV14: Carga Puntual | TI14: q ro min= | TJ14: =TJ12*TH11/TJ10 -> 0.061357199 | TK14: =TJ14*(1-(0.5*TJ14)) -> 0.059474846 | TM14: Ro real | TN14: =TN13*TJ10/TH11 -> 0.0026598732 | TW14: 3 | TX14: #3 - 3/8 | TY14: =2.54*3/8 -> 0.9525 | TZ14: =3.1416*((TY14/2)^2) -> 0.71255906 | UB14: 30 | US14: 3 | UU14: P1 | VE14: =US14 -> 3 | WM14: Confianmiento especial para ME1 en Sotano | XN14: ME3 | XR14: MC | ZJ14: q ro min= | ZK14: =ZK12*ZI11/ZK10 -> 0.068599434 | ZL14: =ZK14*(1-(0.5*ZK14)) -> 0.066246493 | ZN14: Ro real | ZO14: =ZO13*ZK10/ZI11 -> 0.0017370685
AL15: Peso volumétrico Seco: medido | AU15: combinaciones de carga | CK15: Distancia de nudo a carga puntual | CM15: =-1*(IF(CM24=0,0,IF(CL15=0,0,IF(CL16=0,0,IF(CL15=(CM24/2),CL16*CM24/8,CL16*CL15*((CM24-CL15)*(CM24-CL15))/(CM24*CM24)))))) -> 0 | CN15: =IF(CM24=0,0,IF(CL15=0,0,IF(CL16=0,0,IF(CL15=(CM24/2),CM15*-1,CL16*(CL15*CL15)*(CM24-CL15)/(CM24*CM24))))) -> 0 | CQ15: Distancia de nudo a carga puntual | CS15: =-1*(IF(CS24=0,0,IF(CR15=0,0,IF(CR16=0,0,IF(CR15=(CS24/2),CR16*CS24/8,CR16*CR15*((CS24-CR15)*(CS24-CR15))/(CS24*CS24)))))) -> 0 | CT15: =IF(CS24=0,0,IF(CR15=0,0,IF(CR16=0,0,IF(CR15=(CS24/2),CS15*-1,CR16*(CR15*CR15)*(CS24-CR15)/(CS24*CS24))))) -> 0 | DR15: =DT14 -> 3 | DS15: Varilla | DT15: =IF(DM17=DM18,DN18,IF(DM17=DM19,DN19,IF(DM17=DM20,DN20,IF(DM17=DM21,DN21,IF(DM17=DM22,DN22,IF(DM17=DM23,DN23,"escribe as")))))) -> 5/16" | EC15: Distancia de nudo a carga puntual | EE15: =-1*(IF(EE24=0,0,IF(ED15=0,0,IF(ED16=0,0,IF(ED15=(EE24/2),ED16*EE24/8,ED16*ED15*((EE24-ED15)*(EE24-ED15))/(EE24*EE24)))))) -> 0 | EF15: =IF(EE24=0,0,IF(ED15=0,0,IF(ED16=0,0,IF(ED15=(EE24/2),EE15*-1,ED16*(ED15*ED15)*(EE24-ED15)/(EE24*EE24))))) -> 0 | EI15: Distancia de nudo a carga puntual | EK15: =-1*(IF(EK24=0,0,IF(EJ15=0,0,IF(EJ16=0,0,IF(EJ15=(EK24/2),EJ16*EK24/8,EJ16*EJ15*((EK24-EJ15)*(EK24-EJ15))/(EK24*EK24)))))) -> 0 | EL15: =IF(EK24=0,0,IF(EJ15=0,0,IF(EJ16=0,0,IF(EJ15=(EK24/2),EK15*-1,EJ16*(EJ15*EJ15)*(EK24-EJ15)/(EK24*EK24))))) -> 0 | EO15: Distancia de nudo a carga puntual | EQ15: =-1*(IF(EQ24=0,0,IF(EP15=0,0,IF(EP16=0,0,IF(EP15=(EQ24/2),EP16*EQ24/8,EP16*EP15*((EQ24-EP15)*(EQ24-EP15))/(EQ24*EQ24)))))) -> 0 | ER15: =IF(EQ24=0,0,IF(EP15=0,0,IF(EP16=0,0,IF(EP15=(EQ24/2),EQ15*-1,EP16*(EP15*EP15)*(EQ24-EP15)/(EQ24*EQ24))))) -> 0 | FA15: d prop = | FB15: =DN12 -> 12.974155 | FC15: d ro max | FD15: =SQRT((FB17)/(FB12*FD10*FB16*FE13)) -> 4.7798893 | FE15: =IF(FD15<FB15,"pasa el peralte con ro max","no pasa el peralte") -> pasa el peralte con ro max | FG15: As | FH15: =IF(FH14<FD12,FD12*FB15*FB16,IF(FH14>FD11,"peralte no pasa",FH14*FB16*FB15)) -> 1.3516433 | FQ15: Distancia de nudo a carga puntual | FS15: =-1*(IF(FS24=0,0,IF(FR15=0,0,IF(FR16=0,0,IF(FR15=(FS24/2),FR16*FS24/8,FR16*FR15*((FS24-FR15)*(FS24-FR15))/(FS24*FS24)))))) -> 0 | FT15: =IF(FS24=0,0,IF(FR15=0,0,IF(FR16=0,0,IF(FR15=(FS24/2),FS15*-1,FR16*(FR15*FR15)*(FS24-FR15)/(FS24*FS24))))) -> 0 | FW15: Distancia de nudo a carga puntual | FY15: =-1*(IF(FY24=0,0,IF(FX15=0,0,IF(FX16=0,0,IF(FX15=(FY24/2),FX16*FY24/8,FX16*FX15*((FY24-FX15)*(FY24-FX15))/(FY24*FY24)))))) -> 0 | FZ15: =IF(FY24=0,0,IF(FX15=0,0,IF(FX16=0,0,IF(FX15=(FY24/2),FY15*-1,FX16*(FX15*FX15)*(FY24-FX15)/(FY24*FY24))))) -> 0 | GH15: d prop = | GI15: =DN12 -> 12.974155 | GJ15: d ro max | GK15: =SQRT((GI17)/(GI12*GK10*GI16*GL13)) -> 5.479027 | GL15: =IF(GK15<GI15,"pasa el peralte con ro max","no pasa el peralte") -> pasa el peralte con ro max | GN15: As | GO15: =IF(GO14<GK12,GK12*GI15*GI16,IF(GO14>GK11,"peralte no pasa",GO14*GI16*GI15)) -> 1.930919 | HD15: . \/ selecciona varilla | HL15: 3 | IF15: . \/ selecciona varilla | IN15: 3 | IZ15: As= | JA15: =JA13*(HN33*HN32*JA8)/JD5 -> 3.0304576 | JI15: As= | JJ15: =JJ13*(JB27*JA27*JJ8)/JM5 -> 4.5456865 | JL15: Ro | JM15: =JJ13*JJ8/JM5 -> 0.0060609153 | JN15: =IF(JM15<HP28,IF(JM15>HP29,"pasa","no pasa"),"no pasa") -> pasa | KN15: 0 | KO15: 0 | KP15: 0 | KR15: 0 | KS15: 0 | KT15: 0 | KU15: =KN17 -> 0 | KV15: =KO17 -> 0 | KW15: 0 | KX15: 0 | KY15: =IF(KW15=0,"",KX15/KW15) | KZ15: =KX15+KW15 -> 0 | LA15: 0 | LB15: =IF(KZ15=0,"",IF(LA15>KZ15,"pasa","no pasa")) | LW15: . \/ selecciona varilla | ME15: =ES15 -> 0 | MQ15: As= | MR15: =MR13*(MG33*MG32*MR8)/MU5 -> 3.0910668 | NG15: . \/ selecciona varilla | NO15: 0 | OA15: As= | OB15: =OB13*(NQ33*NQ32*OB8)/OE5 -> 3.0910668 | OG15: =ME15 -> 0 | OS15: As= | OT15: =OT13*(OI33*OI32*OT8)/OW5 -> 6.5255854 | PR15: . \/ selecciona varilla | PZ15: =HL15 -> 3 | QL15: As= | QM15: =QM13*(QB30*QB29*QM8)/QP5 -> 6.5255854 | QR15: =PZ15 -> 3 | RD15: As= | RE15: =RE13*(QT33*QT32*RE8)/RH5 -> 6.5255854 | SG15: 5 | SH15: #5 - 5/8 | SI15: =2.54*5/8 -> 1.5875 | SJ15: =3.1416*((SI15/2)^2) -> 1.9793307 | SL15: A req | SM15: =SM11/(SM14) -> 12.206156 | SP15: Distancia de nudo a carga puntual | SR15: =-1*(IF(SR24=0,0,IF(SQ15=0,0,IF(SQ16=0,0,IF(SQ15=(SR24/2),SQ16*SR24/8,SQ16*SQ15*((SR24-SQ15)*(SR24-SQ15))/(SR24*SR24)))))) -> 0 | SS15: =IF(SR24=0,0,IF(SQ15=0,0,IF(SQ16=0,0,IF(SQ15=(SR24/2),SR15*-1,SQ16*(SQ15*SQ15)*(SR24-SQ15)/(SR24*SR24))))) -> 0 | SV15: Distancia de nudo a carga puntual | SX15: =-1*(IF(SX24=0,0,IF(SW15=0,0,IF(SW16=0,0,IF(SW15=(SX24/2),SW16*SX24/8,SW16*SW15*((SX24-SW15)*(SX24-SW15))/(SX24*SX24)))))) -> 0 | SY15: =IF(SX24=0,0,IF(SW15=0,0,IF(SW16=0,0,IF(SW15=(SX24/2),SX15*-1,SW16*(SW15*SW15)*(SX24-SW15)/(SX24*SX24))))) -> 0 | TG15: d prop = | TH15: 25 | TI15: d ro max | TJ15: =SQRT((TH17)/(TH12*TJ10*TH16*TK13)) -> 12.399423 | TK15: =IF(TJ15<TH15,"pasa el peralte con ro max","no pasa el peralte") -> pasa el peralte con ro max | TM15: As | TN15: =IF(TN14<TJ12,TJ12*TH15*TH16,IF(TN14>TJ11,"peralte no pasa",TN14*TH16*TH15)) -> 6.649683 | TW15: 4 | TX15: #4 - 1/2 | TY15: =TY13*2 -> 1.27 | TZ15: =3.1416*((TY15/2)^2) -> 1.2667717 | UB15: 30 | UD15: As= | UE15: =UE13*(UB15*UB14*UE8)/(ABS(UH5)*100000) -> 0.33467666 | VD15: =VE14-VD17 -> 1.7044057 | VH15: =VF22-VC16 -> -3.6774192 | WE15: Edificio 1 | WM15: En el Sotano los ME1 se confinaran con tres cadenas de 30 x 20 de concreto armados con 2 varillas #4 en cada lecho y Estribos #3 @ 15cm | WV15: Columnas C2 30x30 | XE15: Del Sotano y Losa de Cimentacion | ZH15: d prop = | ZI15: 10 | ZJ15: d ro max | ZK15: =SQRT((ZO10*10000)/(ZI12*ZK10*ZI16*ZL13)) -> 1.4214947 | ZL15: =IF(ZK15<ZI15,"pasa el peralte con ro max","no pasa el peralte") -> pasa el peralte con ro max | ZN15: As | ZO15: =IF(ZO14<ZK12,ZK12*ZI15*ZI16,IF(ZO14>ZK11,"peralte no pasa",ZO14*ZI16*ZI15)) -> 2.221315
